Workbook

Sheet Kiểm toán trong ngày
A1: KIỂM TOÁN TRONG NGÀY :
A2: TIỀN KÉT | B2: 1581640 | C2: CHI
A3: DOANH THU | B3: 0 | C3: SỐ TIỀN | D3: NƠI CHI
A4: TỔNG TIỀN | B4: =SUM(B2:B3) -> 1581640
A5: SHIP | B5: 0
A6: SHIP BƯU ĐIỆN | B6: 0
A7: TRẢ HÀNG | B7: 0
A8: TT ĐIỂM | B8: 0
A9: TỔNG CHI | B9: =SUM(C4:C12) -> 0
A10: TỔNG TIỀN MẶT | B10: 0
A11: KHÁCH CK : | B11: 0
A12: CHÊNH LỆCH | B12: =B4-B5-B6-B7-B8-B9-B10-B11 -> 1581640
A15: KIỂM TOÁN TRONG NGÀY :
A16: TIỀN KÉT | C16: CHI
A17: DOANH THU | C17: SỐ TIỀN | D17: NƠI CHI
A18: TỔNG TIỀN
A19: SHIP
A20: SHIP BƯU ĐIỆN
A21: TRẢ HÀNG
A22: TT ĐIỂM
A23: TỔNG CHI
A24: TỔNG TIỀN MẶT
A25: KHÁCH CK :
A26: CHÊNH LỆCH

Sheet Chi tiết_2023_Mẫu
A1: CHI | B1: CHI TIẾT | C1: MỤC | E1: TỔNG THEO MỤC
A2: 45231 | E2: 食材 | F2: =SUMIF($C$3:$C$165,"=食材",$A$3:$A$165) -> 0 | G2: =SUM(F2:F8) -> 0
E3: 消耗品 | F3: =SUMIF($C$3:$C$165,"=消耗品",$A$3:$A$165) -> 0
E4: 家賃 | F4: =SUMIF($C$3:$C$165,"=家賃",$A$3:$A$165) -> 0
E5: 水代 | F5: =SUMIF($C$3:$C$165,"=水代",$A$3:$A$165) -> 0
E6: 電気代 | F6: =SUMIF($C$3:$C$165,"=電気代",$A$3:$A$165) -> 0
E7: 米 | F7: =SUMIF($C$3:$C$165,"=米",$A$3:$A$165) -> 0
A8: =SUM(A3:A7) -> 0 | E8: その他 | F8: =SUMIF($C$3:$C$165,"=その他",$A$3:$A$165) -> 0

Sheet Báo cáo tháng_Mẫu
A1: 日付 | C1: 売上 | D1: 支出 | E1: 入金 | F1: 不足 | G1: デリバリ | H1: 累計 | I1: 配達 | J1: 数 | L1: BÁO CÁO THÁNG
A2: 45139 | B2: 火 | C2: 388063 | D2: 91821 | E2: =C2-D2 -> 296242 | F2: -420 | G2: 31072 | H2: =E2+F2 -> 295822 | I2: 124532 | J2: 11 | L2: THU
A3: 45140 | B3: 水 | C3: 224971 | D3: 350405 | E3: =C3-D3 -> -125434 | F3: -202 | G3: 0 | H3: =H2+E3+F3 -> 170186 | I3: 0 | J3: 0 | L3: TỔNG | M3: SHIP BD | N3: SHIP | O3: Chênh lệch | P3: THANH TOÁN POINT
A4: 45141 | B4: 木 | C4: 208043 | D4: 330427 | E4: =C4-D4 -> -122384 | F4: -108 | G4: 12412 | H4: =H3+E4+F4 -> 47694 | I4: 96212 | J4: 8 | L4: =C33 -> 12758842 | M4: =G33 -> 559742 | N4: =I33 -> 5015906 | O4: =F33 -> -5934 | P4: 48431
A5: 45142 | B5: 金 | C5: 602364 | D5: 355522 | E5: =C5-D5 -> 246842 | F5: -417 | G5: 26408 | H5: =H4+E5+F5 -> 294119 | I5: 103472 | J5: 7 | M5: =M4/L4 -> 0.043870909 | N5: =N4/L4 -> 0.39313176 | O5: =O4/L4 -> -0.00046508923 | P5: =P4/L4 -> 0.0037958774
A6: 45143 | B6: 土 | C6: 464001 | D6: 89070 | E6: =C6-D6 -> 374931 | F6: -17 | G6: 0 | H6: =H5+E6+F6 -> 669033 | I6: 154763 | J6: 8 | L6: CHI
A7: 45144 | B7: 日 | C7: 288421 | D7: 33681 | E7: =C7-D7 -> 254740 | F7: -457 | G7: 0 | H7: =H6+E7+F7 -> 923316 | I7: 167530 | J7: 18 | L7: NHẬP HÀNG | M7: LƯƠNG | N7: TRẢ HÀNG | O7: Hỗ trợ ship BĐ | P7: TỔNG
A8: 45145 | B8: 月 | C8: 232104 | D8: 854538 | E8: =C8-D8 -> -622434 | F8: -729 | G8: 14272 | H8: =H7+E8+F8 -> 300153 | I8: 382120 | J8: 42 | L8: =D33 -> 11155239 | M8: =O16 -> 0 | N8: =Q19 -> 0 | O8: =M4*0.065 -> 36383.23 | P8: =SUM(L8:O8) -> 11191622
A9: 45146 | B9: 火 | C9: 353798 | D9: 197748 | E9: =C9-D9 -> 156050 | F9: -477 | G9: 12247 | H9: =H8+E9+F9 -> 455726 | I9: 112403 | J9: 6 | L9: LỢI NHUẬN | M9: =L4-P8 -> 1567219.8
A10: 45147 | B10: 水 | C10: 277820 | D10: 451545 | E10: =C10-D10 -> -173725 | F10: -327 | G10: 0 | H10: =H9+E10+F10 -> 281674 | I10: 0 | J10: 0 | L10: CHI TIẾT
A11: 45148 | B11: 木 | C11: 516600 | D11: 315292 | E11: =C11-D11 -> 201308 | F11: -410 | G11: 24720 | H11: =H10+E11+F11 -> 482572 | I11: 87650 | J11: 8 | L11: LƯƠNG - 給与
A12: 45149 | B12: 金 | C12: 889181 | D12: 215562 | E12: =C12-D12 -> 673619 | F12: -472 | G12: 10722 | H12: =H11+E12+F12 -> 1155719 | I12: 254690 | J12: 16 | L12: A. Giang | M12: A.Thái | N12: C.Hiền | O12: Nhàn | P12: Cưng | Q12: Nghĩa
A13: 45150 | B13: 土 | C13: 783523 | D13: 224503 | E13: =C13-D13 -> 559020 | F13: -311 | G13: 37489 | H13: =H12+E13+F13 -> 1714428 | I13: 210320 | J13: 15
A14: 45151 | B14: 日 | C14: 370475 | D14: 365034 | E14: =C14-D14 -> 5441 | F14: -774 | G14: 0 | H14: =H13+E14+F14 -> 1719095 | I14: 186542 | J14: 12 | L14: HỖ TRỢ
A15: 45152 | B15: 月 | C15: 456932 | D15: 982251 | E15: =C15-D15 -> -525319 | F15: -702 | G15: 17243 | H15: =H14+E15+F15 -> 1193074 | I15: 423412 | J15: 34
A16: 45153 | B16: 火 | C16: 430715 | D16: 81780 | E16: =C16-D16 -> 348935 | F16: -107 | G16: 15205 | H16: =H15+E16+F16 -> 1541902 | I16: 124328 | J16: 10 | L16: TỔNG | O16: =SUM(L13:Q13)+SUM(L15:Q15) -> 0
A17: 45154 | B17: 水 | C17: 463579 | D17: 78340 | E17: =C17-D17 -> 385239 | F17: 0 | G17: 45137 | H17: =H16+E17+F17 -> 1927141 | I17: 0 | J17: 0 | L17: CHI KHÁC - その他
A18: 45155 | B18: 木 | C18: 296872 | D18: 106660 | E18: =C18-D18 -> 190212 | F18: 0 | G18: 8882 | H18: =H17+E18+F18 -> 2117353 | I18: 192012 | J18: 12 | L18: TRẢ HÀNG | M18: HUỶ ĐƠN | N18: CHÊNH LỆCH | Q18: TỔNG
A19: 45156 | B19: 金 | C19: 584882 | D19: 768292 | E19: =C19-D19 -> -183410 | F19: 0 | G19: 38477 | H19: =H18+E19+F19 -> 1933943 | I19: 186312 | J19: 14 | Q19: =SUM(L19:P19) -> 0
A20: 45157 | B20: 土 | C20: 445331 | D20: 888408 | E20: =C20-D20 -> -443077 | F20: 0 | G20: 12712 | H20: =H19+E20+F20 -> 1490866 | I20: 146312 | J20: 11
A21: 45158 | B21: 日 | C21: 240602 | D21: 755010 | E21: =C21-D21 -> -514408 | F21: 0 | G21: 0 | H21: =H20+E21+F21 -> 976458 | I21: 78932 | J21: 8
A22: 45159 | B22: 月 | C22: 269988 | D22: 302465 | E22: =C22-D22 -> -32477 | F22: 0 | G22: 30904 | H22: =H21+E22+F22 -> 943981 | I22: 321267 | J22: 34
A23: 45160 | B23: 火 | C23: 320194 | D23: 115580 | E23: =C23-D23 -> 204614 | F23: 100 | G23: 12720 | H23: =H22+E23+F23 -> 1148695 | I23: 182712 | J23: 11
A24: 45161 | B24: 水 | C24: 227495 | D24: 268780 | E24: =C24-D24 -> -41285 | F24: -17 | G24: 0 | H24: =H23+E24+F24 -> 1107393 | I24: 0 | J24: 0
A25: 45162 | B25: 木 | C25: 320540 | D25: 191482 | E25: =C25-D25 -> 129058 | F25: -26 | G25: 42160 | H25: =H24+E25+F25 -> 1236425 | I25: 65901 | J25: 7
A26: 45163 | B26: 金 | C26: 870189 | D26: 590164 | E26: =C26-D26 -> 280025 | F26: -3 | G26: 22711 | H26: =H25+E26+F26 -> 1516447 | I26: 234518 | J26: 16
A27: 45164 | B27: 土 | C27: 584302 | D27: 258720 | E27: =C27-D27 -> 325582 | F27: -42 | G27: 28802 | H27: =H26+E27+F27 -> 1841987 | I27: 154302 | J27: 12
A28: 45165 | B28: 日 | C28: 586819 | D28: 839672 | E28: =C28-D28 -> -252853 | F28: 12 | G28: 0 | H28: =H27+E28+F28 -> 1589146 | I28: 183621 | J28: 12
A29: 45166 | B29: 月 | C29: 239366 | D29: 302670 | E29: =C29-D29 -> -63304 | F29: 0 | G29: 27720 | H29: =H28+E29+F29 -> 1525842 | I29: 532102 | J29: 44
A30: 45167 | B30: 火 | C30: 219358 | D30: 195331 | E30: =C30-D30 -> 24027 | F30: -12 | G30: 40007 | H30: =H29+E30+F30 -> 1549857 | I30: 117621 | J30: 10
A31: 45168 | B31: 水 | C31: 245142 | D31: 224636 | E31: =C31-D31 -> 20506 | F31: -7 | G31: 0 | H31: =H30+E31+F31 -> 1570356 | I31: 0 | J31: 0
A32: 45169 | B32: 木 | C32: 357172 | D32: 329850 | E32: =C32-D32 -> 27322 | F32: -9 | G32: 47720 | H32: =H31+E32+F32 -> 1597669 | I32: 192320 | J32: 17
A33: TỔNG | C33: =SUM(C2:C32) -> 12758842 | D33: =SUM(D2:D32) -> 11155239 | E33: =SUM(E2:E32) -> 1603603 | F33: =SUM(F2:F32) -> -5934 | G33: =SUM(G2:G32) -> 559742 | H33: =H32 -> 1597669 | I33: =SUM(I2:I32) -> 5015906 | J33: =SUM(J2:J32) -> 403

Sheet Mẫu 売り上げ
A1: 日付 | C1: 売上 | D1: CHI | E1: THU | F1: THIẾU | G1: SHIP BĐ | H1: LUỸ KẾ | I1: SHIP
A2: 45200 | B2: 水
A3: 45201 | B3: 木
A4: 45202 | B4: 金
A5: 45203 | B5: 土
A6: 45204 | B6: 日
A7: 45205 | B7: 月
A8: 45206 | B8: 火
A9: 45207 | B9: 水
A10: 45208 | B10: 木
A11: 45209 | B11: 金
A12: 45210 | B12: 土
A13: 45211 | B13: 日
... A31: 45229 | B31: 木

Sheet Hoá đơn_2023_5
A1: 日付： 01/05/2023(月曜日)
A2: 売り上げ
A3: 金額 | B3: 支払先 | C3: 詳細
A4: 20330 | B4: 三島株 | C4: 75kg Chân gà
A5: 21190 | B5: Kome | C5: G7(2x24)+Bột canh (2x40)+Miến (1x50)
A6: 29800 | B6: Sachan 株 | C6: 60kg Lạc
A7: 61179 | B7: THAK 株 | C7: Vịt (30) + Bắp heo (28.72)
A8: 44370 | B8: TRADIFOOD | C8: Gà ủ muối (50)
A9: 合計 | C9: =SUM(A4:A8) -> 176869
A10: チャージ
A11: ポイント支払い
A12: レジ
A13: 入金
A14: 不足
A16: 日付： 02/05/2023(火曜日)
A17: 売り上げ
A18: 金額 | B18: 支払先 | C18: 詳細
A19: 2110 | C19: Phí ship Mướp
A20: 9246 | B20: ナフコ | C20: Túi bóng
A21: 142240 | C21: Hoa quả tháng 4
A22: 96300 | B22: ベトナムハウス | C22: 50kg ớt + 30 cây Thăng Long
A23: 合計 | C23: =SUM(A19:A22) -> 249896
A24: チャージ
A25: ポイント支払い
A26: レジ
A27: 入金
A28: 不足
A30: 日付： 03/05/2023(水曜日)
A31: 売り上げ
A32: 金額 | B32: 支払先 | C32: 詳細
A33: 24441 | B33: フリチク | C33: 60 gà đông lạnh
A34: 550 | B34: ダイソ | C34: Băng keo
A35: 59170 | B35: Yến Ming 株 | C35: Rau
A36: 21450 | C36: 22 Gà ủ muối
A37: 2505 | C37: Phí ship Xoài
A38: 合計 | C38: =SUM(A33:A37) -> 108116
A39: チャージ
A40: ポイント支払い
A41: レジ
A42: 入金
A43: 不足
A45: 日付： 04/05/2023(木曜日)
A46: 売り上げ
A47: 金額 | B47: 支払先 | C47: 詳細
A48: 64000 | C48: 40 Gạo 10kg
A49: 1830 | C49: Phí ship mướp
A50: 7800 | B50: Oba | C50: 10kg Riềng + 10kg Lá chuối
A51: 24100 | B51: Kome 株 | C51: 20 Cá trắm + 60 Ram Hà Tĩnh
A52: 54973 | B52: THAK株 | C52: 45 Vịt
A53: 49600 | B53: Tonderu株 | C53: Dừa 36, Xoài 38, Hành Tím 18
A54: 22480 | B54: Sachan株 | C54: 96 Sữa ông thọ
A55: 88644 | B55: Vĩnh Phát 株 | C55: 144 Nam ngư, 144 Sữa bắp, 48 Kun cam, 96 Kun Dâu
A56: 合計 | C56: =SUM(A48:A55) -> 313427
A57: チャージ
A58: ポイント支払い
A59: レジ
A60: 入金
A61: 不足
A63: 日付： 05/05/2023(金曜日)
A64: 売り上げ
A65: 金額 | B65: 支払先 | C65: 詳細
A66: 800550 | B66: Vietcook
A67: 24200 | B67: Yến Minh 株 | C67: 50 bánh mỳ dừa, 15 sả
A68: 210850 | B68: Xuxu Group | C68: Thịt
A69: 126420 | B69: Diandi | C69: Chè + Bông lan trứng muối
A70: 66860 | B70: Mika Food | C70: 32.3 Ba chỉ + 32 Tim heo + 28 Khấu đuôi
A71: 42058 | B71: THAK株 | C71: 80 phở tươi + 36 Maggi + 50 chân gà + 10kg sả
A72: 60188 | B72: MUNDIAL | C72: 24 vịt + 160 Bò kho + 80 thịt kho tàu + 80 thịt nướng sả
A73: 63400 | B73: Tonderu | C73: 84kg Xoài
A74: 2220 | B74: Phí ship | C74: 14 gà
A75: 30196 | B75: Kome | C75: 24 Nước cốt, 24 bánh xẻo,24 bánh cuốn, 40 bún bò huế, 60 phồng tôm
A76: 合計 | C76: =SUM(A66:A75) -> 1426942
A77: チャージ
A78: ポイント支払い
A79: レジ
A80: 入金
A81: 不足
A83: 日付： 06/05/2023(土曜日)
A84: 売り上げ
A85: 金額 | B85: 支払先 | C85: 詳細
A86: 9000 | C86: 30 gạo nếp
A87: 1830 | B87: Phí ship | C87: Phí ship đu đủ
A88: 58600 | B88: MIRAI 株 | C88: 30 Bắp heo, 30kg Móng heo, 30 Bắp heo cắt lát
A89: 43860 | B89: Vĩnh Phát 株 | C89: 144 Chinsu
A90: 合計 | C90: =SUM(A86:A89) -> 113290
A91: チャージ
A92: ポイント支払い
A93: レジ
A94: 入金
A95: 不足
A97: 日付： 07/05/2023(日曜日)
A98: 売り上げ
A99: 金額 | B99: 支払先 | C99: 詳細
A100: 2505 | B100: Phí ship | C100: Phí ship Xoài
A101: 181790 | B101: 成富株 | C101: Tiền trứng Tháng 4
A102: 合計 | C102: =SUM(A100:A101) -> 184295
A103: チャージ
A104: ポイント支払い
A105: レジ
A106: 入金
...

Sheet 2022_11
B2: Tháng trước | C2: 400000
B4: 日付 | C4: Doanh thu | D4: Trả hàng | E4: Chi | F4: Chi tiết | G4: Tổng chi | H4: Luỹ kế
B5: 44866 | C5: 329962 | E5: 410024 | F5: Đồ khô | G5: =SUM(E5) -> 410024 | H5: =C2+C5 -> 729962
B6: 44867 | C6: 165251 | E6: 94550 | F6: Vietcook | G6: =SUM(E6) -> 94550 | H6: =H5+C6-D6-G6 -> 800663
B7: 44868 | C7: 365411 | E7: 135700 | F7: Vietcook | G7: =E7 -> 135700 | H7: =H6+C7-D7-G7 -> 1030374
B8: 44869 | C8: 342540 | E8: 92550 | F8: Vietcook | G8: =SUM(E8:E9) -> 114440 | H8: =H7+C8-D8-G8 -> 1258474
E9: 21890 | F9: Gà lộn 2 kiện | H9: =H8+C9-D9-G9 -> 1258474
B10: 44870 | C10: 343069 | G10: =E10 -> 0 | H10: =H9+C10-D10-G10 -> 1601543
B11: 44871 | C11: 458613 | E11: 64490 | F11: Vietcook | G11: =E11 -> 64490 | H11: =H10+C11-D11-G11 -> 1995666
B12: 44872 | C12: 314471 | E12: 163470 | F12: Vietcook | G12: =E12 -> 163470 | H12: =H11+C12-D12-G12 -> 2146667
E13: 544817 | F13: Đồ khô | G13: =E13 -> 544817
B14: 44873 | C14: 226228 | E14: 30000 | F14: Thi công điện | G14: =SUM(E14:E16) -> 32990 | H14: =H12+C14-D14-G14 -> 2339905
E15: 1830 | F15: Phí ship rau | H15: =H14+C15-D15-G15 -> 2339905
E16: 1160 | F16: Phí ship rau | H16: =H15+C16-D16-G16 -> 2339905
B17: 44874 | C17: 207346 | E17: 10730 | F17: Gà lộn 1 kiện | G17: =E17 -> 10730 | H17: =H16+C17-D17-G17 -> 2536521
B18: 44875 | C18: 178730 | E18: 2110 | F18: Phí ship rau | G18: =SUM(E18:E21) -> 107702 | H18: =H17+C18-D18-G18 -> 2607549
E19: 1830 | F19: Phí ship rau | H19: =H18+C19-D19-G19 -> 2607549
E20: 54700 | F20: Thịt heo | H20: =H19+C20-D20-G20 -> 2607549
E21: 49062 | F21: Xoài | H21: =H20+C21-D21-G21 -> 2607549
B22: 44876 | C22: 302120 | D22: 9888 | E22: 43160 | F22: Vịt | G22: =SUM(E22:E26) -> 92176 | H22: =H21+C22-D22-G22 -> 2807605
E23: 21130 | F23: Gà lộn 2 kiện | H23: =H22+C23-D23-G23 -> 2807605
E24: 23668 | F24: Hành khô | H24: =H23+C24-D24-G24 -> 2807605
E25: 1830 | F25: Phí ship ổi | H25: =H24+C25-D25-G25 -> 2807605
E26: 2388 | F26: Cồn rửa | H26: =#REF!+C26-D26-G26 -> #REF!
B27: 44877 | C27: 417626 | E27: 572505 | F27: Đồ khô | G27: =SUM(E27:E34) -> 967537 | H27: =H26+C27-D27-G27 -> #REF!
E28: 29000 | F28: Rau | H28: =H27+C28-D28-G28 -> #REF!
E29: 249100 | F29: Thịt | H29: =H28+C29-D29-G29 -> #REF!
E30: 8000 | F30: Rau | H30: =H29+C30-D30-G30 -> #REF!
E31: 43110 | F31: Chè sầu-Bông lan | H31: =H30+C31-D31-G31 -> #REF!
E32: 64490 | F32: Vietcook | H32: =H31+C32-D32-G32 -> #REF!
E33: 770 | F33: Túi bóng | H33: =H32+C33-D33-G33 -> #REF!
E34: 562 | F34: Túi bóng | H34: =H33+C34-D34-G34 -> #REF!
B35: 44878 | C35: 414182 | E35: 163470 | F35: Vietcook | G35: =SUM(E35:E38) -> 356100 | H35: =H34+C35-D35-G35 -> #REF!
E36: 188620 | F36: Đông lạnh | H36: =H35+C36-D36-G36 -> #REF!
E37: 2400 | F37: Cải muối | H37: =H36+C37-D37-G37 -> #REF!
E38: 1610 | F38: Phí ship rau | H38: =H37+C38-D38-G38 -> #REF!
B39: 44879 | C39: 187564 | G39: =E39 -> 0 | H39: =H38+C39-D39-G39 -> #REF!
B40: 44880 | C40: 251319 | D40: 2947 | E40: 1654 | F40: Túi bóng | G40: =SUM(E40:E45) -> 36126 | H40: =H39+C40-D40-G40 -> #REF!
E41: 7980 | F41: Túi bóng | H41: =H40+C41-D41-G41 -> #REF!
E42: 10802 | F42: Mua cân | H42: =H41+C42-D42-G42 -> #REF!
E43: 1830 | F43: Phí ship rau | H43: =H42+C43-D43-G43 -> #REF!
E44: 1830 | F44: Phí ship rau | H44: =H43+C44-D44-G44 -> #REF!
E45: 12030 | F45: Gà lộn 1 kiện | H45: =H44+C45-D45-G45 -> #REF!
B46: 44881 | C46: 230717 | D46: 15480 | E46: 12030 | F46: Gà lộn 1 kiện | G46: =E46 -> 12030 | H46: =H45+C46-D46-G46 -> #REF!
B47: 44882 | C47: 145887 | D47: 1703 | E47: 112985 | F47: Đông lạnh | G47: =SUM(E47:E50) -> 377170 | H47: =H46+C47-D47-G47 -> #REF!
E48: 72985 | F48: Thịt | H48: =H47+C48-D48-G48 -> #REF!
E49: 182450 | F49: Thịt | H49: =H48+C49-D49-G49 -> #REF!
E50: 8750 | F50: Túi bóng | H50: =H49+C50-D50-G50 -> #REF!
B51: 44883 | C51: 240667 | E51: 150280 | F51: Vietcook | G51: =SUM(E51:E52) -> 161010 | H51: =#REF!+C51-D51-G51 -> #REF!
E52: 10730 | F52: Gà lộn 1 kiện | H52: =H51+C52-D52-G52 -> #REF!
B53: 44884 | C53: 453822 | E53: 92160 | F53: Bắp bò | G53: =SUM(E53:E57) -> 120356 | H53: =H52+C53-D53-G53 -> #REF!
E54: 15906 | F54: Ớt | H54: =H53+C54-D54-G54 -> #REF!
E55: 5000 | F55: Cải xoong | H55: =H54+C55-D55-G55 -> #REF!
E56: 4856 | F56: Nafuco | H56: =H55+C56-D56-G56 -> #REF!
E57: 2434 | F57: Xương ống | H57: =H56+C57-D57-G57 -> #REF!
B58: 44885 | C58: 402432 | E58: 39400 | F58: Xoài | G58: =SUM(E58:E62) -> 192230 | H58: =H57+C58-D58-G58 -> #REF!
E59: 43660 | F59: Đông lạnh | H59: =H58+C59-D59-G59 -> #REF!
E60: 22900 | F60: Sả | H60: =H59+C60-D60-G60 -> #REF!
E61: 43160 | F61: Vịt | H61: =H60+C61-D61-G61 -> #REF!
E62: 43110 | F62: Chè dừa-Bông lan | H62: =H61+C62-D62-G62 -> #REF!
B63: 44886 | C63: 203345 | E63: 130000 | F63: Tiền nhà | G63: =SUM(E63:E69) -> 1383784 | H63: =H62+C63-D63-G63 -> #REF!
E64: 138450 | F64: Ba chỉ | H64: =H63+C64-D64-G64 -> #REF!
E65: 19065 | F65: Ớt | H65: =H64+C65-D65-G65 -> #REF!
E66: 80550 | F66: Rau | H66: =H65+C66-D66-G66 -> #REF!
E67: 8000 | F67: Bưởi | H67: =H66+C67-D67-G67 -> #REF!
E68: 978969 | F68: Đồ khô | H68: =H67+C68-D68-G68 -> #REF!
E69: 28750 | F69: Cải muối | H69: =H68+C69-D69-G69 -> #REF!
B70: 44887 | C70: 128825 | E70: 31600 | F70: Thịt | G70: =SUM(E70:E72) -> 240539 | H70: =H69+C70-D70-G70 -> #REF!
E71: 203025 | F71: Vietcook | H71: =H70+C71-D71-G71 -> #REF!
E72: 5914 | F72: Túi bóng | H72: =H71+C72-D72-G72 -> #REF!
B73: 44888 | C73: 240808 | E73: 23730 | F73: Gà lộn 2 kiện | G73: =SUM(E73:E75) -> 349223 | H73: =H72+C73-D73-G73 -> #REF!
E74: 134353 | F74: Bắp bò | H74: =H73+C74-D74-G74 -> #REF!
E75: 191140 | F75: Đông lạnh | H75: =H74+C75-D75-G75 -> #REF!
B76: 44889 | C76: 326794 | E76: 1830 | F76: Phí ship rau | G76: =SUM(E76:E77) -> 46630 | H76: =H75+C76-D76-G76 -> #REF!
E77: 44800 | F77: Xoài | H77: =H76+C77-D77-G77 -> #REF!
B78: 44890 | C78: 326050 | E78: 3622 | F78: Dây cáp | G78: =SUM(E78:E79) -> 15652 | H78: =H77+C78-D78-G78 -> #REF!
E79: 12030 | F79: Gà lộn 1 kiện | H79: =H78+C79-D79-G79 -> #REF!
B80: 44891 | C80: 500096 | E80: 8939 | F80: Túi bóng | G80: =SUM(E80:E83) -> 295183 | H80: =H79+C80-D80-G80 -> #REF!
E81: 102600 | F81: Bún safoco | H81: =#REF!+C81-D81-G81 -> #REF!
E82: 130775 | F82: Vietcook | H82: =H81+C82-D82-G82 -> #REF!
E83: 52869 | F83: Hành khô | H83: =H82+C83-D83-G83 -> #REF!
B84: 44892 | E84: 9576 | F84: Kago | G84: =SUM(E84:E87) -> 399648 | H84: =H83+C84-D84-G84 -> #REF!
E85: 29970 | F85: Chè sầu | H85: =H84+C85-D85-G85 -> #REF!
E86: 357992 | F86: Đồ khô | H86: =H85+C86-D86-G86 -> #REF!
E87: 2110 | F87: Phí ship | H87: =H86+C87-D87-G87 -> #REF!
B88: 44893 | E88: 97560 | F88: Đông lạnh | G88: =SUM(E88:E92) -> 173420 | H88: =H87+C88-D88-G88 -> #REF!
E89: 21050 | F89: Măng chua | H89: =H88+C89-D89-G89 -> #REF!
E90: 44700 | F90: Gà ủ muối | H90: =H89+C90-D90-G90 -> #REF!
E91: 8000 | F91: Susu
E92: 2110 | F92: Phí ship mướp | H92: =H90+C92-D92-G92 -> #REF!
B93: 44894 | E93: 800 | F93: Trả đơn | G93: =SUM(E93:E97) -> 251740 | H93: =H92+C93-D93-G93 -> #REF!
E94: 6200 | F94: Túi bóng | H94: =H93+C94-D94-G94 -> #REF!
E95: 32400 | F95: Rau | H95: =H94+C95-D95-G95 -> #REF!
E96: 93560 | F96: Vietcook
E97: 118780 | F97: Phí ship mướp | H97: =H95+C97-D97-G97 -> #REF!
B98: 44895 | E98: 31650 | F98: Gà ủ muối | G98: =SUM(E98:E106) -> 1242694 | H98: =H97+C98-D98-G98 -> #REF!
E99: 834641 | F99: Đồ khô
E100: 21070 | F100: Gà ủ muối | H100: =H98+C100-D100-G100 -> #REF!
E101: 10730 | F101: Gà lộn | H101: =H100+C101-D101-G101 -> #REF!
E102: 26223 | F102: Ếch
...

Sheet 2023_2
A1: Tháng trước
A2: 日付 | C2: Doanh thu | D2: Tổng chi | E2: 小計 | F2: Luỹ kế | G2: 入金
A3: 44958 | B3: 水 | C3: 156900 | D3: 110325 | E3: =C3-D3 -> 46575 | F3: =E3 -> 46575
A4: 44959 | B4: 木 | C4: 349841 | D4: 108665 | E4: =C4-D4 -> 241176 | F4: =F3+E4 -> 287751
A5: 44960 | B5: 金 | C5: 243550 | D5: 163250 | E5: =C5-D5 -> 80300 | F5: =F4+E5 -> 368051
A6: 44961 | B6: 土 | C6: 423870 | D6: 28635 | E6: =C6-D6 -> 395235 | F6: =F5+E6 -> 763286
A7: 44962 | B7: 日 | C7: 390667 | D7: 334895 | E7: =C7-D7 -> 55772 | F7: =F6+E7 -> 819058
A8: 44963 | B8: 月 | C8: 150304 | D8: 122886 | E8: =C8-D8 -> 27418 | F8: =F7+E8 -> 846476
A9: 44964 | B9: 火 | C9: 253040 | D9: 652907 | E9: =C9-D9 -> -399867 | F9: =F8+E9 -> 446609
A10: 44965 | B10: 水 | C10: 242255 | D10: 262933 | E10: =C10-D10 -> -20678 | F10: =F9+E10 -> 425931
A11: 44966 | B11: 木 | C11: 161847 | D11: 128934 | E11: =C11-D11 -> 32913 | F11: =F10+E11 -> 458844
A12: 44967 | B12: 金 | C12: 286707 | D12: 206633 | E12: =C12-D12 -> 80074 | F12: =F11+E12 -> 538918
A13: 44968 | B13: 土 | C13: 384625 | D13: 318780 | E13: =C13-D13 -> 65845 | F13: =F12+E13 -> 604763
A14: 44969 | B14: 日 | C14: 342732 | D14: 56510 | E14: =C14-D14 -> 286222 | F14: =F13+E14 -> 890985
A15: 44970 | B15: 月 | C15: 194289 | D15: 448900 | E15: =C15-D15 -> -254611 | F15: =F14+E15 -> 636374
... A30: 44985 | B30: 火 | C30: 356126 | D30: 425439 | E30: =C30-D30 -> -69313 | F30: =F29+E30 -> 1227571
D31: 190000 | E31: =C31-D31 -> -190000 | F31: =F30+E31 -> 1037571
D32: =F155 -> 60000
C33: =SUM(C3:C30) -> 8197983 | D33: =F156 -> 6737507 | F33: =C33-D33 -> 1460476
A35: 領収書
A36: 日付 | C36: Nơi chi | D36: 金額 | E36: Chi Tiết | F36: Tổng | G36: 確認
A37: 44958 | B37: 水 | D37: 23555 | E37: Sườn già | F37: =SUM(D37:D41) -> 110325
D38: 5000 | E38: Nước mía
D39: 37900 | E39: Xoài
D40: 30400 | E40: Sả
D41: 13470 | E41: BLTM
A42: 44959 | B42: 木 | D42: 44700 | E42: Gà ủ muối | F42: =SUM(D42:D44) -> 108665
D43: 44900 | E43: Bún safoco
D44: 19065 | E44: Hành khô
A45: 44960 | B45: 金 | D45: 2110 | E45: Phí ship | F45: =SUM(D45:D47) -> 28635
D46: 5005 | E46: Túi bóng
D47: 21520 | E47: Ớt
A48: 44961 | B48: 土 | D48: 163250 | E48: Thịt heo | F48: =D48 -> 163250
A49: 44962 | B49: 日 | D49: 370 | F49: =SUM(D49:D52) -> 334895
C50: Vietcook | D50: 79560 | E50: Giò chả
D51: 28010 | E51: Gà ủ muối
C52: Xuân Shop | D52: 226955 | E52: Đồ khô
A53: 44963 | B53: 月 | D53: 27640 | E53: Bò húc | F53: =SUM(D53:D56) -> 122880
D54: 59660 | E54: Giò chả
D55: 16240 | E55: Numberone
D56: 19340 | E56: Chân gà
A57: 44964 | B57: 火 | C57: Xuân Shop | D57: 546744 | E57: Đồ khô | F57: =SUM(D57:D60) -> 652907
D58: 65393 | E58: Tiền điện
D59: 30330 | E59: Chè
D60: 10440 | E60: Vịt
A61: 44965 | B61: 水 | D61: 36980 | E61: Vịt | F61: =SUM(D61:D66) -> 262933
D62: 14000 | E62: Sả
D63: 37700 | E63: Thịt heo
D64: 17900 | E64: Hảo hảo
D65: 119083 | E65: Xuân Shop
D66: 37270 | E66: Rau
A67: 44966 | B67: 木 | D67: 1830 | E67: Phí ship | F67: =SUM(D67:D71) -> 128934
D68: 2534 | E68: Băng dính
D69: 50750 | E69: Rau
D70: 40720 | E70: Chinsu
D71: 33100 | E71: Omachi
A72: 44967 | B72: 金 | C72: Vietcook | D72: 137968 | E72: Giò chả | F72: =SUM(D72:D75) -> 206633
D73: 7555 | E73: Túi bóng
C74: Saomai | D74: 34750 | E74: Mắm nêm
D75: 26360 | E75: Nước cốt dừa
A76: 44968 | B76: 土 | D76: 65500 | E76: Gạo | F76: =SUM(D76:D80) -> 318780
D77: 30330 | E77: Chè
D78: 10960 | E78: Nước dừa
D79: 11440 | E79: Sữa ông thọ
D80: 200550 | E80: Gà lộn
A81: 44969 | B81: 日 | C81: Vietcook | D81: 56510 | E81: Giò chả | F81: =D81 -> 56510
A82: 44970 | B82: 月 | C82: Xuxu Mart | D82: 443700 | E82: Thịt | F82: =SUM(D82:D83) -> 458900
D83: 15200 | E83: Gà đông lạnh
A84: 44971 | B84: 火 | C84: Vietcook | D84: 100639 | E84: Giò chả | F84: =SUM(D84:D87) -> 485421
D85: 42062 | E85: Bắp heo
C86: Xuân Shop | D86: 329250 | E86: Đồ khô
D87: 13470 | E87: Chè
A88: 44972 | B88: 水 | D88: 2419 | E88: Sườn non | F88: =SUM(D88:D92) -> 179773
D89: 22400 | E89: Cá lóc
C90: Vietcook | D90: 94854 | E90: Giò chả
D91: 44900 | E91: Bún safoco
D92: 15200 | E92: Fami
A93: 44973 | B93: 木 | D93: 17700 | E93: Hảo hảo | F93: =SUM(D93:D100) -> 556795
D94: 78150 | E94: Sả-Xoài
D95: 26440 | E95: Dừa
D96: 28023 | E96: Sườn non
C97: Xuân Shop | D97: 325062 | E97: Đồ khô
D98: 44700 | E98: Gà ủ muối
D99: 15200 | E99: Gà
D100: 21520 | E100: Ớt
A101: 44974 | B101: 金 | D101: 28470 | E101: Chè | F101: =SUM(D101:D106) -> 334548
D102: 16300 | E102: Cá trê
C103: Xuân Shop | D103: 150770 | E103: Đồ khô
D104: 18070 | E104: Vịt
D105: 24000 | E105: Omachi
C106: Vietcook | D106: 96938 | E106: Giò chả
A107: 44975 | B107: 土 | D107: 19200 | E107: Rau | F107: =SUM(D107:D108) -> 85700
D108: 66500 | E108: Gạo
A109: 44976 | B109: 日 | D109: 1830 | E109: Phí ship | F109: =SUM(D109:D113) -> 101401
D110: 15330 | E110: Chè
D111: 31200 | E111: Mắm
D112: 16240 | E112: Numberone
D113: 36801 | E113: Vịt
A114: 44977 | B114: 月 | C114: Vietcook | D114: 49935 | E114: Giò chả | F114: =SUM(D114:D119) -> 275808
C115: Vietcook | D115: 60930 | E115: Giò chả
...

Sheet 2023_3
A1: Tháng trước
A2: 日付 | C2: Doanh thu | D2: Tổng chi | E2: 小計 | F2: Luỹ kế | G2: 入金
A3: 44986 | B3: 水 | C3: 418832 | D3: =F38 -> 45569 | E3: =C3-D3 -> 373263 | F3: =E3 -> 373263
A4: 44987 | B4: 木 | C4: 289820 | D4: =F41 -> 83955 | E4: =C4-D4 -> 205865 | F4: =F3+E4 -> 579128
A5: 44988 | B5: 金 | C5: 589257 | D5: =F44 -> 190842 | E5: =C5-D5 -> 398415 | F5: =F4+E5 -> 977543
A6: 44989 | B6: 土 | C6: 463659 | D6: =F52 -> 263162 | E6: =C6-D6 -> 200497 | F6: =F5+E6 -> 1178040
A7: 44990 | B7: 日 | C7: 401658 | D7: =F61 -> 118683 | E7: =C7-D7 -> 282975 | F7: =F6+E7 -> 1461015
A8: 44991 | B8: 月 | C8: 195456 | D8: =F65 -> 996094 | E8: =C8-D8 -> -800638 | F8: =F7+E8 -> 660377
A9: 44992 | B9: 火 | C9: 185887 | D9: =F71 -> 245332 | E9: =C9-D9 -> -59445 | F9: =F8+E9 -> 600932
A10: 44993 | B10: 水 | C10: 243908 | D10: =F75 -> 176477 | E10: =C10-D10 -> 67431 | F10: =F9+E10 -> 668363
A11: 44994 | B11: 木 | C11: 196885 | D11: =F80 -> 127305 | E11: =C11-D11 -> 69580 | F11: =F10+E11 -> 737943
A12: 44995 | B12: 金 | C12: 416444 | D12: =F83 -> 41230 | E12: =C12-D12 -> 375214 | F12: =F11+E12 -> 1113157
A13: 44996 | B13: 土 | C13: 591768 | D13: =F85 -> 42446 | E13: =C13-D13 -> 549322 | F13: =F12+E13 -> 1662479
A14: 44997 | B14: 日 | C14: 386901 | D14: =F88 -> 871431 | E14: =C14-D14 -> -484530 | F14: =F13+E14 -> 1177949
A15: 44998 | B15: 月 | C15: 213669 | D15: =F95 -> 107786 | E15: =C15-D15 -> 105883 | F15: =F14+E15 -> 1283832
A16: 44999 | B16: 火 | C16: 286213 | D16: =F98 -> 184313 | E16: =C16-D16 -> 101900 | F16: =F15+E16 -> 1385732
A17: 45000 | B17: 水 | C17: 214192 | D17: =F103 -> 230206 | E17: =C17-D17 -> -16014 | F17: =F16+E17 -> 1369718
A18: 45001 | B18: 木 | C18: 181386 | D18: =F109 -> 144374 | E18: =C18-D18 -> 37012 | F18: =F17+E18 -> 1406730
A19: 45002 | B19: 金 | C19: 581148 | D19: =F115 -> 138200 | E19: =C19-D19 -> 442948 | F19: =F18+E19 -> 1849678
A20: 45003 | B20: 土 | C20: 360237 | D20: =F120 -> 235100 | E20: =C20-D20 -> 125137 | F20: =F19+E20 -> 1974815
A21: 45004 | B21: 日 | C21: 280605 | D21: =F125 -> 183908 | E21: =C21-D21 -> 96697 | F21: =F20+E21 -> 2071512
A22: 45005 | B22: 月 | C22: 261819 | D22: =F129 -> 662444 | E22: =C22-D22 -> -400625 | F22: =F21+E22 -> 1670887
A23: 45006 | B23: 火 | C23: 232191 | D23: =F133 -> 80970 | E23: =C23-D23 -> 151221 | F23: =F22+E23 -> 1822108
A24: 45007 | B24: 水 | C24: 169153 | D24: =F138 -> 72324 | E24: =C24-D24 -> 96829 | F24: =F23+E24 -> 1918937
A25: 45008 | B25: 木 | C25: 244680 | D25: =F139 -> 86060 | E25: =C25-D25 -> 158620 | F25: =F24+E25 -> 2077557
A26: 45009 | B26: 金 | C26: 438725 | D26: =F143 -> 114890 | E26: =C26-D26 -> 323835 | F26: =F25+E26 -> 2401392
A27: 45010 | B27: 土 | C27: 550730 | D27: =F146 -> 684758 | E27: =C27-D27 -> -134028 | F27: =F26+E27 -> 2267364
A28: 45011 | B28: 日 | C28: 340934 | D28: =F153 -> 38392 | E28: =C28-D28 -> 302542 | F28: =F27+E28 -> 2569906
A29: 45012 | B29: 月 | C29: 0 | D29: =F155 -> 42795 | E29: =C29-D29 -> -42795 | F29: =F28+E29 -> 2527111
A30: 45013 | B30: 火 | C30: 319435 | D30: =F156 -> 712172 | E30: =C30-D30 -> -392737 | F30: =F29+E30 -> 2134374
A31: 45014 | B31: 水 | C31: 282375 | D31: =F162 -> 259900 | E31: =C31-D31 -> 22475 | F31: =F30+E31 -> 2156849
A32: 45015 | B32: 木 | C32: 302199 | D32: =F165 -> 141888 | E32: =C32-D32 -> 160311 | F32: =F31+E32 -> 2317160
A33: 45016 | B33: 金 | C33: 705681 | D33: =F171 -> 315830 | E33: =C33-D33 -> 389851 | F33: =F32+E33 -> 2707011
D34: 708321 | E34: =C34-D34 -> -708321 | F34: =F33+E34 -> 1998690
A35: 合計 | C35: =SUM(C3:C33) -> 10345847 | D35: =SUM(D3:D33) -> 7638836
A36: 領収書
A37: 日付 | C37: Nơi chi | D37: 金額 | E37: Chi Tiết | F37: Tổng | G37: 確認
A38: 44986 | B38: 水 | C38: Chợ Sỹ Thak | D38: 17099 | E38: 20kg bắp heo | F38: =SUM(D38:D39) -> 45569
C39: Di An Di | D39: 28470 | E39: 18 BLTM+30 chè sầu + 20 chè dừa non
D40: 130000 | E40: Tiền nhà
A41: 44987 | B41: 木 | C41: XS | D41: 8730 | E41: 24 Gà size nhỏ | F41: =SUM(D41:D43) -> 83955
C42: MIRAI | D42: 48400 | E42: Omachi+Fami
C43: VietNamHouse | D43: 26825 | E43: Chân+Đùi gà ủ
A44: 44988 | B44: 金 | C44: Daiso | D44: 3634 | E44: Băng dính | F44: =SUM(D44:D51) -> 190842
C45: VietnNamHouse | D45: 26738 | E45: Bò húc
C46: Rau | D46: 1830 | E46: Phí ship
D47: 6000 | E47: Cải dưa muối
D48: 46320 | E48: Gà ủ muối
C49: Vietcook | D49: 46660 | E49: Gà ủ muối
C50: Yến Minh | D50: 36700 | E50: Rau
C51: MIRAI | D51: 22960 | E51: Mắm tôm
A52: 44989 | B52: 土 | C52: MIRAI | D52: 37560 | E52: Fami+Sứa | F52: =SUM(D52:D60) -> 263162
C53: HSC | D53: 42190 | E53: Safoco
C54: MIRAI | D54: 20400 | E54: Xoài
C55: SACHAN | D55: 11400 | E55: Sữa ông thọ
C56: SACHAN | D56: 40720 | E56: Chinsu to
C57: Chợ Sỹ Thak | D57: 52614 | E57: Thịt
C58: Nafuco | D58: 5048 | E58: Túi bóng
C59: Di An Di | D59: 30330 | E59: Chè
C60: MIRAI | D60: 22900 | E60: Sả
A61: 44990 | B61: 日 | C61: Nafuco | D61: 3860 | E61: Túi bóng | F61: =SUM(D61:D64) -> 118683
D62: 33190 | E62: Mix
C63: Chợ Sỹ Thak | D63: 57633 | E63: Thịt
C64: MIRAI | D64: 24000 | E64: Omachi
A65: 44991 | B65: 月 | C65: Xuxu Mart | D65: 437575 | E65: Thịt | F65: =SUM(D65:D69) -> 996094
C66: Kho tổng | D66: 469979 | E66: Đồ khô
C67: MIRAI | D67: 24000 | E67: Omachi
D68: 19340 | E68: Chân gà
C69: BUITRAM | D69: 45200 | E69: Xoài
D70: 60550 | E70: Tủ lạnh
A71: 44992 | B71: 火 | D71: 155910 | E71: Trứng lộn | F71: =SUM(D71:D74) -> 245332
D72: 66192 | E72: Rau
C73: SACHAN | D73: 21400 | E73: Me cục
D74: 1830 | E74: Phí ship
A75: 44993 | B75: 水 | C75: MIRAI | D75: 15000 | E75: Ngô nếp | F75: =SUM(D75:D79) -> 176477
D76: 12127 | E76: Muối hảo hảo
D77: 25410 | E77: Gà đông lạnh
D78: 49540 | E78: Ba chỉ
D79: 74400 | E79: Hoa quả
A80: 44994 | B80: 木 | D80: 13470 | E80: Bông lan | F80: =SUM(D80:D82) -> 127305
D81: 32835 | E81: Đùi + Chân gà ủ
D82: 81000 | E82: Xoài + Sả
A83: 44995 | B83: 金 | D83: 15330 | E83: Chè | F83: =SUM(D83:D84) -> 41230
D84: 25900 | E84: Rau
A85: 44996 | B85: 土 | D85: 8500 | E85: Gà đông lạnh | F85: =SUM(D85:D87) -> 42446
D86: 15330 | E86: Chè
D87: 18616 | E87: Vit
A88: 44997 | B88: 日 | D88: 15280 | E88: Dầu hào | F88: =SUM(D88:D94) -> 871431
D89: 2110 | E89: Phí ship
D90: 15330 | E90: Chè
C91: Amazon | D91: 2980 | E91: Giấy in
C92: Kho tổng | D92: 590506 | E92: Đồ khô
C93: Xuxu Mart | D93: 238225 | E93: Thịt
D94: 7000 | E94: Rau
A95: 44998 | B95: 月 | D95: 19340 | E95: Chân gà | F95: =SUM(D95:D97) -> 107786
D96: 45480 | E96: Mì xào
D97: 42966 | E97: Vịt
A98: 44999 | B98: 火 | D98: 13470 | E98: Bông lan | F98: =SUM(D98:D102) -> 184313
D99: 47150 | E99: Gà ủ muối
D100: 23375 | E100: Nhót
...

Sheet 2023_4
A1: 日付 | C1: Doanh Thu | D1: Tổng Chi | E1: Ship BĐ | F1: Luỹ kế | G1: Ship
A2: 45017 | B2: 土 | C2: 392879 | D2: 180197 | E2: 0 | F2: =C2-D2 -> 212682 | G2: 50520
A3: 45018 | B3: 日 | C3: 288213 | D3: 206824 | E3: 17529 | F3: =C3-D3+F2 -> 294071 | G3: 0
A4: 45019 | B4: 月 | C4: 261646 | D4: 716462 | E4: 30200 | F4: =C4-D4+F3 -> -160745 | G4: 91849
A5: 45020 | B5: 火 | C5: 342457 | D5: 146387 | E5: 0 | F5: =C5-D5+F4 -> 35325 | G5: 182436
A6: 45021 | B6: 水 | C6: 194932 | D6: 1004590 | E6: 0 | F6: =C6-D6+F5 -> -774333 | G6: 72210
A7: 45022 | B7: 木 | C7: 344621 | D7: 533119 | E7: 0 | F7: =C7-D7+F6 -> -962831 | G7: 127167
A8: 45023 | B8: 金 | C8: 485949 | D8: 197708 | E8: 8324 | F8: =C8-D8+F7 -> -674590 | G8: 334341
A9: 45024 | B9: 土 | C9: 416374 | D9: 64412 | E9: 0 | F9: =C9-D9+F8 -> -322628 | G9: 64232
A10: 45025 | B10: 日 | C10: 324598 | D10: 391190 | E10: 0 | F10: =C10-D10+F9 -> -389220 | G10: 0
A11: 45026 | B11: 月 | C11: 215353 | D11: 63470 | E11: 20006 | F11: =C11-D11+F10 -> -237337 | G11: 75127
A12: 45027 | B12: 火 | C12: 392103 | D12: 24980 | E12: 0 | F12: =C12-D12+F11 -> 129786 | G12: 245247
A13: 45028 | B13: 水 | C13: 267178 | D13: 85764 | E13: 26712 | F13: =C13-D13+F12 -> 311200 | G13: 170179
A14: 45029 | B14: 木 | C14: 325349 | D14: 154349 | E14: 7602 | F14: =C14-D14+F13 -> 482200 | G14: 140212
... A18: 45033 | B18: 月 | C18: 194940 | D18: 289320 | E18: 13945 | F18: =C18-D18+F17 -> 485468 | G18: 79242
A19: 45034 | B19: 火 | C19: 254482 | D19: 80810 | E19: 0 | F19: 659140 | G19: 113538
A20: 45035 | B20: 水 | C20: 190349 | D20: 183857 | E20: 25612 | F20: =C20-D20+F19 -> 665632 | G20: 60322
A21: 45036 | B21: 木 | C21: 203693 | D21: 126930 | E21: 0 | F21: =C21-D21+F20 -> 742395 | G21: 82712
A22: 45037 | B22: 金 | C22: 425984 | D22: 484843 | E22: 0 | F22: =C22-D22+F21 -> 683536 | G22: 287918
A23: 45038 | B23: 土 | C23: 485848 | D23: 170451 | E23: 28248 | F23: =C23-D23+F22 -> 998933 | G23: 89224
A24: 45039 | B24: 日 | C24: 350968 | D24: 64428 | E24: 0 | F24: =C24-D24+F23 -> 1285473 | G24: 0
A25: 45040 | B25: 月 | C25: 144851 | D25: 676242 | E25: 21553 | F25: =C25-D25+F24 -> 754082 | G25: 32662
A26: 45041 | B26: 火 | C26: 256866 | D26: 25495 | E26: 36121 | F26: =C26-D26+F25 -> 985453 | G26: 171159
A27: 45042 | B27: 水 | C27: 427621 | D27: 98856 | E27: 17399 | F27: =C27-D27+F26 -> 1314218 | G27: 211339
A28: 45043 | B28: 木 | C28: 361633 | D28: 123933 | E28: 0 | F28: =C28-D28+F27 -> 1551918 | G28: 210273
A29: 45044 | B29: 金 | C29: 762448 | D29: 642585 | E29: 39001 | F29: =C29-D29+F28 -> 1671781 | G29: 487726
A30: 45045 | B30: 土 | C30: 409023 | D30: 161979 | E30: 10731 | F30: =C30-D30+F29 -> 1918825 | G30: 134108
A31: 45046 | B31: 日 | C31: 674794 | D31: 856629 | E31: 21643 | F31: =C31-D31+F30 -> 1736990 | G31: 15850
A32: TỔNG | C32: =SUM(C2:C31) -> 10638575 | D32: =SUM(D2:D31) -> 8901585 | E32: =SUM(E2:E31) -> 345622 | F32: =F31 -> 1736990 | G32: =SUM(G2:G31) -> 3954720
A33: BÁO CÁO THÁNG
C34: THU
C35: TỔNG | D35: SHIP BD | E35: SHIP
C36: =C32 -> 10638575 | D36: =E32 -> 345622 | E36: =G32 -> 3954720
D37: =D36/C36 -> 0.032487622 | E37: =E36/C36 -> 0.371734
C38: CHI
C39: NHẬP HÀNG | D39: LƯƠNG | E39: HỖ TRỢ SHIP | F39: TRẢ HÀNG | G39: TỔNG
C40: =D32 -> 8901585 | D40: =SUM(D47:G47) -> 518800 | E40: =D36*0.055 -> 19009.21 | F40: =SUM(D49:G49) -> 6414 | G40: =SUM(C40:F40) -> 9445808.2
C41: LỢI NHUẬN | D41: =C36-G40 -> 1192766.8
C42: CHI TIẾT
C43: LƯƠNG | D43: Anh Giang | E43: Anh Thái | F43: Nghĩa | G43: Khánh
D44: 250000 | E44: 50000 | F44: 164000 | G44: 19800
C45: THƯỞNG | D45: Anh Giang | E45: Anh Thái | F45: Nghĩa | G45: Khánh
D46: 10000 | E46: 10000 | F46: 10000 | G46: 5000
C47: TỔNG | D47: =D44+D46 -> 260000 | E47: =E44+E46 -> 60000 | F47: =F44+F46 -> 174000 | G47: =G44+G46 -> 24800
C48: TRẢ HÀNG | D48: ĐƠN 1 | E48: ĐƠN 2 | F48: ĐƠN 3 | G48: ĐƠN 4
D49: 2800 | E49: 1000 | F49: 264 | G49: 2350
C50: Nội dung | D50: Gà lộn | E50: Xoài | F50: Bột năng | G50: Sữa TH

Sheet 2023_5
A1: 日付 | C1: Doanh Thu | D1: Tổng Chi | E1: Ship BĐ | F1: Luỹ kế | G1: Ship | H1: Đơn
A2: 45047 | B2: 月 | C2: 395724 | D2: 176869 | E2: 0 | F2: =C2-D2 -> 218855 | G2: 168757 | H2: 12
A3: 45048 | B3: 火 | C3: 364455 | D3: 249869 | E3: 0 | F3: =C3-D3+F2 -> 333441 | G3: 57626 | H3: 9
A4: 45049 | B4: 水 | C4: 577062 | D4: 108116 | E4: 8289 | F4: =C4-D4+F3 -> 802387 | G4: 106124 | H4: 7
A5: 45050 | B5: 木 | C5: 536243 | D5: 313427 | E5: 0 | F5: =C5-D5+F4 -> 1025203 | G5: 110212 | H5: 8
A6: 45051 | B6: 金 | C6: 480165 | D6: 1426942 | E6: 0 | F6: =C6-D6+F5 -> 78426 | G6: 162021 | H6: 20
A7: 45052 | B7: 土 | C7: 279652 | D7: 113290 | E7: 0 | F7: =C7-D7+F6 -> 244788 | G7: 124320 | H7: 11
A8: 45053 | B8: 日 | C8: 248779 | D8: 184295 | E8: 25887 | F8: =C8-D8+F7 -> 309272 | G8: 0 | H8: 0
A9: 45054 | B9: 月 | C9: 239320 | D9: 63165 | E9: 0 | F9: =C9-D9+F8 -> 485427 | G9: 52430 | H9: 4
A10: 45055 | B10: 火 | C10: 247470 | D10: 592382 | E10: 31711 | F10: =C10-D10+F9 -> 140515 | G10: 73182 | H10: 8
A11: 45056 | B11: 水 | C11: 262362 | D11: 66890 | E11: 27852 | F11: =C11-D11+F10 -> 335987 | G11: 68420 | H11: 6
A12: 45057 | B12: 木 | C12: 219319 | D12: 177157 | E12: 8612 | F12: =C12-D12+F11 -> 378149 | G12: 80168 | H12: 10
A13: 45058 | B13: 金 | C13: 702894 | D13: 41121 | E13: 26511 | F13: =C13-D13+F12 -> 1039922 | G13: 444003 | H13: 41
A14: 45059 | B14: 土 | C14: 297040 | D14: 604873 | E14: 36574 | F14: =C14-D14+F13 -> 732089 | G14: 92164 | H14: 11
... A32: 45077 | B32: 水 | C32: 228910 | D32: 279199 | E32: 109080 | F32: =C32-D32+F31 -> 1235471 | G32: 0 | H32: 11
A33: TỔNG | C33: =SUM(C2:C32) -> 10551079 | D33: =SUM(D2:D32) -> 9315608 | E33: =SUM(E2:E32) -> 561525 | F33: =F32 -> 1235471 | G33: =SUM(G2:G32) -> 3474234 | H33: =SUM(H2:H32) -> 359
A34: BÁO CÁO THÁNG
C35: THU
C36: TỔNG | D36: SHIP BD | E36: SHIP | F36: THANH TOÁN POINT
C37: =C33 -> 10551079 | D37: =E33 -> 561525 | E37: =G33 -> 3474234 | F37: 76964
D38: =D37/C37 -> 0.053219675 | E38: =E37/C37 -> 0.3292776 | F38: =F37/C37 -> 0.0072944198
C39: CHI
C40: NHẬP HÀNG | D40: LƯƠNG | E40: HỖ TRỢ SHIP | F40: TRẢ HÀNG | G40: TỔNG
C41: =D33 -> 9315608 | D41: =SUM(D45:G45) -> 505750 | E41: =E33*0.057 -> 32006.925 | F41: =F52 -> 2644 | G41: =SUM(C41:F41) -> 9856008.9
C42: LỢI NHUẬN | D42: =C37-G41-F37 -> 618106.07
C43: CHI TIẾT
C44: LƯƠNG | D44: Anh Giang | E44: Anh Thái | F44: Nghĩa | G44: Khánh
D45: 250000 | E45: 60000 | F45: 172000 | G45: 23750
C46: THƯỞNG | D46: Anh Giang | E46: Anh Thái | F46: Nghĩa | G46: Khánh
D47: 0 | E47: 0 | F47: 0 | G47: 0
C48: TỔNG | D48: =D45+D47 -> 250000 | E48: =E45+E47 -> 60000 | F48: =F45+F47 -> 172000 | G48: =G45+G47 -> 23750
C49: TRẢ HÀNG | D49: ĐƠN 1 | E49: ĐƠN 2 | F49: ĐƠN 3 | G49: ĐƠN 4
D50: 800 | E50: 920 | F50: 924 | G50: 0
C51: Nội dung | D51: Gà lộn | E51: Tính nhầm | F51: Tai heo
C52: Tổng | F52: =SUM(D50:G50) -> 2644

Sheet 2023_6
A1: 日付 | C1: Doanh Thu | D1: Tổng Chi | E1: Ship BĐ | F1: Luỹ kế | G1: Ship | H1: Đơn
A2: 45078 | B2: 木 | C2: 165869 | D2: 66000 | E2: 0 | F2: =C2-D2 -> 99869 | G2: 70851 | H2: 6
A3: 45079 | B3: 金 | C3: 558838 | D3: 10520 | E3: 5188 | F3: =C3-D3+F2 -> 648187 | G3: 370484 | H3: 38
A4: 45080 | B4: 土 | C4: 454777 | D4: 100383 | E4: 19543 | F4: =C4-D4+F3 -> 1002581 | G4: 106124 | H4: 7
A5: 45081 | B5: 日 | C5: 572681 | D5: 91615 | E5: 21778 | F5: =C5-D5+F4 -> 1483647 | G5: 0 | H5: 0
A6: 45082 | B6: 月 | C6: 277611 | D6: 1184125 | E6: 52904 | F6: =C6-D6+F5 -> 577133 | G6: 98727 | H6: 14
A7: 45083 | B7: 火 | C7: 278988 | D7: 92524 | E7: 15285 | F7: =C7-D7+F6 -> 763597 | G7: 141620 | H7: 16
A8: 45084 | B8: 水 | C8: 255712 | D8: 553685 | E8: 0 | F8: =C8-D8+F7 -> 465624 | G8: 125555 | H8: 14
A9: 45085 | B9: 木 | C9: 231880 | D9: 212778 | E9: 0 | F9: =C9-D9+F8 -> 484726 | G9: 144229 | H9: 17
A10: 45086 | B10: 金 | C10: 674965 | D10: 286339 | E10: 17425 | F10: =C10-D10+F9 -> 873352 | G10: 462124 | H10: 34
A11: 45087 | B11: 土 | C11: 663609 | D11: 292901 | E11: 10334 | F11: =C11-D11+F10 -> 1244060 | G11: 201720 | H11: 13
A12: 45088 | B12: 日 | C12: 491942 | D12: 103690 | E12: 30342 | F12: =C12-D12+F11 -> 1632312 | G12: 0 | H12: 0
A13: 45089 | B13: 月 | C13: 225920 | D13: 641010 | E13: 21941 | F13: =C13-D13+F12 -> 1217222 | G13: 92142 | H13: 8
A14: 45090 | B14: 火 | C14: 276059 | D14: 40493 | E14: 2921 | F14: =C14-D14+F13 -> 1452788 | G14: 102342 | H14: 9
... A31: 45107 | B31: 金 | C31: 636145 | D31: 501894 | E31: 20320 | F31: =C31-D31+F30 -> 2623458 | G31: 457329 | H31: 45
A33: TỔNG | C33: =SUM(C2:C32) -> 11588760 | D33: =SUM(D2:D32) -> 8965302 | E33: =SUM(E2:E32) -> 433398 | F33: =F31 -> 2623458 | G33: =SUM(G2:G32) -> 4494386 | H33: =SUM(H2:H32) -> 397
A34: BÁO CÁO THÁNG
C35: THU
C36: TỔNG | D36: SHIP BD | E36: SHIP | F36: THANH TOÁN POINT
C37: =C33 -> 11588760 | D37: =E33 -> 433398 | E37: =G33 -> 4494386 | F37: 125814
D38: =D37/C37 -> 0.037398134 | E38: =E37/C37 -> 0.38782286 | F38: =F37/C37 -> 0.010856554
C39: CHI
C40: NHẬP HÀNG | D40: LƯƠNG | E40: HỖ TRỢ SHIP | F40: TRẢ HÀNG | G40: TỔNG
C41: =D33 -> 8965302 | D41: =SUM(D48:H48) -> 657275 | E41: =E33*0.065 -> 28170.87 | F41: =F54 -> 78834 | G41: =SUM(C41:F41) -> 9729581.9
C42: LỢI NHUẬN | D42: =C37-G41-F37 -> 1733364.1
C43: CHI TIẾT
C44: LƯƠNG | D44: Anh Giang | E44: A Thái | F44: Nghĩa | G44: Khánh | H44: C Hiền
D45: 250000 | E45: 64000 | F45: 184000 | G45: =24.5*950 -> 23275 | H45: 18000
C46: Hỗ trợ ship | D46: Anh Giang | E46: Anh Thái | F46: Nghĩa | G46: Khánh | H46: Nhàn
D47: 80000 | E47: 10000 | F47: 0 | G47: 0 | H47: 28000
C48: TỔNG | D48: =D45+D47 -> 330000 | E48: =E45+E47 -> 74000 | F48: =F45+F47 -> 184000 | G48: =G45+G47 -> 23275 | H48: =H45+H47 -> 46000
C49: TRẢ HÀNG | D49: Huỷ đơn | E49: Hàng hỏng | F49: Chênh lệch
D50: 53888 | E50: 16256 | F50: 8690
C53: Nội dung
C54: Tổng | F54: =SUM(D49:G53) -> 78834

Sheet 2023_7
A1: 日付 | C1: Doanh Thu | D1: Tổng Chi | E1: Ship BĐ | F1: Luỹ kế | G1: Ship | H1: Đơn
A2: 45108 | B2: 土 | C2: 495705 | D2: 96019 | E2: 37813 | F2: =C2-D2 -> 399686 | G2: 124532 | H2: 11
A3: 45109 | B3: 日 | C3: 451876 | D3: 273248 | E3: 12786 | F3: =C3-D3+F2 -> 578314 | G3: 0 | H3: 0
A4: 45110 | B4: 月 | C4: 225295 | D4: 123180 | E4: 13460 | F4: =C4-D4+F3 -> 680429 | G4: 96212 | H4: 8
A5: 45111 | B5: 火 | C5: 258091 | D5: 60945 | E5: 6214 | F5: =C5-D5+F4 -> 877575 | G5: 103472 | H5: 7
A6: 45112 | B6: 水 | C6: 354967 | D6: 1186911 | E6: 42358 | F6: =C6-D6+F5 -> 45631 | G6: 154763 | H6: 8
A7: 45113 | B7: 木 | C7: 368284 | D7: 541442 | E7: 21420 | F7: =C7-D7+F6 -> -127527 | G7: 167530 | H7: 18
A8: 45114 | B8: 金 | C8: 563589 | D8: 119045 | E8: 0 | F8: =C8-D8+F7 -> 317017 | G8: 382120 | H8: 42
A9: 45115 | B9: 土 | C9: 419912 | D9: 330941 | E9: 0 | F9: =C9-D9+F8 -> 405988 | G9: 112403 | H9: 6
A10: 45116 | B10: 日 | C10: 318644 | D10: 11525 | E10: 8743 | F10: =C10-D10+F9 -> 713107 | G10: 0 | H10: 0
A11: 45117 | B11: 月 | C11: 243441 | D11: 39330 | E11: 12768 | F11: =C11-D11+F10 -> 917218 | G11: 87650 | H11: 8
A12: 45118 | B12: 火 | C12: 491466 | D12: 148170 | E12: 36720 | F12: =C12-D12+F11 -> 1260514 | G12: 254690 | H12: 16
A13: 45119 | B13: 水 | C13: 438229 | D13: 239780 | E13: 0 | F13: =C13-D13+F12 -> 1458963 | G13: 210320 | H13: 15
A14: 45120 | B14: 木 | C14: 312439 | D14: 151536 | E14: 22102 | F14: =C14-D14+F13 -> 1619866 | G14: 186542 | H14: 12
... A32: 45138 | B32: 月 | C32: 304721 | D32: 996894 | E32: 12439 | F32: =C32-D32+F31 -> 1955807 | G32: 192320 | H32: 17
A33: TỔNG | C33: =SUM(C2:C32) -> 11780128 | D33: =SUM(D2:D32) -> 9824321 | E33: =SUM(E2:E32) -> 466556 | F33: =F32 -> 1955807 | G33: =SUM(G2:G32) -> 5015906 | H33: =SUM(H2:H32) -> 403
A34: BÁO CÁO THÁNG
C35: THU
C36: TỔNG | D36: SHIP BD | E36: SHIP | F36: THANH TOÁN POINT
C37: =C33 -> 11780128 | D37: =E33 -> 466556 | E37: =G33 -> 5015906 | F37: 93723
D38: =D37/C37 -> 0.039605342 | E38: =E37/C37 -> 0.42579385 | F38: =F37/C37 -> 0.0079560256
C39: CHI
C40: NHẬP HÀNG | D40: LƯƠNG | E40: HỖ TRỢ SHIP | F40: TRẢ HÀNG | G40: TỔNG
C41: =D33 -> 9824321 | D41: =SUM(D48:H48) -> 677500 | E41: =E33*6% -> 27993.36 | F41: =F54 -> 95672 | G41: =SUM(C41:F41) -> 10625486
C42: LỢI NHUẬN | D42: =C37-G41-F37 -> 1060918.6
C43: CHI TIẾT
C44: LƯƠNG | D44: Anh Giang | E44: A Thái | F44: Nghĩa | G44: Nhàn | H44: C Hiền
D45: 250000 | E45: 61000 | F45: 174000 | G45: 91000 | H45: 24000
C46: Hỗ trợ ship | D46: Anh Giang | E46: Anh Thái | F46: Nghĩa | G46: Nhàn | H46: C Hiền
D47: 57500 | E47: 20000 | F47: 0 | G47: 0 | H47: 0
C48: TỔNG | D48: =D45+D47 -> 307500 | E48: =E45+E47 -> 81000 | F48: =F45+F47 -> 174000 | G48: =G45+G47 -> 91000 | H48: =H45+H47 -> 24000
C49: TRẢ HÀNG | D49: Huỷ đơn | E49: Hàng hỏng | F49: Chênh lệch | G49: Thuê ship
D50: 19660 | E50: 32642 | F50: 14370 | G50: 29000
C53: Nội dung
C54: Tổng | F54: =SUM(D49:G53) -> 95672

Sheet 2023_8
A1: 日付 | C1: 売上 | D1: 支出 | E1: 入金 | F1: 不足 | G1: デリバリ | H1: 累計 | I1: 配達 | J1: 数
A2: 45139 | B2: 火 | C2: 388063 | D2: 91821 | E2: =C2-D2 -> 296242 | F2: -420 | G2: 31072 | H2: =E2+F2 -> 295822 | I2: 124532 | J2: 11
A3: 45140 | B3: 水 | C3: 224971 | D3: 350405 | E3: =C3-D3 -> -125434 | F3: -202 | G3: 0 | H3: =H2+E3+F3 -> 170186 | I3: 0 | J3: 0
A4: 45141 | B4: 木 | C4: 208043 | D4: 330427 | E4: =C4-D4 -> -122384 | F4: -108 | G4: 12412 | H4: =H3+E4+F4 -> 47694 | I4: 96212 | J4: 8
A5: 45142 | B5: 金 | C5: 602364 | D5: 355522 | E5: =C5-D5 -> 246842 | F5: -417 | G5: 26408 | H5: =H4+E5+F5 -> 294119 | I5: 103472 | J5: 7
A6: 45143 | B6: 土 | C6: 464001 | D6: 89070 | E6: =C6-D6 -> 374931 | F6: -17 | G6: 0 | H6: =H5+E6+F6 -> 669033 | I6: 154763 | J6: 8
A7: 45144 | B7: 日 | C7: 288421 | D7: 33681 | E7: =C7-D7 -> 254740 | F7: -457 | G7: 0 | H7: =H6+E7+F7 -> 923316 | I7: 167530 | J7: 18
A8: 45145 | B8: 月 | C8: 232104 | D8: 854538 | E8: =C8-D8 -> -622434 | F8: -729 | G8: 14272 | H8: =H7+E8+F8 -> 300153 | I8: 382120 | J8: 42
A9: 45146 | B9: 火 | C9: 353798 | D9: 197748 | E9: =C9-D9 -> 156050 | F9: -477 | G9: 12247 | H9: =H8+E9+F9 -> 455726 | I9: 112403 | J9: 6
A10: 45147 | B10: 水 | C10: 277820 | D10: 451545 | E10: =C10-D10 -> -173725 | F10: -327 | G10: 0 | H10: =H9+E10+F10 -> 281674 | I10: 0 | J10: 0
A11: 45148 | B11: 木 | C11: 516600 | D11: 315292 | E11: =C11-D11 -> 201308 | F11: -410 | G11: 24720 | H11: =H10+E11+F11 -> 482572 | I11: 87650 | J11: 8
A12: 45149 | B12: 金 | C12: 889181 | D12: 215562 | E12: =C12-D12 -> 673619 | F12: -472 | G12: 10722 | H12: =H11+E12+F12 -> 1155719 | I12: 254690 | J12: 16
A13: 45150 | B13: 土 | C13: 783523 | D13: 224503 | E13: =C13-D13 -> 559020 | F13: -311 | G13: 37489 | H13: =H12+E13+F13 -> 1714428 | I13: 210320 | J13: 15
A14: 45151 | B14: 日 | C14: 370475 | D14: 365034 | E14: =C14-D14 -> 5441 | F14: -774 | G14: 0 | H14: =H13+E14+F14 -> 1719095 | I14: 186542 | J14: 12
... A32: 45169 | B32: 木 | C32: 357172 | D32: 329850 | E32: =C32-D32 -> 27322 | F32: -9 | G32: 47720 | H32: =H31+E32+F32 -> 1597669 | I32: 192320 | J32: 17
A33: TỔNG | C33: =SUM(C2:C32) -> 12758842 | D33: =SUM(D2:D32) -> 11155239 | E33: =SUM(E2:E32) -> 1603603 | F33: =SUM(F2:F32) -> -5934 | G33: =SUM(G2:G32) -> 559742 | H33: =H32 -> 1597669 | I33: =SUM(I2:I32) -> 5015906 | J33: =SUM(J2:J32) -> 403
A34: BÁO CÁO THÁNG
C35: THU
C36: TỔNG | D36: SHIP BD | E36: SHIP | F36: Chênh lệch | H36: THANH TOÁN POINT
C37: =C33 -> 12758842 | D37: =G33 -> 559742 | E37: =I33 -> 5015906 | F37: =F33 -> -5934 | H37: 48431
D38: =D37/C37 -> 0.043870909 | E38: =E37/C37 -> 0.39313176 | F38: =F37/C37 -> -0.00046508923 | H38: =H37/C37 -> 0.0037958774
C39: CHI
C40: NHẬP HÀNG | D40: LƯƠNG | E40: TRẢ HÀNG | F40: Hỗ trợ ship BĐ | H40: TỔNG
C41: =D33 -> 11155239 | D41: =F48 -> 826896 | E41: =F50 -> 30444 | F41: =D37*0.065 -> 36383.23 | H41: =SUM(C41:G41) -> 12048962
C42: LỢI NHUẬN | D42: =C37-H37-H41 -> 661448.77
C43: CHI TIẾT
C44: LƯƠNG | D44: Anh Giang | E44: A Thái | F44: Nghĩa | H44: Nhàn | I44: Chị Hiền
D45: 250000 | E45: 39900 | F45: 192500 | H45: 132300 | I45: 23100
C46: Hỗ trợ ship | D46: Anh Giang | E46: A Thái | F46: Cưng | H46: Thuê ship
D47: 137896 | E47: 20000 | F47: 15200 | H47: 16000
C48: TỔNG | D48: =D45+D47 -> 387896 | E48: =E45+E47 -> 59900 | F48: =SUM(D48,E48,F45:J45,F47:J47) -> 826896
C49: TRẢ HÀNG | D49: Huỷ đơn | E49: Trả hàng | F49: TỔNG
D50: 20620 | E50: 9824 | F50: =SUM(D50:E50) -> 30444

Sheet 2023_9
A1: 日付 | C1: 売上 | D1: 支出 | E1: 入金 | F1: 不足 | G1: デリバリ | H1: 累計 | I1: BÁO CÁO THÁNG
A2: 45170 | B2: 金 | C2: 789961 | D2: 385993 | E2: =C2-D2 -> 403968 | F2: -1277 | G2: 42107 | H2: =E2+F2 -> 402691 | I2: THU
A3: 45171 | B3: 土 | C3: 721899 | D3: 127640 | E3: =C3-D3 -> 594259 | F3: -732 | G3: 21272 | H3: =H2+E3+F3 -> 996218 | I3: TỔNG | J3: SHIP BD | K3: SHIP | L3: Chênh lệch | M3: THANH TOÁN POINT
A4: 45172 | B4: 日 | C4: 485112 | D4: 297015 | E4: =C4-D4 -> 188097 | F4: 0 | G4: 0 | H4: =H3+E4+F4 -> 1184315 | I4: =C33 -> 13789456 | J4: =G33 -> 411948 | L4: =F33 -> -4407 | M4: 25586
A5: 45173 | B5: 月 | C5: 177354 | D5: 52514 | E5: =C5-D5 -> 124840 | F5: 0 | G5: 0 | H5: =H4+E5+F5 -> 1309155 | J5: =J4/I4 -> 0.02987413 | K5: =K4/I4 -> 0 | L5: =L4/I4 -> -0.00031959201 | M5: =M4/I4 -> 0.0018554757
A6: 45174 | B6: 火 | C6: 321907 | D6: 964213 | E6: =C6-D6 -> -642306 | F6: 0 | G6: 0 | H6: =H5+E6+F6 -> 666849 | I6: CHI
A7: 45175 | B7: 水 | C7: 320086 | D7: 185957 | E7: =C7-D7 -> 134129 | F7: 0 | G7: 0 | H7: =H6+E7+F7 -> 800978 | I7: NHẬP HÀNG | J7: LƯƠNG | K7: TRẢ HÀNG | L7: Hỗ trợ ship BĐ | M7: TỔNG
A8: 45176 | B8: 木 | C8: 281528 | D8: 501081 | E8: =C8-D8 -> -219553 | F8: -270 | G8: 14720 | H8: =H7+E8+F8 -> 581155 | I8: =D33 -> 11249226 | J8: =L16 -> 799650 | K8: =N19 -> 87407 | L8: =J4*0.065 -> 26776.62 | M8: =SUM(I8:L8) -> 12163060
A9: 45177 | B9: 金 | C9: 687907 | D9: 434680 | E9: =C9-D9 -> 253227 | F9: -14 | G9: 0 | H9: =H8+E9+F9 -> 834368 | I9: LỢI NHUẬN | J9: =I4-M8-M4 -> 1600810.4
A10: 45178 | B10: 土 | C10: 607769 | D10: 384991 | E10: =C10-D10 -> 222778 | F10: 10 | G10: 0 | H10: =H9+E10+F10 -> 1057156 | I10: CHI TIẾT
A11: 45179 | B11: 日 | C11: 376721 | D11: 343770 | E11: =C11-D11 -> 32951 | F11: 0 | G11: 0 | H11: =H10+E11+F11 -> 1090107 | I11: LƯƠNG - 給与
A12: 45180 | B12: 月 | C12: 241765 | D12: 573298 | E12: =C12-D12 -> -331533 | F12: 0 | G12: 18272 | H12: =H11+E12+F12 -> 758574 | I12: A. Giang | J12: A.Thái | K12: C.Hiền | L12: Nhàn | M12: Cưng | N12: Nghĩa
A13: 45181 | B13: 火 | C13: 291238 | D13: 104554 | E13: =C13-D13 -> 186684 | F13: 0 | G13: 37911 | H13: =H12+E13+F13 -> 945258 | I13: 250000 | J13: 75075 | K13: 19425 | L13: 119700 | M13: 33250 | N13: 194000
A14: 45182 | B14: 水 | C14: 413434 | D14: 637495 | E14: =C14-D14 -> -224061 | F14: -122 | G14: 0 | H14: =H13+E14+F14 -> 721075 | I14: HỖ TRỢ
A15: 45183 | B15: 木 | C15: 354850 | D15: 369372 | E15: =C15-D15 -> -14522 | F15: 2 | G15: 0 | H15: =H14+E15+F15 -> 706555 | I15: 88200 | J15: 20000
A16: 45184 | B16: 金 | C16: 715090 | D16: 281814 | E16: =C16-D16 -> 433276 | F16: 0 | G16: 0 | H16: =H15+E16+F16 -> 1139831 | I16: TỔNG | L16: =SUM(I13:N13)+SUM(I15:N15) -> 799650
A17: 45185 | B17: 土 | C17: 637018 | D17: 711233 | E17: =C17-D17 -> -74215 | F17: -18 | G17: 27120 | H17: =H16+E17+F17 -> 1065598 | I17: CHI KHÁC - その他
A18: 45186 | B18: 日 | C18: 365865 | D18: 249769 | E18: =C18-D18 -> 116096 | F18: -27 | G18: 0 | H18: =H17+E18+F18 -> 1181667 | I18: TRẢ - HUỶ | J18: 社会保険 | K18: CHÊNH LỆCH | L18: XĂNG XE | M18: THUÊ XE | N18: TỔNG
A19: 45187 | B19: 月 | C19: 334806 | D19: 165855 | E19: =C19-D19 -> 168951 | F19: -430 | G19: 12721 | H19: =H18+E19+F19 -> 1350188 | I19: 30000 | J19: 35000 | K19: 4407 | L19: 13000 | M19: 5000 | N19: =SUM(I19:M19) -> 87407
A20: 45188 | B20: 火 | C20: 268795 | D20: 183887 | E20: =C20-D20 -> 84908 | F20: 0 | G20: 19997 | H20: =H19+E20+F20 -> 1435096
A21: 45189 | B21: 水 | C21: 256197 | D21: 313486 | E21: =C21-D21 -> -57289 | F21: 0 | G21: 5762 | H21: =H20+E21+F21 -> 1377807
A22: 45190 | B22: 木 | C22: 239216 | D22: 361664 | E22: =C22-D22 -> -122448 | F22: -112 | G22: 14720 | H22: =H21+E22+F22 -> 1255247
A23: 45191 | B23: 金 | C23: 653657 | D23: 191131 | E23: =C23-D23 -> 462526 | F23: -224 | G23: 43020 | H23: =H22+E23+F23 -> 1717549
A24: 45192 | B24: 土 | C24: 676152 | D24: 76760 | E24: =C24-D24 -> 599392 | F24: 0 | G24: 31493 | H24: =H23+E24+F24 -> 2316941
A25: 45193 | B25: 日 | C25: 318815 | D25: 768020 | E25: =C25-D25 -> -449205 | F25: 0 | G25: 0 | H25: =H24+E25+F25 -> 1867736
A26: 45194 | B26: 月 | C26: 388724 | D26: 789950 | E26: =C26-D26 -> -401226 | F26: 0 | G26: 22780 | H26: =H25+E26+F26 -> 1466510
A27: 45195 | B27: 火 | C27: 459864 | D27: 395937 | E27: =C27-D27 -> 63927 | F27: 0 | G27: 0 | H27: =H26+E27+F27 -> 1530437
A28: 45196 | B28: 水 | C28: 478328 | D28: 305761 | E28: =C28-D28 -> 172567 | F28: -472 | G28: 37420 | H28: =H27+E28+F28 -> 1702532
A29: 45197 | B29: 木 | C29: 443547 | D29: 273404 | E29: =C29-D29 -> 170143 | F29: 0 | G29: 21212 | H29: =H28+E29+F29 -> 1872675
A30: 45198 | B30: 金 | C30: 674894 | D30: 291926 | E30: =C30-D30 -> 382968 | F30: 0 | G30: 0 | H30: =H29+E30+F30 -> 2255643
A31: 45199 | B31: 土 | C31: 806957 | D31: 526056 | E31: =C31-D31 -> 280901 | F31: -721 | G31: 41421 | H31: =H30+E31+F31 -> 2535823
E32: =C32-D32 -> 0 | H32: =H31+E32+F32 -> 2535823
A33: TỔNG | C33: =SUM(C2:C32) -> 13789456 | D33: =SUM(D2:D32) -> 11249226 | E33: =SUM(E2:E32) -> 2540230 | F33: =SUM(F2:F32) -> -4407 | G33: =SUM(G2:G32) -> 411948 | H33: =H32 -> 2535823

Sheet 2023_10
A1: 日付 | C1: 売上 | D1: 支出 | E1: 入金 | F1: 不足 | G1: デリバリ | H1: 累計 | I1: BÁO CÁO THÁNG
A2: 45200 | B2: 日 | C2: 439404 | D2: 97531 | E2: =C2-D2 -> 341873 | F2: 0 | G2: 24302 | H2: =E2+F2 -> 341873 | I2: THU
A3: 45201 | B3: 月 | C3: 293024 | D3: 193295 | E3: =C3-D3 -> 99729 | F3: 0 | G3: 0 | H3: =H2+E3+F3 -> 441602 | I3: TỔNG | J3: SHIP BD | K3: SHIP | L3: Chênh lệch | M3: THANH TOÁN POINT
A4: 45202 | B4: 火 | C4: 356376 | D4: 1153287 | E4: =C4-D4 -> -796911 | F4: -17 | G4: 12712 | H4: =H3+E4+F4 -> -355326 | I4: =C33 -> 12689656 | J4: =G33 -> 339621 | L4: =F33 -> -3598 | M4: 12094
A5: 45203 | B5: 水 | C5: 202909 | D5: 644555 | E5: =C5-D5 -> -441646 | F5: -340 | G5: 9780 | H5: =H4+E5+F5 -> -797312 | J5: =J4/I4 -> 0.02676361 | K5: =K4/I4 -> 0 | L5: =L4/I4 -> -0.00028353802 | M5: =M4/I4 -> 0.00095305972
A6: 45204 | B6: 木 | C6: 333146 | D6: 144531 | E6: =C6-D6 -> 188615 | F6: 0 | G6: 0 | H6: =H5+E6+F6 -> -608697 | I6: CHI
A7: 45205 | B7: 金 | C7: 754186 | D7: 341290 | E7: =C7-D7 -> 412896 | F7: 0 | G7: 0 | H7: =H6+E7+F7 -> -195801 | I7: NHẬP HÀNG | J7: LƯƠNG | K7: TRẢ HÀNG | L7: Hỗ trợ ship BĐ | M7: TỔNG
A8: 45206 | B8: 土 | C8: 815492 | D8: 510750 | E8: =C8-D8 -> 304742 | F8: 22 | G8: 60271 | H8: =H7+E8+F8 -> 108963 | I8: =D33 -> 11138899 | J8: =L16 -> 747750 | K8: =N19 -> 84657 | L8: =J4*0.065 -> 22075.365 | M8: =SUM(I8:L8) -> 11993381
A9: 45207 | B9: 日 | C9: 331185 | D9: 80902 | E9: =C9-D9 -> 250283 | F9: -470 | G9: 0 | H9: =H8+E9+F9 -> 358776 | I9: LỢI NHUẬN | J9: =I4-M8-M4 -> 684180.63
A10: 45208 | B10: 月 | C10: 292673 | D10: 253143 | E10: =C10-D10 -> 39530 | F10: 0 | G10: 21120 | H10: =H9+E10+F10 -> 398306 | I10: CHI TIẾT
A11: 45209 | B11: 火 | C11: 294338 | D11: 1004156 | E11: =C11-D11 -> -709818 | F11: 0 | G11: 0 | H11: =H10+E11+F11 -> -311512 | I11: LƯƠNG - 給与
A12: 45210 | B12: 水 | C12: 331533 | D12: 410522 | E12: =C12-D12 -> -78989 | F12: 2 | G12: 22727 | H12: =H11+E12+F12 -> -390499 | I12: A. Giang | J12: A.Thái | K12: C.Hiền | L12: Nhàn | M12: Cưng | N12: Nghĩa
A13: 45211 | B13: 木 | C13: 280023 | D13: 267327 | E13: =C13-D13 -> 12696 | F13: -6 | G13: 11011 | H13: =H12+E13+F13 -> -377809 | I13: 250000 | J13: 180000 | K13: 60500 | L13: 16000 | M13: 34250 | N13: 185000
A14: 45212 | B14: 金 | C14: 595580 | D14: 312102 | E14: =C14-D14 -> 283478 | F14: 157 | G14: 0 | H14: =H13+E14+F14 -> -94174 | I14: HỖ TRỢ
A15: 45213 | B15: 土 | C15: 776798 | D15: 512510 | E15: =C15-D15 -> 264288 | F15: -420 | G15: 0 | H15: =H14+E15+F15 -> 169694 | I15: 22000
A16: 45214 | B16: 日 | C16: 374422 | D16: 44310 | E16: =C16-D16 -> 330112 | F16: -221 | G16: 17720 | H16: =H15+E16+F16 -> 499585 | I16: TỔNG | L16: =SUM(I13:N13)+SUM(I15:N15) -> 747750
A17: 45215 | B17: 月 | C17: 195191 | D17: 304208 | E17: =C17-D17 -> -109017 | F17: -75 | G17: 17708 | H17: =H16+E17+F17 -> 390493 | I17: CHI KHÁC - その他
A18: 45216 | B18: 火 | C18: 293535 | D18: 502427 | E18: =C18-D18 -> -208892 | F18: 0 | G18: 0 | H18: =H17+E18+F18 -> 181601 | I18: TRẢ - HUỶ | J18: 社会保険 | K18: CHÊNH LỆCH | L18: XĂNG XE | M18: Khác | N18: TỔNG
A19: 45217 | B19: 水 | C19: 195064 | D19: 388611 | E19: =C19-D19 -> -193547 | F19: 0 | G19: 4780 | H19: =H18+E19+F19 -> -11946 | I19: 8000 | J19: 35000 | K19: 4407 | L19: 13000 | M19: =N23 -> 24250 | N19: =SUM(I19:M19) -> 84657
A20: 45218 | B20: 木 | C20: 283240 | D20: 244742 | E20: =C20-D20 -> 38498 | F20: 2 | G20: 20071 | H20: =H19+E20+F20 -> 26554
A21: 45219 | B21: 金 | C21: 592511 | D21: 369238 | E21: =C21-D21 -> 223273 | F21: -798 | G21: 0 | H21: =H20+E21+F21 -> 249029 | I21: 参考
A22: 45220 | B22: 土 | C22: 450664 | D22: 96665 | E22: =C22-D22 -> 353999 | F22: 0 | G22: 0 | H22: =H21+E22+F22 -> 603028 | I22: Anh Minh | J22: LƯƠNG | K22: ĐI LẠI | N22: TỔNG
A23: 45221 | B23: 日 | C23: 369899 | D23: 150706 | E23: =C23-D23 -> 219193 | F23: 0 | G23: 17424 | H23: =H22+E23+F23 -> 822221 | J23: 21850 | K23: 2400 | N23: =SUM(J23:M23) -> 24250
A24: 45222 | B24: 月 | C24: 209750 | D24: 98052 | E24: =C24-D24 -> 111698 | F24: -22 | G24: 0 | H24: =H23+E24+F24 -> 933897
A25: 45223 | B25: 火 | C25: 271625 | D25: 138980 | E25: =C25-D25 -> 132645 | F25: -423 | G25: 21720 | H25: =H24+E25+F25 -> 1066119
A26: 45224 | B26: 水 | C26: 378544 | D26: 1096679 | E26: =C26-D26 -> -718135 | F26: 0 | G26: 4872 | H26: =H25+E26+F26 -> 347984
A27: 45225 | B27: 木 | C27: 424075 | D27: 217761 | E27: =C27-D27 -> 206314 | F27: 0 | G27: 0 | H27: =H26+E27+F27 -> 554298
A28: 45226 | B28: 金 | C28: 693142 | D28: 384833 | E28: =C28-D28 -> 308309 | F28: -221 | G28: 34217 | H28: =H27+E28+F28 -> 862386
A29: 45227 | B29: 土 | C29: 844628 | D29: 511660 | E29: =C29-D29 -> 332968 | F29: -657 | G29: 0 | H29: =H28+E29+F29 -> 1194697
A30: 45228 | B30: 日 | C30: 380493 | D30: 39632 | E30: =C30-D30 -> 340861 | F30: 0 | G30: 18471 | H30: =H29+E30+F30 -> 1535558
A31: 45229 | B31: 月 | C31: 355739 | D31: 138624 | E31: =C31-D31 -> 217115 | F31: 0 | G31: 9841 | H31: =H30+E31+F31 -> 1752673
A32: 45230 | B32: 火 | C32: 280467 | D32: 485870 | E32: =C32-D32 -> -205403 | F32: -111 | G32: 10874 | H32: =H31+E32+F32 -> 1547159
A33: TỔNG | C33: =SUM(C2:C32) -> 12689656 | D33: =SUM(D2:D32) -> 11138899 | E33: =SUM(E2:E32) -> 1550757 | F33: =SUM(F2:F32) -> -3598 | G33: =SUM(G2:G32) -> 339621 | H33: =H32 -> 1547159

Sheet Chi tiết_2023_1１
A1: CHI | B1: CHI TIẾT | C1: MỤC | F1: TỔNG THEO MỤC
A2: 45231 | F2: 食材 | G2: =SUMIF($C$3:$C$497,"=食材",$A$3:$A$497) -> 7882672 | H2: =SUM(G2:G10) -> 11196218
A3: 18650 | B3: Hành tím | C3: 食材 | F3: 消耗品 | G3: =SUMIF($C$3:$C$497,"=消耗品",$A$3:$A$497) -> 54827
A4: 88020 | B4: Gà | C4: 食材 | F4: 家賃 | G4: =SUMIF($C$3:$C$497,"=家賃",$A$3:$A$497) -> 132000
A5: 484215 | B5: Thịt | C5: 食材 | F5: 水代 | G5: =SUMIF($C$3:$C$497,"=水代",$A$3:$A$497) -> 0
A6: 26155 | B6: Bắp heo rút xương | C6: 食材 | F6: 電気代 | G6: =SUMIF($C$3:$C$497,"=電気代",$A$3:$A$497) -> 67185
A7: 10400 | B7: Sả tươi | C7: 食材 | F7: ガソリン | G7: =SUMIF($C$3:$C$497,"=ガソリン",$A$3:$A$497) -> 68588
A8: 59346 | B8: Kome | C8: 食材 | F8: 米 | G8: =SUMIF($C$3:$C$497,"=米",$A$3:$A$497) -> 693600
A9: =SUM(A3:A8) -> 686786 | F9: TPX | G9: =SUMIF($C$3:$C$497,"=TPX",$A$3:$A$497) -> 2101650
A10: 45232 | F10: その他 | G10: =SUMIF($C$3:$C$497,"=その他",$A$3:$A$497) -> 195696
A11: 2510 | B11: Phí ship | C11: その他
A12: 110 | B12: Túi bóng | C12: 消耗品
A13: 8836 | B13: Xăng | C13: ガソリン
A14: 82582 | B14: Ba chỉ | C14: 食材
A15: 15840 | B15: Hành tím | C15: 食材
A16: 45600 | B16: Rau | C16: 食材
A17: 62550 | B17: Kome | C17: 食材
A18: =SUM(A11:A17) -> 218028
A19: 45233
A20: 160 | B20: Phí qua hầm | C20: その他
A21: 2000 | B21: Túi rác | C21: 消耗品
A22: 200440 | B22: Thuốc lá | C22: 食材
A23: 2754 | B23: Túi bóng | C23: 消耗品
A24: 27328 | B24: Xoài | C24: 食材
A25: 4900 | B25: Chuối xanh | C25: 食材
A26: 6182 | B26: Túi bóng | C26: 消耗品
A27: 366430 | B27: Chè đông lạnh | C27: 食材
A28: 25072 | B28: Sữa Milo | C28: 食材
A29: 47670 | B29: Nam ngư | C29: 食材
A30: 25996 | B30: Tai heo | C30: 食材
A31: 73750 | B31: Hoa chuối | C31: 食材
... A33: 80000 | B33: Gạo | C33: 米
A34: =SUM(A20:A33) -> 886582
A35: 45234
A36: 2510 | B36: Phí ship | C36: その他
A37: 3350 | B37: Sả + ớt | C37: 食材
A38: 42000 | B38: Bún safoco | C38: 食材
A39: 32462 | B39: G7 | C39: 食材
A40: 18400 | B40: Phở gà | C40: 食材
A41: =SUM(A36:A40) -> 98722
A42: 45235
A43: 662 | B43: Băng dính | C43: 消耗品
A44: 600550 | B44: Đồ khô | C44: TPX
A45: 59412 | B45: Sữa kun | C45: 食材
A46: 33652 | B46: Bún Vifon | C46: 食材
A47: 67750 | B47: Cá + ớt | C47: 食材
A48: =SUM(A43:A47) -> 762026
A49: 45236
A50: 82100 | B50: Omachi | C50: 食材
A51: 118451 | B51: Thịt | C51: 食材
A52: 62249 | B52: Vịt | C52: 食材
A53: 27880 | B53: Sả + Hành | C53: 食材
A54: 88300 | B54: Gạo | C54: 米
A55: =SUM(A50:A54) -> 378980
A56: 45237
A57: 2510 | B57: Phí ship | C57: その他
A58: 18930 | B58: Lòng non | C58: 食材
A59: 9051 | B59: Xăng | C59: ガソリン
A60: 16720 | B60: Bim bim mix | C60: 食材
A61: =SUM(A57:A60) -> 47211
A62: 45238
A63: 99846 | B63: Kome | C63: 食材
A64: 29880 | B64: Cá basa | C64: 食材
A65: 37399 | B65: Thịt | C65: 食材
A66: 29880 | B66: Khấu đuôi | C66: 食材
A67: 142727 | B67: Nam ngư | C67: 食材
A68: 49000 | B68: Gà ủ muối | C68: 食材
A69: 44340 | B69: Gà | C69: 食材
A70: 14070 | B70: Gia vị | C70: 食材
A71: 87800 | B71: Gạo | C71: 米
A72: 15800 | B72: Fami | C72: 食材
A73: 90200 | B73: Omachi | C73: 食材
A74: =SUM(A63:A73) -> 640942
A75: 45239
A76: 807 | B76: その他 | C76: その他
A77: 32240 | B77: TD Mart | C77: 食材
A78: 15331 | B78: Lạc | C78: 食材
A79: 62770 | B79: Ớt + bò húc | C79: 食材
A80: 82300 | B80: Rau | C80: 食材
A81: =SUM(A76:A80) -> 193448
A82: 45240
A83: 4900 | B83: Chuối xanh | C83: 食材
A84: 4287 | B84: Túi bóng | C84: 消耗品
A85: 5000 | B85: Xăng | C85: 食材
A86: 67185 | B86: Tiền điện T9 | C86: 電気代
A87: 69400 | B87: Hoa quả | C87: 食材
A88: 13431 | B88: Tai heo | C88: 食材
A89: =SUM(A83:A88) -> 164203
A90: 45241
A91: 94422 | B91: Tiểu ngạch | C91: 食材
A92: 737 | B92: Café | C92: その他
A93: 10500 | B93: Móng heo | C93: 食材
A94: 26032 | B94: Kome | C94: 食材
A95: 71080 | B95: Phí ship Yamato | C95: その他
A96: =SUM(A91:A95) -> 202771
A97: 45242
A98: 9105 | B98: Sả | C98: 食材
A99: 22000 | B99: Tiểu ngạch | C99: 食材
A100: 30280 | B100: Tiểu ngạch | C100: 食材
A101: 44500 | B101: Sườn già | C101: 食材
...

Sheet 2023_11
A1: 日付 | C1: 売上 | D1: 支出 | E1: 入金 | F1: 不足 | G1: デリバリ | H1: 累計 | I1: BÁO CÁO THÁNG
A2: 45231 | B2: 水 | C2: 389338 | D2: 686786 | E2: =C2-D2 -> -297448 | F2: -2 | G2: 12547 | H2: =E2+F2 -> -297450 | I2: THU
A3: 45232 | B3: 木 | C3: 204632 | D3: 218028 | E3: =C3-D3 -> -13396 | F3: -17 | G3: 0 | H3: =H2+E3+F3 -> -310863 | I3: TỔNG | J3: SHIP BD | K3: SHIP | L3: Chênh lệch | M3: THANH TOÁN POINT
A4: 45233 | B4: 金 | C4: 861190 | D4: 886582 | E4: =C4-D4 -> -25392 | F4: 0 | G4: 45541 | H4: =H3+E4+F4 -> -336255 | I4: =C33 -> 12007335 | J4: =G33 -> 270102 | L4: =F33 -> -1378 | M4: 19881
A5: 45234 | B5: 土 | C5: 401924 | D5: 98722 | E5: =C5-D5 -> 303202 | F5: 0 | G5: 8571 | H5: =H4+E5+F5 -> -33053 | J5: =J4/I4 -> 0.02249475 | K5: =K4/I4 -> 0 | L5: =L4/I4 -> -0.00011476318 | M5: =M4/I4 -> 0.0016557379
A6: 45235 | B6: 日 | C6: 391274 | D6: 762026 | E6: =C6-D6 -> -370752 | F6: 0 | G6: 0 | H6: =H5+E6+F6 -> -403805 | I6: CHI
A7: 45236 | B7: 月 | C7: 180736 | D7: 378980 | E7: =C7-D7 -> -198244 | F7: -22 | G7: 0 | H7: =H6+E7+F7 -> -602071 | I7: NHẬP HÀNG | J7: LƯƠNG | K7: CHI KHÁC | L7: Hỗ trợ ship BĐ | M7: TỔNG
A8: 45237 | B8: 火 | C8: 315166 | D8: 47211 | E8: =C8-D8 -> 267955 | F8: -29 | G8: 12475 | H8: =H7+E8+F8 -> -334145 | I8: =D33 -> 11196218 | J8: =L16 -> 705000 | K8: =N19 -> 55542 | L8: =J4*0.065 -> 17556.63 | M8: =SUM(I8:L8) -> 11974317
A9: 45238 | B9: 水 | C9: 186466 | D9: 640942 | E9: =C9-D9 -> -454476 | F9: 24 | G9: 0 | H9: =H8+E9+F9 -> -788597 | I9: LỢI NHUẬN | J9: =I4-M8-M4 -> 13137.37
A10: 45239 | B10: 木 | C10: 315770 | D10: 193448 | E10: =C10-D10 -> 122322 | F10: -222 | G10: 0 | H10: =H9+E10+F10 -> -666497 | I10: CHI TIẾT
A11: 45240 | B11: 金 | C11: 635625 | D11: 164203 | E11: =C11-D11 -> 471422 | F11: 0 | G11: 11254 | H11: =H10+E11+F11 -> -195075 | I11: LƯƠNG - 給与
A12: 45241 | B12: 土 | C12: 987759 | D12: 202771 | E12: =C12-D12 -> 784988 | F12: 0 | G12: 24710 | H12: =H11+E12+F12 -> 589913 | I12: A. Giang | J12: A.Thái | K12: C.Hiền | L12: Nhàn | M12: Cưng | N12: Nghĩa
A13: 45242 | B13: 日 | C13: 367750 | D13: 213701 | E13: =C13-D13 -> 154049 | F13: -779 | G13: 0 | H13: =H12+E13+F13 -> 743183 | I13: 250000 | J13: 68500 | K13: 75000 | L13: 10000 | M13: 35500 | N13: 197000
A14: 45243 | B14: 月 | C14: 268983 | D14: 1311196 | E14: =C14-D14 -> -1042213 | F14: 22 | G14: 0 | H14: =H13+E14+F14 -> -299008 | I14: HỖ TRỢ
A15: 45244 | B15: 火 | C15: 372138 | D15: 275915 | E15: =C15-D15 -> 96223 | F15: -54 | G15: 15442 | H15: =H14+E15+F15 -> -202839 | I15: 69000
A16: 45245 | B16: 水 | C16: 272372 | D16: 313598 | E16: =C16-D16 -> -41226 | F16: -11 | G16: 0 | H16: =H15+E16+F16 -> -244076 | I16: TỔNG | L16: =SUM(I13:N13)+SUM(I15:N15) -> 705000
A17: 45246 | B17: 木 | C17: 243354 | D17: 247550 | E17: =C17-D17 -> -4196 | F17: 0 | G17: 8521 | H17: =H16+E17+F17 -> -248272 | I17: CHI KHÁC - その他
A18: 45247 | B18: 金 | C18: 605936 | D18: 103641 | E18: =C18-D18 -> 502295 | F18: 124 | G18: 12545 | H18: =H17+E18+F18 -> 254147 | I18: TRẢ - HUỶ | J18: 社会保険 | K18: CHÊNH LỆCH | L18: XĂNG XE | M18: Khác | N18: TỔNG
A19: 45248 | B19: 土 | C19: 534465 | D19: 256569 | E19: =C19-D19 -> 277896 | F19: 11 | G19: 0 | H19: =H18+E19+F19 -> 532054 | I19: 18000 | J19: 35000 | M19: =N23 -> 2542 | N19: =SUM(I19:M19) -> 55542
A20: 45249 | B20: 日 | C20: 234365 | D20: 402138 | E20: =C20-D20 -> -167773 | F20: -22 | G20: 0 | H20: =H19+E20+F20 -> 364259
A21: 45250 | B21: 月 | C21: 258659 | D21: 81200 | E21: =C21-D21 -> 177459 | F21: -41 | G21: 15754 | H21: =H20+E21+F21 -> 541677 | I21: 参考
A22: 45251 | B22: 火 | C22: 266581 | D22: 40190 | E22: =C22-D22 -> 226391 | F22: 0 | G22: 12272 | H22: =H21+E22+F22 -> 768068 | J22: Giảm giá HD | N22: TỔNG
A23: 45252 | B23: 水 | C23: 359856 | D23: 165370 | E23: =C23-D23 -> 194486 | F23: -254 | G23: 0 | H23: =H22+E23+F23 -> 962300 | J23: 2542 | N23: =SUM(J23:M23) -> 2542
A24: 45253 | B24: 木 | C24: 332407 | D24: 611083 | E24: =C24-D24 -> -278676 | F24: 0 | G24: 0 | H24: =H23+E24+F24 -> 683624
A25: 45254 | B25: 金 | C25: 679449 | D25: 186047 | E25: =C25-D25 -> 493402 | F25: -4 | G25: 0 | H25: =H24+E25+F25 -> 1177022
A26: 45255 | B26: 土 | C26: 736726 | D26: 272342 | E26: =C26-D26 -> 464384 | F26: 0 | G26: 15756 | H26: =H25+E26+F26 -> 1641406
A27: 45256 | B27: 日 | C27: 509454 | D27: 305588 | E27: =C27-D27 -> 203866 | F27: -125 | G27: 48510 | H27: =H26+E27+F27 -> 1845147
A28: 45257 | B28: 月 | C28: 328560 | D28: 1019462 | E28: =C28-D28 -> -690902 | F28: 12 | G28: 0 | H28: =H27+E28+F28 -> 1154257
A29: 45258 | B29: 火 | C29: 155170 | D29: 416397 | E29: =C29-D29 -> -261227 | F29: 0 | G29: 0 | H29: =H28+E29+F29 -> 893030
A30: 45259 | B30: 水 | C30: 370378 | D30: 443466 | E30: =C30-D30 -> -73088 | F30: 0 | G30: 15750 | H30: =H29+E30+F30 -> 819942
A31: 45260 | B31: 木 | C31: 240852 | D31: 251066 | E31: =C31-D31 -> -10214 | F31: 11 | G31: 10454 | H31: =H30+E31+F31 -> 809739
A32: 0/12/2023 | B32: 金 | C32: 0 | D32: 0 | E32: =C32-D32 -> 0 | H32: =H31+E32+F32 -> 809739
A33: TỔNG | C33: =SUM(C2:C32) -> 12007335 | D33: =SUM(D2:D32) -> 11196218 | E33: =SUM(E2:E32) -> 811117 | F33: =SUM(F2:F32) -> -1378 | G33: =SUM(G2:G32) -> 270102 | H33: =H32 -> 809739

Sheet Chi tiết_2023_12
A1: CHI | B1: CHI TIẾT | C1: MỤC | E1: TỔNG THEO MỤC
A2: 45261 | E2: 食材 | F2: =SUMIF($C$3:$C$193,"=食材",$A$3:$A$193) -> 1079483 | G2: =SUM(F2:F8) -> 1199761
A3: 6776 | B3: Túi bóng | C3: 消耗品 | E3: 消耗品 | F3: =SUMIF($C$3:$C$193,"=消耗品",$A$3:$A$193) -> 6776
A4: 114020 | B4: Thịt | C4: 食材 | E4: 家賃 | F4: =SUMIF($C$3:$C$193,"=家賃",$A$3:$A$193) -> 0
A5: 39400 | B5: Xoài | C5: 食材 | E5: 水代 | F5: =SUMIF($C$3:$C$193,"=水代",$A$3:$A$193) -> 9242
A6: 64705 | B6: Bim bim mix | C6: 食材 | E6: 電気代 | F6: =SUMIF($C$3:$C$193,"=電気代",$A$3:$A$193) -> 0
A7: 48790 | B7: Ba chỉ | C7: 食材 | E7: 米 | F7: =SUMIF($C$3:$C$193,"=米",$A$3:$A$193) -> 102500
A8: =SUM(A3:A7) -> 273691 | E8: その他 | F8: =SUMIF($C$3:$C$193,"=その他",$A$3:$A$193) -> 1760
A9: 45262
A10: 520 | B10: Cao tốc | C10: その他
A11: 320 | B11: Phí qua hầm | C11: その他
A12: 9242 | B12: Tiền nước tháng 9 | C12: 水代
A13: 50401 | B13: Bún safoco | C13: 食材
A14: 53740 | B14: Sả tươi + Number | C14: 食材
A15: 41980 | B15: Kome | C15: 食材
A16: 59904 | B16: Vịt đông lạnh | C16: 食材
A17: 102500 | B17: Gạo | C17: 米
A18: =SUM(A10:A17) -> 318607
A19: 45263
A20: 141440 | B20: Thuốc lá | C20: 食材
A21: 400 | B21: Bãi xe | C21: その他
A22: 36330 | B22: Chè đông lạnh | C22: 食材
A23: 55900 | B23: Mướp | C23: 食材
A24: 26440 | B24: Pía mini | C24: 食材
A25: 4900 | B25: Chuối xanh | C25: 食材
A26: 35220 | B26: Sữa TH socola | C26: 食材
A27: 123560 | B27: Thịt | C27: 食材
A28: 43412 | B28: Thịt | C28: 食材
A29: =SUM(A20:A28) -> 467602
A30: 45264
A31: 14780 | B31: Chân gà | C31: 食材
A32: 520 | B32: Cao tốc | C32: その他
A33: 27862 | B33: Tai heo | C33: 食材
A34: 20729 | B34: Mì chính | C34: 食材
A35: 75970 | B35: Ba chỉ | C35: 食材
A36: =SUM(A31:A35) -> 139861

Sheet 2023_12
A1: 日付 | C1: 売上 | D1: 支出 | E1: 入金 | F1: 不足 | G1: デリバリ | H1: 累計 | I1: BÁO CÁO THÁNG
A2: 45261 | B2: 金 | C2: 738781 | D2: 273691 | E2: =C2-D2 -> 465090 | F2: 0 | G2: 34521 | H2: =E2+F2 -> 465090 | I2: THU
A3: 45262 | B3: 土 | C3: 595882 | D3: 318607 | E3: =C3-D3 -> 277275 | F3: 0 | G3: 0 | H3: =H2+E3+F3 -> 742365 | I3: TỔNG | J3: SHIP BD | K3: SHIP | L3: Chênh lệch | M3: THANH TOÁN POINT
A4: 45263 | B4: 日 | C4: 402381 | D4: 467602 | E4: =C4-D4 -> -65221 | F4: -27 | G4: 0 | H4: =H3+E4+F4 -> 677117 | I4: =C33 -> 15504613 | J4: =G33 -> 318236 | L4: =F33 -> -2561 | M4: 17416
A5: 45264 | B5: 月 | C5: 256488 | D5: 139861 | E5: =C5-D5 -> 116627 | F5: 0 | G5: 12332 | H5: =H4+E5+F5 -> 793744 | J5: =J4/I4 -> 0.020525246 | K5: =K4/I4 -> 0 | L5: =L4/I4 -> -0.00016517665 | M5: =M4/I4 -> 0.0011232786
A6: 45265 | B6: 火 | C6: 352259 | D6: 457508 | E6: =C6-D6 -> -105249 | F6: -452 | G6: 0 | H6: =H5+E6+F6 -> 688043 | I6: CHI
A7: 45266 | B7: 水 | C7: 279923 | D7: 421325 | E7: =C7-D7 -> -141402 | F7: 0 | G7: 0 | H7: =H6+E7+F7 -> 546641 | I7: NHẬP HÀNG | J7: LƯƠNG | K7: TRẢ HÀNG | L7: Hỗ trợ ship BĐ | M7: TỔNG
A8: 45267 | B8: 木 | C8: 300658 | D8: 173080 | E8: =C8-D8 -> 127578 | F8: 0 | G8: 22312 | H8: =H7+E8+F8 -> 674219 | I8: =D33 -> 13711257 | J8: =L16 -> 794500 | K8: =N19 -> 60744 | L8: =J4*0.065 -> 20685.34 | M8: =SUM(I8:L8) -> 14587186
A9: 45268 | B9: 金 | C9: 588630 | D9: 280309 | E9: =C9-D9 -> 308321 | F9: 0 | G9: 0 | H9: =H8+E9+F9 -> 982540 | I9: LỢI NHUẬN | J9: =I4-M8-M4 -> 900010.66
A10: 45269 | B10: 土 | C10: 840506 | D10: 338435 | E10: =C10-D10 -> 502071 | F10: 21 | G10: 9753 | H10: =H9+E10+F10 -> 1484632 | I10: CHI TIẾT
A11: 45270 | B11: 日 | C11: 336089 | D11: 661617 | E11: =C11-D11 -> -325528 | F11: -43 | G11: 0 | H11: =H10+E11+F11 -> 1159061 | I11: LƯƠNG - 給与
A12: 45271 | B12: 月 | C12: 179290 | D12: 204034 | E12: =C12-D12 -> -24744 | F12: -12 | G12: 12210 | H12: =H11+E12+F12 -> 1134305 | I12: A. Giang | J12: A.Thái | K12: C.Hiền | L12: Nhàn | M12: Cưng | N12: Nghĩa
A13: 45272 | B13: 火 | C13: 455506 | D13: 802449 | E13: =C13-D13 -> -346943 | F13: 0 | G13: 22431 | H13: =H12+E13+F13 -> 787362 | I13: 250000 | J13: 90000 | K13: 100500 | L13: 0 | M13: 39000 | N13: 220000
A14: 45273 | B14: 水 | C14: 245075 | D14: 607037 | E14: =C14-D14 -> -361962 | F14: 0 | G14: 0 | H14: =H13+E14+F14 -> 425400 | I14: HỖ TRỢ
A15: 45274 | B15: 木 | C15: 283889 | D15: 51817 | E15: =C15-D15 -> 232072 | F15: -14 | G15: 0 | H15: =H14+E15+F15 -> 657458 | I15: 95000
A16: 45275 | B16: 金 | C16: 680907 | D16: 419811 | E16: =C16-D16 -> 261096 | F16: 23 | G16: 65763 | H16: =H15+E16+F16 -> 918577 | I16: TỔNG | L16: =SUM(I13:N13)+SUM(I15:N15) -> 794500
A17: 45276 | B17: 土 | C17: 539452 | D17: 223226 | E17: =C17-D17 -> 316226 | F17: -654 | G17: 0 | H17: =H16+E17+F17 -> 1234149 | I17: CHI KHÁC - その他
A18: 45277 | B18: 日 | C18: 316433 | D18: 223410 | E18: =C18-D18 -> 93023 | F18: -87 | G18: 12650 | H18: =H17+E18+F18 -> 1327085 | I18: TRẢ - HUỶ | J18: 社会保険 | K18: CHÊNH LỆCH | L18: XĂNG XE | M18: Khác | N18: TỔNG
A19: 45278 | B19: 月 | C19: 149668 | D19: 319156 | E19: =C19-D19 -> -169488 | F19: 0 | G19: 0 | H19: =H18+E19+F19 -> 1157597 | I19: 21781 | J19: 35000 | M19: =N23 -> 3963 | N19: =SUM(I19:M19) -> 60744
A20: 45279 | B20: 火 | C20: 306776 | D20: 244490 | E20: =C20-D20 -> 62286 | F20: 0 | G20: 11432 | H20: =H19+E20+F20 -> 1219883
A21: 45280 | B21: 水 | C21: 273501 | D21: 654779 | E21: =C21-D21 -> -381278 | F21: -144 | G21: 0 | H21: =H20+E21+F21 -> 838461 | I21: 参考
A22: 45281 | B22: 木 | C22: 335730 | D22: 576774 | E22: =C22-D22 -> -241044 | F22: 0 | G22: 15310 | H22: =H21+E22+F22 -> 597417 | J22: Giảm giá HD | N22: TỔNG
A23: 45282 | B23: 金 | C23: 729693 | D23: 30852 | E23: =C23-D23 -> 698841 | F23: -122 | G23: 0 | H23: =H22+E23+F23 -> 1296136 | J23: 3963 | N23: =SUM(J23:M23) -> 3963
A24: 45283 | B24: 土 | C24: 639922 | D24: 246060 | E24: =C24-D24 -> 393862 | F24: 0 | G24: 12101 | H24: =H23+E24+F24 -> 1689998
A25: 45284 | B25: 日 | C25: 431463 | D25: 220777 | E25: =C25-D25 -> 210686 | F25: 21 | G25: 0 | H25: =H24+E25+F25 -> 1900705
A26: 45285 | B26: 月 | C26: 438061 | D26: 296070 | E26: =C26-D26 -> 141991 | F26: -12 | G26: 43521 | H26: =H25+E26+F26 -> 2042684
A27: 45286 | B27: 火 | C27: 660026 | D27: 414022 | E27: =C27-D27 -> 246004 | F27: -33 | G27: 12329 | H27: =H26+E27+F27 -> 2288655
A28: 45287 | B28: 水 | C28: 575883 | D28: 794590 | E28: =C28-D28 -> -218707 | F28: 12 | G28: 0 | H28: =H27+E28+F28 -> 2069960
A29: 45288 | B29: 木 | C29: 607217 | D29: 317276 | E29: =C29-D29 -> 289941 | F29: -231 | G29: 0 | H29: =H28+E29+F29 -> 2359670
A30: 45289 | B30: 金 | C30: 1262317 | D30: 832331 | E30: =C30-D30 -> 429986 | F30: 0 | G30: 12451 | H30: =H29+E30+F30 -> 2789656
A31: 45290 | B31: 土 | C31: 1335501 | D31: 306462 | E31: =C31-D31 -> 1029039 | F31: -453 | G31: 0 | H31: =H30+E31+F31 -> 3818242
A32: 45291 | B32: 日 | C32: 366706 | D32: 2393799 | E32: =C32-D32 -> -2027093 | F32: -354 | G32: 19120 | H32: =H31+E32+F32 -> 1790795
A33: TỔNG | C33: =SUM(C2:C32) -> 15504613 | D33: =SUM(D2:D32) -> 13711257 | E33: =SUM(E2:E32) -> 1793356 | F33: =SUM(F2:F32) -> -2561 | G33: =SUM(G2:G32) -> 318236 | H33: =H32 -> 1790795

Sheet 2024_1
A1: 日付 | C1: 売上 | D1: 支出 | E1: 入金 | F1: 不足 | G1: デリバリ | H1: 累計 | I1: BÁO CÁO THÁNG 1/2024
A2: 45292 | B2: 月 | C2: 363702 | D2: 374578 | E2: =C2-D2 -> -10876 | F2: -451 | G2: 12574 | H2: =E2+F2 -> -11327 | I2: THU
A3: 45262 | B3: 火 | C3: 333568 | D3: 75050 | E3: =C3-D3 -> 258518 | F3: 0 | G3: 22741 | H3: =H2+E3+F3 -> 247191 | I3: TỔNG | J3: SHIP BD | K3: SHIP | L3: Chênh lệch | M3: THANH TOÁN POINT
A4: 45263 | B4: 水 | C4: 307096 | D4: 229810 | E4: =C4-D4 -> 77286 | F4: 0 | G4: 0 | H4: =H3+E4+F4 -> 324477 | I4: =C33 -> 12958096 | J4: =G33 -> 487304 | L4: =F33 -> -4118 | M4: 3603
A5: 45264 | B5: 木 | C5: 377140 | D5: 275532 | E5: =C5-D5 -> 101608 | F5: 0 | G5: 0 | H5: =H4+E5+F5 -> 426085 | J5: =J4/I4 -> 0.037606142 | K5: =K4/I4 -> 0 | L5: =L4/I4 -> -0.0003177936 | M5: =M4/I4 -> 0.00027805011
A6: 45265 | B6: 金 | C6: 469040 | D6: 1170189 | E6: =C6-D6 -> -701149 | F6: -575 | G6: 25840 | H6: =H5+E6+F6 -> -275639 | I6: CHI
A7: 45266 | B7: 土 | C7: 323936 | D7: 337938 | E7: =C7-D7 -> -14002 | F7: 0 | G7: 0 | H7: =H6+E7+F7 -> -289641 | I7: NHẬP HÀNG | J7: LƯƠNG | K7: TRẢ HÀNG | L7: Hỗ trợ ship BĐ | M7: TỔNG
A8: 45267 | B8: 日 | C8: 270447 | D8: 297063 | E8: =C8-D8 -> -26616 | F8: -11 | G8: 0 | H8: =H7+E8+F8 -> -316268 | I8: =D33 -> 12575770 | J8: =L16 -> 701500 | K8: =N19 -> 59547 | L8: =J4*0.065 -> 31674.76 | M8: =SUM(I8:L8) -> 13368492
A9: 45268 | B9: 月 | C9: 272640 | D9: 190468 | E9: =C9-D9 -> 82172 | F9: 0 | G9: 44875 | H9: =H8+E9+F9 -> -234096 | I9: LỢI NHUẬN | J9: =I4-M8 -> -410395.76
A10: 45269 | B10: 火 | C10: 337829 | D10: 102855 | E10: =C10-D10 -> 234974 | F10: -147 | G10: 0 | H10: =H9+E10+F10 -> 731 | I10: CHI TIẾT
A11: 45270 | B11: 水 | C11: 433020 | D11: 152559 | E11: =C11-D11 -> 280461 | F11: -55 | G11: 25484 | H11: =H10+E11+F11 -> 281137 | I11: LƯƠNG - 給与
A12: 45271 | B12: 木 | C12: 351361 | D12: 265250 | E12: =C12-D12 -> 86111 | F12: 0 | G12: 57540 | H12: =H11+E12+F12 -> 367248 | I12: A. Giang | J12: A.Thái | K12: C.Hiền | L12: Nhàn | M12: Cưng | N12: Nghĩa
A13: 45272 | B13: 金 | C13: 574555 | D13: 454751 | E13: =C13-D13 -> 119804 | F13: 12 | G13: 0 | H13: =H12+E13+F13 -> 487064 | I13: 250000 | J13: 63150 | K13: 87350 | L13: 0 | M13: 37500 | N13: 198500
A14: 45273 | B14: 土 | C14: 735814 | D14: 415010 | E14: =C14-D14 -> 320804 | F14: -779 | G14: 44320 | H14: =H13+E14+F14 -> 807089 | I14: HỖ TRỢ
A15: 45274 | B15: 日 | C15: 386351 | D15: 144870 | E15: =C15-D15 -> 241481 | F15: 0 | G15: 14720 | H15: =H14+E15+F15 -> 1048570 | I15: 65000
A16: 45275 | B16: 月 | C16: 365446 | D16: 295221 | E16: =C16-D16 -> 70225 | F16: -22 | G16: 0 | H16: =H15+E16+F16 -> 1118773 | I16: TỔNG | L16: =SUM(I13:N13)+SUM(I15:N15) -> 701500
A17: 45276 | B17: 火 | C17: 317796 | D17: 144870 | E17: =C17-D17 -> 172926 | F17: 0 | G17: 44740 | H17: =H16+E17+F17 -> 1291699 | I17: CHI KHÁC - その他
A18: 45277 | B18: 水 | C18: 309485 | D18: 445664 | E18: =C18-D18 -> -136179 | F18: 0 | G18: 45970 | H18: =H17+E18+F18 -> 1155520 | I18: TRẢ - HUỶ | J18: 社会保険 | K18: CHÊNH LỆCH | L18: XĂNG XE | M18: Khác | N18: TỔNG
A19: 45278 | B19: 木 | C19: 277807 | D19: 323230 | E19: =C19-D19 -> -45423 | F19: -774 | G19: 0 | H19: =H18+E19+F19 -> 1109323 | I19: 24547 | J19: 35000 | M19: =N23 -> 0 | N19: =SUM(I19:M19) -> 59547
A20: 45279 | B20: 金 | C20: 666591 | D20: 706373 | E20: =C20-D20 -> -39782 | F20: 0 | G20: 0 | H20: =H19+E20+F20 -> 1069541
A21: 45280 | B21: 土 | C21: 498808 | D21: 188792 | E21: =C21-D21 -> 310016 | F21: -124 | G21: 32140 | H21: =H20+E21+F21 -> 1379433 | I21: 参考
A22: 45281 | B22: 日 | C22: 346555 | D22: 109780 | E22: =C22-D22 -> 236775 | F22: 0 | G22: 8574 | H22: =H21+E22+F22 -> 1616208 | J22: Giảm giá HD | N22: TỔNG
A23: 45282 | B23: 月 | C23: 183272 | D23: 95964 | E23: =C23-D23 -> 87308 | F23: 0 | G23: 0 | H23: =H22+E23+F23 -> 1703516 | J23: 0 | N23: =SUM(J23:M23) -> 0
A24: 45283 | B24: 火 | C24: 328345 | D24: 34899 | E24: =C24-D24 -> 293446 | F24: -145 | G24: 31241 | H24: =H23+E24+F24 -> 1996817
A25: 45284 | B25: 水 | C25: 206578 | D25: 219870 | E25: =C25-D25 -> -13292 | F25: 0 | G25: 0 | H25: =H24+E25+F25 -> 1983525
A26: 45285 | B26: 木 | C26: 447608 | D26: 460828 | E26: =C26-D26 -> -13220 | F26: -110 | G26: 12744 | H26: =H25+E26+F26 -> 1970195
A27: 45286 | B27: 金 | C27: 922448 | D27: 819319 | E27: =C27-D27 -> 103129 | F27: 0 | G27: 14740 | H27: =H26+E27+F27 -> 2073324
A28: 45287 | B28: 土 | C28: 1144027 | D28: 388336 | E28: =C28-D28 -> 755691 | F28: -474 | G28: 0 | H28: =H27+E28+F28 -> 2828541
A29: 45288 | B29: 日 | C29: 472800 | D29: 647448 | E29: =C29-D29 -> -174648 | F29: 0 | G29: 25260 | H29: =H28+E29+F29 -> 2653893
A30: 45289 | B30: 月 | C30: 274762 | D30: 919770 | E30: =C30-D30 -> -645008 | F30: 0 | G30: 12547 | H30: =H29+E30+F30 -> 2008885
A31: 45290 | B31: 火 | C31: 281858 | D31: 355051 | E31: =C31-D31 -> -73193 | F31: -14 | G31: 11254 | H31: =H30+E31+F31 -> 1935678
A32: 45291 | B32: 水 | C32: 377411 | D32: 1934432 | E32: =C32-D32 -> -1557021 | F32: -449 | G32: 0 | H32: =H31+E32+F32 -> 378208
A33: TỔNG | C33: =SUM(C2:C32) -> 12958096 | D33: =SUM(D2:D32) -> 12575770 | E33: =SUM(E2:E32) -> 382326 | F33: =SUM(F2:F32) -> -4118 | G33: =SUM(G2:G32) -> 487304 | H33: =H32 -> 378208

Sheet 2024_2
A1: 日付 | C1: 売上 | D1: 支出 | E1: 入金 | F1: 不足 | G1: デリバリ | H1: 累計 | I1: BÁO CÁO THÁNG 2/2024
A2: 45323 | B2: 木 | C2: 384182 | D2: 707386 | E2: =C2-D2 -> -323204 | F2: -275 | G2: 33127 | H2: =E2+F2 -> -323479 | I2: THU
A3: 45324 | B3: 金 | C3: 815748 | D3: 250951 | E3: =C3-D3 -> 564797 | F3: 22 | G3: 11544 | H3: =H2+E3+F3 -> 241340 | I3: TỔNG | J3: SHIP BD | K3: SHIP | L3: Chênh lệch | M3: THANH TOÁN POINT
A4: 45325 | B4: 土 | C4: 739439 | D4: 509467 | E4: =C4-D4 -> 229972 | F4: -258 | G4: 0 | H4: =H3+E4+F4 -> 471054 | I4: =C33 -> 13681469 | J4: =G33 -> 486613 | L4: =F33 -> -2778 | M4: 4673
A5: 45326 | B5: 日 | C5: 441666 | D5: 225054 | E5: =C5-D5 -> 216612 | F5: -432 | G5: 47461 | H5: =H4+E5+F5 -> 687234 | J5: =J4/I4 -> 0.035567306 | K5: =K4/I4 -> 0 | L5: =L4/I4 -> -0.00020304837 | M5: =M4/I4 -> 0.00034155689
A6: 45327 | B6: 月 | C6: 398035 | D6: 485253 | E6: =C6-D6 -> -87218 | F6: 0 | G6: 14740 | H6: =H5+E6+F6 -> 600016 | I6: CHI
A7: 45328 | B7: 火 | C7: 582372 | D7: 150913 | E7: =C7-D7 -> 431459 | F7: 0 | G7: 0 | H7: =H6+E7+F7 -> 1031475 | I7: NHẬP HÀNG | J7: LƯƠNG | K7: CHI KHÁC | L7: Hỗ trợ ship BĐ | M7: TỔNG
A8: 45329 | B8: 水 | C8: 420408 | D8: 413547 | E8: =C8-D8 -> 6861 | F8: -445 | G8: 22349 | H8: =H7+E8+F8 -> 1037891 | I8: =D33 -> 11146778 | J8: =L16 -> 764180 | K8: =N19 -> 90454 | L8: =J4*0.065 -> 31629.845 | M8: =SUM(I8:L8) -> 12033042
A9: 45330 | B9: 木 | C9: 746423 | D9: 547581 | E9: =C9-D9 -> 198842 | F9: 14 | G9: 42540 | H9: =H8+E9+F9 -> 1236747 | I9: LỢI NHUẬN | J9: =I4-M8 -> 1648427.2
A10: 45331 | B10: 金 | C10: 924658 | D10: 663438 | E10: =C10-D10 -> 261220 | F10: -14 | G10: 86541 | H10: =H9+E10+F10 -> 1497953 | I10: CHI TIẾT
A11: 45332 | B11: 土 | C11: 497089 | D11: 329126 | E11: =C11-D11 -> 167963 | F11: -25 | G11: 0 | H11: =H10+E11+F11 -> 1665891 | I11: LƯƠNG - 給与
A12: 45333 | B12: 日 | C12: 345188 | D12: 338442 | E12: =C12-D12 -> 6746 | F12: -12 | G12: 0 | H12: =H11+E12+F12 -> 1672625 | I12: A. Giang | J12: A.Thái | K12: C.Hiền | L12: Nhàn | M12: Cưng | N12: Nghĩa
A13: 45334 | B13: 月 | C13: 148212 | D13: 381430 | E13: =C13-D13 -> -233218 | F13: 4 | G13: 0 | H13: =H12+E13+F13 -> 1439411 | I13: 250000 | J13: 78230 | K13: 99800 | L13: 0 | M13: 35650 | N13: 220500
A14: 45335 | B14: 火 | C14: 326298 | D14: 419279 | E14: =C14-D14 -> -92981 | F14: -312 | G14: 14541 | H14: =H13+E14+F14 -> 1346118 | I14: HỖ TRỢ
A15: 45336 | B15: 水 | C15: 258807 | D15: 224515 | E15: =C15-D15 -> 34292 | F15: 81 | G15: 0 | H15: =H14+E15+F15 -> 1380491 | I15: 80000
A16: 45337 | B16: 木 | C16: 182718 | D16: 423424 | E16: =C16-D16 -> -240706 | F16: 0 | G16: 0 | H16: =H15+E16+F16 -> 1139785 | I16: TỔNG | L16: =SUM(I13:N13)+SUM(I15:N15) -> 764180
A17: 45338 | B17: 金 | C17: 533745 | D17: 285279 | E17: =C17-D17 -> 248466 | F17: -185 | G17: 12476 | H17: =H16+E17+F17 -> 1388066 | I17: CHI KHÁC - その他
A18: 45339 | B18: 土 | C18: 676599 | D18: 628847 | E18: =C18-D18 -> 47752 | F18: -154 | G18: 47214 | H18: =H17+E18+F18 -> 1435664 | I18: TRẢ - HUỶ | J18: 社会保険 | K18: CHÊNH LỆCH | L18: XĂNG XE | M18: Khác | N18: TỔNG
A19: 45340 | B19: 日 | C19: 383164 | D19: 221500 | E19: =C19-D19 -> 161664 | F19: -87 | G19: 0 | H19: =H18+E19+F19 -> 1597241 | I19: 26544 | J19: 35000 | M19: =N23 -> 28910 | N19: =SUM(I19:M19) -> 90454
A20: 45341 | B20: 月 | C20: 306326 | D20: 21953 | E20: =C20-D20 -> 284373 | F20: 0 | G20: 14421 | H20: =H19+E20+F20 -> 1881614
A21: 45342 | B21: 火 | C21: 325288 | D21: 566204 | E21: =C21-D21 -> -240916 | F21: -124 | G21: 0 | H21: =H20+E21+F21 -> 1640574 | I21: 参考
A22: 45343 | B22: 水 | C22: 233297 | D22: 238128 | E22: =C22-D22 -> -4831 | F22: 0 | G22: 11211 | H22: =H21+E22+F22 -> 1635743 | J22: Giảm giá HD | K22: Khấu hao | L22: Bảo hiểm quán | N22: TỔNG
A23: 45344 | B23: 木 | C23: 530053 | D23: 389326 | E23: =C23-D23 -> 140727 | F23: 0 | G23: 46584 | H23: =H22+E23+F23 -> 1776470 | J23: 0 | K23: 21410 | L23: 7500 | N23: =SUM(J23:M23) -> 28910
A24: 45345 | B24: 金 | C24: 977163 | D24: 225725 | E24: =C24-D24 -> 751438 | F24: -51 | G24: 32541 | H24: =H23+E24+F24 -> 2527857
A25: 45346 | B25: 土 | C25: 872196 | D25: 299976 | E25: =C25-D25 -> 572220 | F25: 0 | G25: 0 | H25: =H24+E25+F25 -> 3100077
A26: 45347 | B26: 日 | C26: 477363 | D26: 316189 | E26: =C26-D26 -> 161174 | F26: -247 | G26: 12474 | H26: =H25+E26+F26 -> 3261004
A27: 45348 | B27: 月 | C27: 291563 | D27: 157122 | E27: =C27-D27 -> 134441 | F27: 0 | G27: 12437 | H27: =H26+E27+F27 -> 3395445
A28: 45349 | B28: 火 | C28: 224986 | D28: 835652 | E28: =C28-D28 -> -610666 | F28: -114 | G28: 0 | H28: =H27+E28+F28 -> 2784665
A29: 45350 | B29: 水 | C29: 289676 | D29: 456160 | E29: =C29-D29 -> -166484 | F29: 147 | G29: 0 | H29: =H28+E29+F29 -> 2618328
A30: 45351 | B30: 木 | C30: 348807 | D30: 434911 | E30: =C30-D30 -> -86104 | F30: -311 | G30: 24412 | H30: =H29+E30+F30 -> 2531913
E31: =C31-D31 -> 0 | H31: =H30+E31+F31 -> 2531913
E32: =C32-D32 -> 0 | H32: =H31+E32+F32 -> 2531913
A33: TỔNG | C33: =SUM(C2:C32) -> 13681469 | D33: =SUM(D2:D32) -> 11146778 | E33: =SUM(E2:E32) -> 2534691 | F33: =SUM(F2:F32) -> -2778 | G33: =SUM(G2:G32) -> 486613 | H33: =H32 -> 2531913

Sheet 2024_3
A1: 日付 | C1: 売上 | D1: 支出 | E1: 入金 | F1: 不足 | G1: デリバリ | H1: 累計 | I1: BÁO CÁO THÁNG 3/2024 | O1: Bổ sung 補足
A2: 45352 | B2: 金 | C2: 692564 | D2: 136069 | E2: =C2-D2 -> 556495 | F2: -124 | G2: 15741 | H2: =E2+F2 -> 556371 | I2: THU | O2: Bảo hiểm quán **
A3: 45353 | B3: 土 | C3: 556769 | D3: 687140 | E3: =C3-D3 -> -130371 | F3: -1414 | G3: 14256 | H3: =H2+E3+F3 -> 424586 | I3: TỔNG | J3: SHIP BD | K3: SHIP | L3: Chênh lệch | M3: THANH TOÁN POINT | O3: 44958 | P3: 44986 | Q3: 45017 | R3: 45047 | S3: 45078 | T3: 45108 | U3: 45139 | V3: 45170 | W3: 45200 | X3: 45231 | Y3: 45261 | Z3: 45292 | AA3: Tổng
A4: 45354 | B4: 日 | C4: 421592 | D4: 328525 | E4: =C4-D4 -> 93067 | F4: 0 | G4: 0 | H4: =H3+E4+F4 -> 517653 | I4: =C34 -> 13633002 | J4: =G34 -> 444786 | L4: =F34 -> -6689 | M4: 4188 | O4: 10000 | P4: 10000 | Q4: 10000 | R4: 10000 | S4: 10000 | T4: 10000 | U4: 10000 | V4: 10000 | W4: 10000 | X4: 10000 | Y4: 10000 | Z4: 10000 | AA4: =SUM(O4:Z4) -> 120000
A5: 45355 | B5: 月 | C5: 213146 | D5: 311270 | E5: =C5-D5 -> -98124 | F5: -784 | G5: 14741 | H5: =H4+E5+F5 -> 418745 | J5: =J4/I4 -> 0.032625683 | K5: =K4/I4 -> 0 | L5: =L4/I4 -> -0.00049064762 | M5: =M4/I4 -> 0.00030719573 | O5: Lương *
A6: 45356 | B6: 火 | C6: 433990 | D6: 415746 | E6: =C6-D6 -> 18244 | F6: 12 | G6: 0 | H6: =H5+E6+F6 -> 437001 | I6: CHI | O6: Anh Giang
A7: 45357 | B7: 水 | C7: 294779 | D7: 333543 | E7: =C7-D7 -> -38764 | F7: -444 | G7: 57414 | H7: =H6+E7+F7 -> 397793 | I7: NHẬP HÀNG | J7: LƯƠNG | K7: CHI KHÁC | M7: TỔNG | O7: Lương CB | P7: 250000
A8: 45358 | B8: 木 | C8: 295065 | D8: 439038 | E8: =C8-D8 -> -143973 | F8: 184 | G8: 22470 | H8: =H7+E8+F8 -> 254004 | I8: =D34 -> 11375633 | J8: =L16 -> 820500 | K8: =N19 -> 168621 | M8: =SUM(I8:L8) -> 12364754 | O8: Ship ngoài giờ | P8: 45000
A9: 45359 | B9: 金 | C9: 615598 | D9: 438792 | E9: =C9-D9 -> 176806 | F9: -421 | G9: 0 | H9: =H8+E9+F9 -> 430389 | I9: LỢI NHUẬN | J9: =I4-M8 -> 1268248 | O9: 社会保険 | P9: 35000
A10: 45360 | B10: 土 | C10: 836831 | D10: 280843 | E10: =C10-D10 -> 555988 | F10: -871 | G10: 58456 | H10: =H9+E10+F10 -> 985506 | I10: CHI TIẾT | O10: Tổng | P10: =SUM(P7:P9) -> 330000
A11: 45361 | B11: 日 | C11: 321861 | D11: 197748 | E11: =C11-D11 -> 124113 | F11: 0 | G11: 0 | H11: =H10+E11+F11 -> 1109619 | I11: LƯƠNG - 給与
A12: 45362 | B12: 月 | C12: 220345 | D12: 493244 | E12: =C12-D12 -> -272899 | F12: 0 | G12: 12411 | H12: =H11+E12+F12 -> 836720 | I12: A. Giang | J12: A.Thái | K12: C.Hiền | L12: Nhàn | M12: Cưng | N12: Nghĩa
A13: 45363 | B13: 火 | C13: 393796 | D13: 61992 | E13: =C13-D13 -> 331804 | F13: 0 | G13: 0 | H13: =H12+E13+F13 -> 1168524 | I13: 333000 | J13: 93000 | K13: 138000 | L13: 0 | M13: 35500 | N13: 221000
A14: 45364 | B14: 水 | C14: 352701 | D14: 52700 | E14: =C14-D14 -> 300001 | F14: 5 | G14: 0 | H14: =H13+E14+F14 -> 1468530 | I14: HỖ TRỢ
A15: 45365 | B15: 木 | C15: 324686 | D15: 1345060 | E15: =C15-D15 -> -1020374 | F15: 0 | G15: 14764 | H15: =H14+E15+F15 -> 448156 | I15: 0
A16: 45366 | B16: 金 | C16: 728484 | D16: 22388 | E16: =C16-D16 -> 706096 | F16: -55 | G16: 0 | H16: =H15+E16+F16 -> 1154197 | I16: TỔNG | L16: =SUM(I13:N13)+SUM(I15:N15) -> 820500
A17: 45367 | B17: 土 | C17: 594156 | D17: 317298 | E17: =C17-D17 -> 276858 | F17: 0 | G17: 47854 | H17: =H16+E17+F17 -> 1431055 | I17: CHI KHÁC - その他
A18: 45368 | B18: 日 | C18: 232005 | D18: 234361 | E18: =C18-D18 -> -2356 | F18: -578 | G18: 0 | H18: =H17+E18+F18 -> 1428121 | M18: Khác | N18: TỔNG
A19: 45369 | B19: 月 | C19: 307885 | D19: 223106 | E19: =C19-D19 -> 84779 | F19: -564 | G19: 4641 | H19: =H18+E19+F19 -> 1512336 | M19: =N23 -> 168621 | N19: =SUM(I19:M19) -> 168621
A20: 45370 | B20: 火 | C20: 0 | D20: 60733 | E20: =C20-D20 -> -60733 | F20: 0 | G20: 0 | H20: =H19+E20+F20 -> 1451603
A21: 45371 | B21: 水 | C21: 489871 | D21: 484176 | E21: =C21-D21 -> 5695 | F21: 0 | G21: 48994 | H21: =H20+E21+F21 -> 1457298 | I21: 参考
A22: 45372 | B22: 木 | C22: 364669 | D22: 397620 | E22: =C22-D22 -> -32951 | F22: -474 | G22: 0 | H22: =H21+E22+F22 -> 1423873 | I22: Giảm giá HD | J22: Khấu hao | K22: Wifi | L22: Bảo hiểm quán ** | M22: TRẢ - HUỶ | N22: TỔNG
A23: 45373 | B23: 金 | C23: 663176 | D23: 92555 | E23: =C23-D23 -> 570621 | F23: 0 | G23: 12104 | H23: =H22+E23+F23 -> 1994494 | I23: 0 | J23: 0 | K23: 5750 | L23: 120000 | M23: 42871 | N23: =SUM(J23:M23) -> 168621
A24: 45374 | B24: 土 | C24: 366937 | D24: 524919 | E24: =C24-D24 -> -157982 | F24: -98 | G24: 14765 | H24: =H23+E24+F24 -> 1836414
A25: 45375 | B25: 日 | C25: 227750 | D25: 357220 | E25: =C25-D25 -> -129470 | F25: 0 | G25: 0 | H25: =H24+E25+F25 -> 1706944
A26: 45376 | B26: 月 | C26: 384333 | D26: 753991 | E26: =C26-D26 -> -369658 | F26: 0 | G26: 47410 | H26: =H25+E26+F26 -> 1337286
A27: 45377 | B27: 火 | C27: 494327 | D27: 225724 | E27: =C27-D27 -> 268603 | F27: -471 | G27: 11478 | H27: =H26+E27+F27 -> 1605418
A28: 45378 | B28: 水 | C28: 461253 | D28: 395686 | E28: =C28-D28 -> 65567 | F28: 0 | G28: 0 | H28: =H27+E28+F28 -> 1670985
A29: 45379 | B29: 木 | C29: 395610 | D29: 294392 | E29: =C29-D29 -> 101218 | F29: -75 | G29: 0 | H29: =H28+E29+F29 -> 1772128
A30: 45380 | B30: 金 | C30: 769714 | D30: 654943 | E30: =C30-D30 -> 114771 | F30: 0 | G30: 21546 | H30: =H29+E30+F30 -> 1886899
A31: 45381 | B31: 土 | C31: 728067 | D31: 378801 | E31: =C31-D31 -> 349266 | F31: -44 | G31: 25741 | H31: =H30+E31+F31 -> 2236121
A32: 45382 | B32: 日 | C32: 451042 | D32: 436010 | E32: =C32-D32 -> 15032 | F32: -473 | H32: =H31+E32+F32 -> 2250680
H33: =H32+E33+F33 -> 2250680
A34: TỔNG | C34: =SUM(C2:C32) -> 13633002 | D34: =SUM(D2:D33) -> 11375633 | E34: =SUM(E2:E32) -> 2257369 | F34: =SUM(F2:F32) -> -6689 | G34: =SUM(G2:G32) -> 444786 | H34: =H32 -> 2250680

Sheet 2024_4
A1: 日付 | C1: 売上 | D1: 支出 | E1: 入金 | F1: 不足 | G1: デリバリ | H1: 累計 | I1: BÁO CÁO THÁNG 4/2024 | O1: Bổ sung 補足
A2: 45383 | B2: 月 | C2: 244323 | D2: 1173885 | E2: =C2-D2 -> -929562 | F2: -22 | H2: =E2+F2 -> -929584 | I2: THU | O2: Bảo hiểm quán **
A3: 45384 | B3: 火 | C3: 351575 | D3: 392225 | E3: =C3-D3 -> -40650 | F3: 0 | H3: =H2+E3+F3 -> -970234 | I3: TỔNG | J3: SHIP BD | K3: SHIP | L3: Chênh lệch | M3: THANH TOÁN POINT | AA3: Tổng
A4: 45385 | B4: 水 | C4: 219752 | D4: 671308 | E4: =C4-D4 -> -451556 | F4: -584 | H4: =H3+E4+F4 -> -1422374 | I4: =C33 -> 14451749 | J4: =G33 -> 0 | L4: =F33 -> -5444 | M4: 5319 | AA4: =SUM(O4:Z4) -> 0
A5: 45386 | B5: 木 | C5: 247792 | D5: 125969 | E5: =C5-D5 -> 121823 | F5: 0 | H5: =H4+E5+F5 -> -1300551 | J5: =J4/I4 -> 0 | K5: =K4/I4 -> 0 | L5: =L4/I4 -> -0.00037670181 | M5: =M4/I4 -> 0.00036805234 | O5: Lương *
A6: 45387 | B6: 金 | C6: 760386 | D6: 497252 | E6: =C6-D6 -> 263134 | F6: 0 | H6: =H5+E6+F6 -> -1037417 | I6: CHI | O6: Anh Giang
A7: 45388 | B7: 土 | C7: 682697 | D7: 141292 | E7: =C7-D7 -> 541405 | F7: 18 | H7: =H6+E7+F7 -> -495994 | I7: NHẬP HÀNG | J7: LƯƠNG | K7: CHI KHÁC | M7: TỔNG | O7: Lương CB | P7: 250000
A8: 45389 | B8: 日 | C8: 423920 | D8: 52370 | E8: =C8-D8 -> 371550 | F8: -284 | H8: =H7+E8+F8 -> -124728 | I8: =D33 -> 12350411 | J8: =L16 -> 810000 | K8: =N19 -> 90604 | M8: =SUM(I8:L8) -> 13251015 | O8: Ship ngoài giờ | P8: 80000
A9: 45390 | B9: 月 | C9: 253687 | D9: 575671 | E9: =C9-D9 -> -321984 | F9: -11 | H9: =H8+E9+F9 -> -446723 | I9: LỢI NHUẬN | J9: =I4-M8 -> 1200734 | O9: 社会保険 | P9: 35000
A10: 45391 | B10: 火 | C10: 349830 | D10: 99340 | E10: =C10-D10 -> 250490 | F10: 0 | H10: =H9+E10+F10 -> -196233 | I10: CHI TIẾT | O10: Tổng | P10: =SUM(P7:P9) -> 365000
A11: 45392 | B11: 水 | C11: 446683 | D11: 549457 | E11: =C11-D11 -> -102774 | F11: -871 | H11: =H10+E11+F11 -> -299878 | I11: LƯƠNG - 給与
A12: 45393 | B12: 木 | C12: 544461 | D12: 520157 | E12: =C12-D12 -> 24304 | F12: -1112 | H12: =H11+E12+F12 -> -276686 | I12: A. Giang | J12: A.Thái | K12: C.Hiền | L12: Nhàn | M12: Cưng | N12: Nghĩa
A13: 45394 | B13: 金 | C13: 714325 | D13: 497379 | E13: =C13-D13 -> 216946 | F13: 0 | H13: =H12+E13+F13 -> -59740 | I13: =P10 -> 365000 | J13: 76250 | K13: 105500 | L13: 0 | M13: 39750 | N13: 223500
A14: 45395 | B14: 土 | C14: 710872 | D14: 127459 | E14: =C14-D14 -> 583413 | F14: 9 | H14: =H13+E14+F14 -> 523682 | I14: HỖ TRỢ
A15: 45396 | B15: 日 | C15: 360245 | D15: 226328 | E15: =C15-D15 -> 133917 | F15: -547 | H15: =H14+E15+F15 -> 657052 | I15: 0
A16: 45397 | B16: 月 | C16: 300163 | D16: 167358 | E16: =C16-D16 -> 132805 | F16: 22 | H16: =H15+E16+F16 -> 789879 | I16: TỔNG | L16: =SUM(I13:N13)+SUM(I15:N15) -> 810000
A17: 45398 | B17: 火 | C17: 383586 | D17: 78492 | E17: =C17-D17 -> 305094 | F17: 0 | H17: =H16+E17+F17 -> 1094973 | I17: CHI KHÁC - その他
A18: 45399 | B18: 水 | C18: 326849 | D18: 187618 | E18: =C18-D18 -> 139231 | F18: -57 | H18: =H17+E18+F18 -> 1234147 | M18: Khác | N18: TỔNG
A19: 45400 | B19: 木 | C19: 286872 | D19: 656689 | E19: =C19-D19 -> -369817 | F19: -114 | H19: =H18+E19+F19 -> 864216 | M19: =N23 -> 90604 | N19: =SUM(I19:M19) -> 90604
A20: 45401 | B20: 金 | C20: 597385 | D20: 125130 | E20: =C20-D20 -> 472255 | F20: 2 | H20: =H19+E20+F20 -> 1336473
A21: 45402 | B21: 土 | C21: 691749 | D21: 311889 | E21: =C21-D21 -> 379860 | F21: -74 | H21: =H20+E21+F21 -> 1716259 | I21: 参考
A22: 45403 | B22: 日 | C22: 268077 | D22: 448434 | E22: =C22-D22 -> -180357 | F22: -411 | H22: =H21+E22+F22 -> 1535491 | I22: Giảm giá HD | J22: Khấu hao | K22: Wifi | L22: Bảo hiểm quán ** | M22: TRẢ - HUỶ | N22: TỔNG
A23: 45404 | B23: 月 | C23: 269105 | D23: 41141 | E23: =C23-D23 -> 227964 | F23: 0 | H23: =H22+E23+F23 -> 1763455 | I23: 0 | J23: 0 | K23: 5750 | L23: 10000 | M23: 74854 | N23: =SUM(J23:M23) -> 90604
A24: 45405 | B24: 火 | C24: 378278 | D24: 246841 | E24: =C24-D24 -> 131437 | F24: -411 | H24: =H23+E24+F24 -> 1894481
A25: 45406 | B25: 水 | C25: 466892 | D25: 626889 | E25: =C25-D25 -> -159997 | F25: 0 | H25: =H24+E25+F25 -> 1734484
A26: 45407 | B26: 木 | C26: 415616 | D26: 328664 | E26: =C26-D26 -> 86952 | F26: 0 | H26: =H25+E26+F26 -> 1821436
A27: 45408 | B27: 金 | C27: 1016328 | D27: 729430 | E27: =C27-D27 -> 286898 | F27: -124 | H27: =H26+E27+F27 -> 2108210
A28: 45409 | B28: 土 | C28: 1136278 | D28: 375971 | E28: =C28-D28 -> 760307 | F28: -754 | H28: =H27+E28+F28 -> 2867763
A29: 45410 | B29: 日 | C29: 679193 | D29: 868705 | E29: =C29-D29 -> -189512 | F29: -75 | H29: =H28+E29+F29 -> 2678176
A30: 45411 | B30: 月 | C30: 451549 | D30: 156067 | E30: =C30-D30 -> 295482 | F30: 0 | H30: =H29+E30+F30 -> 2973658
A31: 45412 | B31: 火 | C31: 473281 | D31: 1351001 | E31: =C31-D31 -> -877720 | F31: -44 | H31: =H30+E31+F31 -> 2095894
E32: =C32-D32 -> 0 | H32: =H31+E32+F32 -> 2095894
A33: TỔNG | C33: =SUM(C2:C32) -> 14451749 | D33: =SUM(D2:D32) -> 12350411 | E33: =SUM(E2:E32) -> 2101338 | F33: =SUM(F2:F32) -> -5444 | G33: =SUM(G2:G32) -> 0 | H33: =H32 -> 2095894

Sheet 2024_5
A1: 日付 | C1: 売上 | D1: 支出 | E1: 入金 | F1: 不足 | G1: デリバリ | H1: 累計 | I1: BÁO CÁO THÁNG 5/2024 | O1: Bổ sung 補足
A2: 45413 | B2: 水 | C2: 390386 | D2: 561562 | E2: =C2-D2 -> -171176 | F2: -214 | G2: 0 | H2: =E2+F2 -> -171390 | I2: THU | O2: Bảo hiểm quán **
A3: 45414 | B3: 木 | C3: 476534 | D3: 519038 | E3: =C3-D3 -> -42504 | F3: 0 | G3: 0 | H3: =H2+E3+F3 -> -213894 | I3: TỔNG | J3: SHIP BD | K3: SHIP | L3: Chênh lệch | M3: THANH TOÁN POINT
A4: 45415 | B4: 金 | C4: 802779 | D4: 726167 | E4: =C4-D4 -> 76612 | F4: -22 | G4: 0 | H4: =H3+E4+F4 -> -137304 | I4: =C33 -> 14861786 | J4: =G33 -> 0 | L4: =F33 -> -4409 | M4: 13618
A5: 45416 | B5: 土 | C5: 548178 | D5: 981781 | E5: =C5-D5 -> -433603 | F5: 0 | G5: 0 | H5: =H4+E5+F5 -> -570907 | J5: =J4/I4 -> 0 | K5: =K4/I4 -> 0 | L5: =L4/I4 -> -0.0002966669 | M5: =M4/I4 -> 0.00091630979 | O5: Lương *
A6: 45417 | B6: 日 | C6: 448866 | D6: 171570 | E6: =C6-D6 -> 277296 | F6: -41 | G6: 0 | H6: =H5+E6+F6 -> -293652 | I6: CHI | O6: Anh Giang
A7: 45418 | B7: 月 | C7: 362652 | D7: 995783 | E7: =C7-D7 -> -633131 | F7: 0 | G7: 0 | H7: =H6+E7+F7 -> -926783 | I7: NHẬP HÀNG | J7: LƯƠNG | K7: CHI KHÁC | M7: TỔNG | O7: Lương CB | P7: 250000
A8: 45419 | B8: 火 | C8: 295361 | D8: 178340 | E8: =C8-D8 -> 117021 | F8: 41 | G8: 0 | H8: =H7+E8+F8 -> -809721 | I8: =D33 -> 12783005 | J8: =L16 -> 810750 | K8: =N19 -> 88291 | M8: =SUM(I8:L8) -> 13682046 | O8: Ship ngoài giờ | P8: 50000
A9: 45420 | B9: 水 | C9: 330094 | D9: 235627 | E9: =C9-D9 -> 94467 | F9: -241 | G9: 0 | H9: =H8+E9+F9 -> -715495 | I9: LỢI NHUẬN | J9: =I4-M8 -> 1179740 | O9: 社会保険 | P9: 35000
A10: 45421 | B10: 木 | C10: 344503 | D10: 645380 | E10: =C10-D10 -> -300877 | F10: 3 | G10: 0 | H10: =H9+E10+F10 -> -1016369 | I10: CHI TIẾT | O10: Tổng | P10: =SUM(P7:P9) -> 335000
A11: 45422 | B11: 金 | C11: 763910 | D11: 283471 | E11: =C11-D11 -> 480439 | F11: -471 | G11: 0 | H11: =H10+E11+F11 -> -536401 | I11: LƯƠNG - 給与 | O11: TÀI SẢN CÔNG TY
A12: 45423 | B12: 土 | C12: 854093 | D12: 292214 | E12: =C12-D12 -> 561879 | F12: -224 | G12: 0 | H12: =H11+E12+F12 -> 25254 | I12: A. Giang | J12: A.Thái | K12: C.Hiền | L12: Nhàn | M12: Cưng | N12: Nghĩa | O12: LỢI NHUẬN GỘP
A13: 45424 | B13: 日 | C13: 348979 | D13: 298548 | E13: =C13-D13 -> 50431 | F13: 0 | G13: 0 | H13: =H12+E13+F13 -> 75685 | I13: =P10 -> 335000 | J13: 74100 | K13: 124350 | L13: 0 | M13: 41800 | N13: 235500 | O13: TIỀN MẶT | Q13: JPY
A14: 45425 | B14: 月 | C14: 470618 | D14: 609654 | E14: =C14-D14 -> -139036 | F14: 0 | G14: 0 | H14: =H13+E14+F14 -> -63351 | I14: HỖ TRỢ | Q14: VND
A15: 45426 | B15: 火 | C15: 269892 | D15: 595998 | E15: =C15-D15 -> -326106 | F15: 0 | G15: 0 | H15: =H14+E15+F15 -> -389457 | I15: 0 | O15: ATM | P15: CÁ NHÂN
A16: 45427 | B16: 水 | C16: 278669 | D16: 256911 | E16: =C16-D16 -> 21758 | F16: -447 | G16: 0 | H16: =H15+E16+F16 -> -368146 | I16: TỔNG | L16: =SUM(I13:N13)+SUM(I15:N15) -> 810750 | P16: CÔNG TY
A17: 45428 | B17: 木 | C17: 345144 | D17: 390472 | E17: =C17-D17 -> -45328 | F17: 0 | G17: 0 | H17: =H16+E17+F17 -> -413474 | I17: CHI KHÁC - その他 | O17: NỢ | P17: KHÁCH NỢ
A18: 45429 | B18: 金 | C18: 770934 | D18: 734188 | E18: =C18-D18 -> 36746 | F18: -574 | G18: 0 | H18: =H17+E18+F18 -> -377302 | M18: Khác | N18: TỔNG | O18: TIỀN $ CÁC KHOẢN TƯƠNG ĐƯƠNG
A19: 45430 | B19: 土 | C19: 680427 | D19: 477976 | E19: =C19-D19 -> 202451 | F19: -574 | G19: 0 | H19: =H18+E19+F19 -> -175425 | M19: =N23 -> 88291 | N19: =SUM(I19:M19) -> 88291 | O19: GIÁ TRỊ KHO ƯỚC TÍNH
A20: 45431 | B20: 日 | C20: 303179 | D20: 220641 | E20: =C20-D20 -> 82538 | F20: -44 | G20: 0 | H20: =H19+E20+F20 -> -92931 | O20: TÀI SẢN DÀI HẠN
A21: 45432 | B21: 月 | C21: 317481 | D21: 106775 | E21: =C21-D21 -> 210706 | F21: 0 | G21: 0 | H21: =H20+E21+F21 -> 117775 | I21: 参考 | O21: TỔNG | R21: =SUM(R12:R20) -> 0
A22: 45433 | B22: 火 | C22: 299753 | D22: 331432 | E22: =C22-D22 -> -31679 | F22: -274 | G22: 0 | H22: =H21+E22+F22 -> 85822 | I22: Giảm giá HD | J22: Khấu hao HĐ | K22: Wifi | L22: Bảo hiểm quán ** | M22: TRẢ - HUỶ | N22: TỔNG
A23: 45434 | B23: 水 | C23: 248921 | D23: 276543 | E23: =C23-D23 -> -27622 | F23: -541 | G23: 0 | H23: =H22+E23+F23 -> 57659 | I23: 0 | J23: 0 | K23: 5750 | L23: 10000 | M23: 72541 | N23: =SUM(J23:M23) -> 88291
A24: 45435 | B24: 木 | C24: 264736 | D24: 170243 | E24: =C24-D24 -> 94493 | F24: 0 | G24: 0 | H24: =H23+E24+F24 -> 152152
A25: 45436 | B25: 金 | C25: 777588 | D25: 377001 | E25: =C25-D25 -> 400587 | F25: -54 | G25: 0 | H25: =H24+E25+F25 -> 552685
A26: 45437 | B26: 土 | C26: 1030774 | D26: 58316 | E26: =C26-D26 -> 972458 | F26: 0 | G26: 0 | H26: =H25+E26+F26 -> 1525143
A27: 45438 | B27: 日 | C27: 502815 | D27: 219989 | E27: =C27-D27 -> 282826 | F27: -41 | G27: 0 | H27: =H26+E27+F27 -> 1807928
A28: 45439 | B28: 月 | C28: 344579 | D28: 174710 | E28: =C28-D28 -> 169869 | F28: -23 | G28: 0 | H28: =H27+E28+F28 -> 1977774
A29: 45440 | B29: 火 | C29: 307967 | D29: 416112 | E29: =C29-D29 -> -108145 | F29: -54 | G29: 0 | H29: =H28+E29+F29 -> 1869575
A30: 45441 | B30: 水 | C30: 366297 | D30: 262840 | E30: =C30-D30 -> 103457 | F30: 0 | G30: 0 | H30: =H29+E30+F30 -> 1973032
A31: 45442 | B31: 木 | C31: 507425 | D31: 436420 | E31: =C31-D31 -> 71005 | F31: -44 | G31: 0 | H31: =H30+E31+F31 -> 2043993
A32: 45443 | B32: 金 | C32: 808252 | D32: 777303 | E32: =C32-D32 -> 30949 | F32: -570 | G32: 0 | H32: =H31+E32+F32 -> 2074372
A33: TỔNG | C33: =SUM(C2:C32) -> 14861786 | D33: =SUM(D2:D32) -> 12783005 | E33: =SUM(E2:E32) -> 2078781 | F33: =SUM(F2:F32) -> -4409 | G33: =SUM(G2:G32) -> 0 | H33: =H32 -> 2074372

Sheet 2024_6
A1: 日付 | C1: 売上 | D1: 支出 | E1: 入金 | F1: 不足 | G1: デリバリ | H1: 累計 | I1: BÁO CÁO THÁNG 6/2024 | O1: Bổ sung 補足
A2: 45444 | B2: 土 | C2: 701674 | D2: 704366 | E2: =C2-D2 -> -2692 | F2: -784 | G2: 0 | H2: =E2+F2 -> -3476 | I2: THU | O2: Bảo hiểm quán **
A3: 45445 | B3: 日 | C3: 441567 | D3: 229663 | E3: =C3-D3 -> 211904 | F3: 0 | G3: 0 | H3: =H2+E3+F3 -> 208428 | I3: TỔNG | J3: SHIP BD | K3: SHIP | L3: Chênh lệch | M3: THANH TOÁN POINT
A4: 45446 | B4: 月 | C4: 290385 | D4: 424954 | E4: =C4-D4 -> -134569 | F4: 2 | G4: 0 | H4: =H3+E4+F4 -> 73861 | I4: =C33 -> 14766013 | J4: =G33 -> 0 | L4: =F33 -> -4058 | M4: 5042
A5: 45447 | B5: 火 | C5: 376733 | D5: 173763 | E5: =C5-D5 -> 202970 | F5: -442 | G5: 0 | H5: =H4+E5+F5 -> 276389 | J5: =J4/I4 -> 0 | K5: =K4/I4 -> 0 | L5: =L4/I4 -> -0.00027482029 | M5: =M4/I4 -> 0.00034145981 | O5: Lương *
A6: 45448 | B6: 水 | C6: 303935 | D6: 164032 | E6: =C6-D6 -> 139903 | F6: -224 | G6: 0 | H6: =H5+E6+F6 -> 416068 | I6: CHI | O6: Anh Giang
A7: 45449 | B7: 木 | C7: 299137 | D7: 448469 | E7: =C7-D7 -> -149332 | F7: 0 | G7: 0 | H7: =H6+E7+F7 -> 266736 | I7: NHẬP HÀNG | J7: LƯƠNG | K7: CHI KHÁC | M7: TỔNG | O7: Lương CB | P7: 250000
A8: 45450 | B8: 金 | C8: 521825 | D8: 222945 | E8: =C8-D8 -> 298880 | F8: 0 | G8: 0 | H8: =H7+E8+F8 -> 565616 | I8: =D33 -> 13216237 | J8: =L16 -> 790950 | K8: =N19 -> 68291 | M8: =SUM(I8:L8) -> 14075478 | O8: Ship ngoài giờ | P8: 55000
A9: 45451 | B9: 土 | C9: 646964 | D9: 711566 | E9: =C9-D9 -> -64602 | F9: -4 | G9: 0 | H9: =H8+E9+F9 -> 501010 | I9: LỢI NHUẬN | J9: =I4-M8 -> 690535 | O9: 社会保険 | P9: 35000
A10: 45452 | B10: 日 | C10: 367776 | D10: 275000 | E10: =C10-D10 -> 92776 | F10: -18 | G10: 0 | H10: =H9+E10+F10 -> 593768 | I10: CHI TIẾT | O10: Tổng | P10: =SUM(P7:P9) -> 340000
A11: 45453 | B11: 月 | C11: 394733 | D11: 486810 | E11: =C11-D11 -> -92077 | F11: -22 | G11: 0 | H11: =H10+E11+F11 -> 501669 | I11: LƯƠNG - 給与 | O11: TÀI SẢN CÔNG TY
A12: 45454 | B12: 火 | C12: 434717 | D12: 480466 | E12: =C12-D12 -> -45749 | F12: 0 | G12: 0 | H12: =H11+E12+F12 -> 455920 | I12: A. Giang | J12: A.Thái | K12: C.Hiền | L12: Nhàn | M12: Cưng | N12: Nghĩa | O12: LỢI NHUẬN GỘP
A13: 45455 | B13: 水 | C13: 407925 | D13: 83255 | E13: =C13-D13 -> 324670 | F13: -44 | G13: 0 | H13: =H12+E13+F13 -> 780546 | I13: =P10 -> 340000 | J13: 61000 | K13: 118550 | L13: 0 | M13: 43900 | N13: 227500 | O13: TIỀN MẶT | Q13: JPY
A14: 45456 | B14: 木 | C14: 317657 | D14: 512805 | E14: =C14-D14 -> -195148 | F14: -124 | G14: 0 | H14: =H13+E14+F14 -> 585274 | I14: HỖ TRỢ | Q14: VND
A15: 45457 | B15: 金 | C15: 737690 | D15: 467936 | E15: =C15-D15 -> 269754 | F15: 0 | G15: 0 | H15: =H14+E15+F15 -> 855028 | I15: 0 | O15: ATM | P15: CÁ NHÂN
A16: 45458 | B16: 土 | C16: 900479 | D16: 689464 | E16: =C16-D16 -> 211015 | F16: 6 | G16: 0 | H16: =H15+E16+F16 -> 1066049 | I16: TỔNG | L16: =SUM(I13:N13)+SUM(I15:N15) -> 790950 | P16: CÔNG TY
A17: 45459 | B17: 日 | C17: 507917 | D17: 502602 | E17: =C17-D17 -> 5315 | F17: -410 | G17: 0 | H17: =H16+E17+F17 -> 1070954 | I17: CHI KHÁC - その他 | O17: NỢ | P17: KHÁCH NỢ
A18: 45460 | B18: 月 | C18: 185048 | D18: 226617 | E18: =C18-D18 -> -41569 | F18: 0 | G18: 0 | H18: =H17+E18+F18 -> 1029385 | M18: Khác | N18: TỔNG | O18: TIỀN $ CÁC KHOẢN TƯƠNG ĐƯƠNG
A19: 45461 | B19: 火 | C19: 419388 | D19: 873731 | E19: =C19-D19 -> -454343 | F19: -411 | G19: 0 | H19: =H18+E19+F19 -> 574631 | M19: =N23 -> 68291 | N19: =SUM(I19:M19) -> 68291 | O19: GIÁ TRỊ KHO ƯỚC TÍNH
A20: 45462 | B20: 水 | C20: 443239 | D20: 364689 | E20: =C20-D20 -> 78550 | F20: 0 | G20: 0 | H20: =H19+E20+F20 -> 653181 | O20: TÀI SẢN DÀI HẠN
A21: 45463 | B21: 木 | C21: 341845 | D21: 555120 | E21: =C21-D21 -> -213275 | F21: -22 | G21: 0 | H21: =H20+E21+F21 -> 439884 | I21: 参考 | O21: TỔNG | R21: =SUM(R12:R20) -> 0
A22: 45464 | B22: 金 | C22: 641775 | D22: 528929 | E22: =C22-D22 -> 112846 | F22: 6 | G22: 0 | H22: =H21+E22+F22 -> 552736 | I22: Giảm giá HD | J22: Khấu hao HĐ | K22: Wifi | L22: Bảo hiểm quán ** | M22: TRẢ - HUỶ | N22: TỔNG
A23: 45465 | B23: 土 | C23: 543723 | D23: 614056 | E23: =C23-D23 -> -70333 | F23: -415 | G23: 0 | H23: =H22+E23+F23 -> 481988 | I23: 0 | J23: 0 | K23: 5750 | L23: 10000 | M23: 52541 | N23: =SUM(J23:M23) -> 68291
A24: 45466 | B24: 日 | C24: 391057 | D24: 435931 | E24: =C24-D24 -> -44874 | F24: -24 | G24: 0 | H24: =H23+E24+F24 -> 437090
A25: 45467 | B25: 月 | C25: 250382 | D25: 260333 | E25: =C25-D25 -> -9951 | F25: 0 | G25: 0 | H25: =H24+E25+F25 -> 427139
A26: 45468 | B26: 火 | C26: 415703 | D26: 112642 | E26: =C26-D26 -> 303061 | F26: -64 | G26: 0 | H26: =H25+E26+F26 -> 730136
A27: 45469 | B27: 水 | C27: 548250 | D27: 247932 | E27: =C27-D27 -> 300318 | F27: -58 | G27: 0 | H27: =H26+E27+F27 -> 1030396
A28: 45470 | B28: 木 | C28: 580123 | D28: 317447 | E28: =C28-D28 -> 262676 | F28: -984 | G28: 0 | H28: =H27+E28+F28 -> 1292088
A29: 45471 | B29: 金 | C29: 818938 | D29: 586320 | E29: =C29-D29 -> 232618 | F29: -22 | G29: 0 | H29: =H28+E29+F29 -> 1524684
A30: 45472 | B30: 土 | C30: 909322 | D30: 513654 | E30: =C30-D30 -> 395668 | F30: 0 | G30: 0 | H30: =H29+E30+F30 -> 1920352
A31: 45473 | B31: 日 | C31: 426106 | D31: 664440 | E31: =C31-D31 -> -238334 | F31: 0 | G31: 0 | H31: =H30+E31+F31 -> 1682018
C32: 200000 | D32: 336300 | E32: =C32-D32 -> -136300 | H32: =H31+E32+F32 -> 1545718
A33: TỔNG | C33: =SUM(C2:C32) -> 14766013 | D33: =SUM(D2:D32) -> 13216237 | E33: =SUM(E2:E32) -> 1549776 | F33: =SUM(F2:F32) -> -4058 | G33: =SUM(G2:G32) -> 0 | H33: =H32 -> 1545718

Sheet 2024_7
A1: 日付 | C1: 売上 | D1: 支出 | E1: 入金 | F1: 不足 | G1: デリバリ | H1: 累計 | I1: BÁO CÁO THÁNG | O1: Bổ sung 補足
A2: 45474 | B2: 月 | C2: 314389 | D2: 189330 | E2: =C2-D2 -> 125059 | F2: -241 | G2: 0 | H2: =E2+F2 -> 124818 | I2: THU | O2: Bảo hiểm quán **
A3: 45475 | B3: 火 | C3: 389267 | D3: 408296 | E3: =C3-D3 -> -19029 | F3: -2 | G3: 0 | H3: =H2+E3+F3 -> 105787 | I3: TỔNG | J3: SHIP BD | K3: SHIP | L3: Chênh lệch | M3: THANH TOÁN POINT
A4: 45476 | B4: 水 | C4: 244820 | D4: 555286 | E4: =C4-D4 -> -310466 | F4: -47 | G4: 0 | H4: =H3+E4+F4 -> -204726 | I4: =C34 -> 15215209 | J4: =G34 -> 0 | L4: =F34 -> -7619 | M4: 11738
A5: 45477 | B5: 木 | C5: 318846 | D5: 571956 | E5: =C5-D5 -> -253110 | F5: -787 | G5: 0 | H5: =H4+E5+F5 -> -458623 | J5: =J4/I4 -> 0 | K5: =K4/I4 -> 0 | L5: =L4/I4 -> -0.00050074895 | M5: =M4/I4 -> 0.00077146492 | O5: Lương *
A6: 45478 | B6: 金 | C6: 818101 | D6: 394671 | E6: =C6-D6 -> 423430 | F6: 21 | G6: 0 | H6: =H5+E6+F6 -> -35172 | I6: CHI | O6: Anh Giang
A7: 45479 | B7: 土 | C7: 525832 | D7: 388306 | E7: =C7-D7 -> 137526 | F7: -574 | G7: 0 | H7: =H6+E7+F7 -> 101780 | I7: NHẬP HÀNG | J7: LƯƠNG | K7: CHI KHÁC | M7: TỔNG | O7: Lương CB | P7: 250000
A8: 45480 | B8: 日 | C8: 537601 | D8: 102926 | E8: =C8-D8 -> 434675 | F8: -244 | G8: 0 | H8: =H7+E8+F8 -> 536211 | I8: =D34 -> 12928037 | J8: =L16 -> 776600 | K8: =N19 -> 80004 | M8: =SUM(I8:L8) -> 13784641 | O8: Ship ngoài giờ | P8: 55000
A9: 45481 | B9: 月 | C9: 215047 | D9: 528624 | E9: =C9-D9 -> -313577 | F9: 0 | G9: 0 | H9: =H8+E9+F9 -> 222634 | I9: LỢI NHUẬN | J9: =I4-M8 -> 1430568 | O9: 社会保険 | P9: 35000
A10: 45482 | B10: 火 | C10: 296074 | D10: 420559 | E10: =C10-D10 -> -124485 | F10: -441 | G10: 0 | H10: =H9+E10+F10 -> 97708 | I10: CHI TIẾT | O10: Tổng | P10: =SUM(P7:P9) -> 340000
A11: 45483 | B11: 水 | C11: 315719 | D11: 325585 | E11: =C11-D11 -> -9866 | F11: -748 | G11: 0 | H11: =H10+E11+F11 -> 87094 | I11: LƯƠNG - 給与 | O11: TÀI SẢN CÔNG TY
A12: 45484 | B12: 木 | C12: 570723 | D12: 350634 | E12: =C12-D12 -> 220089 | F12: 0 | G12: 0 | H12: =H11+E12+F12 -> 307183 | I12: A. Giang | J12: A.Thái | K12: C.Hiền | L12: Nhàn | M12: Cưng | N12: Nghĩa | O12: LỢI NHUẬN GỘP
A13: 45485 | B13: 金 | C13: 859380 | D13: 413809 | E13: =C13-D13 -> 445571 | F13: -874 | G13: 0 | H13: =H12+E13+F13 -> 751880 | I13: =P10 -> 340000 | J13: 61000 | K13: 111500 | L13: 0 | M13: 45100 | N13: 219000 | O13: TIỀN MẶT | Q13: JPY
A14: 45486 | B14: 土 | C14: 1182813 | D14: 301035 | E14: =C14-D14 -> 881778 | F14: -584 | G14: 0 | H14: =H13+E14+F14 -> 1633074 | I14: HỖ TRỢ | Q14: VND
A15: 45487 | B15: 日 | C15: 295368 | D15: 901751 | E15: =C15-D15 -> -606383 | F15: -254 | G15: 0 | H15: =H14+E15+F15 -> 1026437 | I15: 0 | O15: ATM | P15: CÁ NHÂN
A16: 45488 | B16: 月 | C16: 451614 | D16: 650822 | E16: =C16-D16 -> -199208 | F16: 0 | G16: 0 | H16: =H15+E16+F16 -> 827229 | I16: TỔNG | L16: =SUM(I13:N13)+SUM(I15:N15) -> 776600 | P16: CÔNG TY
A17: 45489 | B17: 火 | C17: 461987 | D17: 251535 | E17: =C17-D17 -> 210452 | F17: -541 | G17: 0 | H17: =H16+E17+F17 -> 1037140 | I17: CHI KHÁC - その他 | O17: NỢ | P17: KHÁCH NỢ
A18: 45490 | B18: 水 | C18: 541338 | D18: 247347 | E18: =C18-D18 -> 293991 | F18: 0 | G18: 0 | H18: =H17+E18+F18 -> 1331131 | M18: Khác | N18: TỔNG | O18: TIỀN $ CÁC KHOẢN TƯƠNG ĐƯƠNG
A19: 45491 | B19: 木 | C19: 382996 | D19: 465447 | E19: =C19-D19 -> -82451 | F19: -541 | G19: 0 | H19: =H18+E19+F19 -> 1248139 | M19: =N23 -> 80004 | N19: =SUM(I19:M19) -> 80004 | O19: GIÁ TRỊ KHO ƯỚC TÍNH
A20: 45492 | B20: 金 | C20: 695360 | D20: 449277 | E20: =C20-D20 -> 246083 | F20: -47 | G20: 0 | H20: =H19+E20+F20 -> 1494175 | O20: TÀI SẢN DÀI HẠN
A21: 45493 | B21: 土 | C21: 560008 | D21: 387354 | E21: =C21-D21 -> 172654 | F21: -41 | G21: 0 | H21: =H20+E21+F21 -> 1666788 | I21: 参考 | O21: TỔNG | R21: =SUM(R12:R20) -> 0
A22: 45494 | B22: 日 | C22: 373995 | D22: 401447 | E22: =C22-D22 -> -27452 | F22: -44 | G22: 0 | H22: =H21+E22+F22 -> 1639292 | I22: Giảm giá HD | J22: Khấu hao HĐ | K22: Wifi | L22: Bảo hiểm quán ** | M22: TRẢ - HUỶ | N22: TỔNG
A23: 45495 | B23: 月 | C23: 346489 | D23: 269217 | E23: =C23-D23 -> 77272 | F23: 0 | G23: 0 | H23: =H22+E23+F23 -> 1716564 | I23: 0 | J23: 0 | K23: 5750 | L23: 10000 | M23: 64254 | N23: =SUM(J23:M23) -> 80004 | O23: NỢ + CÁC KHOẢN VAY
A24: 45496 | B24: 火 | C24: 244955 | D24: 342840 | E24: =C24-D24 -> -97885 | F24: 0 | G24: 0 | H24: =H23+E24+F24 -> 1618679 | O24: NỢ NGẮN HẠN
A25: 45497 | B25: 水 | C25: 230412 | D25: 502509 | E25: =C25-D25 -> -272097 | F25: 47 | G25: 0 | H25: =H24+E25+F25 -> 1346629
A26: 45498 | B26: 木 | C26: 632059 | D26: 375824 | E26: =C26-D26 -> 256235 | F26: -87 | G26: 0 | H26: =H25+E26+F26 -> 1602777
A27: 45499 | B27: 金 | C27: 887598 | D27: 244310 | E27: =C27-D27 -> 643288 | F27: -644 | G27: 0 | H27: =H26+E27+F27 -> 2245421
A28: 45500 | B28: 土 | C28: 973829 | D28: 329333 | E28: =C28-D28 -> 644496 | F28: -474 | G28: 0 | H28: =H27+E28+F28 -> 2889443
A29: 45501 | B29: 日 | C29: 396596 | D29: 647936 | E29: =C29-D29 -> -251340 | F29: -11 | G29: 0 | H29: =H28+E29+F29 -> 2638092 | O29: NỢ DÀI HẠN
A30: 45502 | B30: 月 | C30: 438785 | D30: 241385 | E30: =C30-D30 -> 197400 | F30: 0 | G30: 0 | H30: =H29+E30+F30 -> 2835492
A31: 45503 | B31: 火 | C31: 361024 | D31: 211406 | E31: =C31-D31 -> 149618 | F31: -47 | G31: 0 | H31: =H30+E31+F31 -> 2985063
A32: 45504 | B32: 水 | C32: 352184 | D32: 907280 | E32: =C32-D32 -> -555096 | F32: -414 | G32: 0 | H32: =H31+E32+F32 -> 2429553
C33: 0 | D33: 150000 | E33: =C33-D33 -> -150000 | H33: =H32+E33+F33 -> 2279553
A34: TỔNG | C34: =SUM(C2:C33) -> 15215209 | D34: =SUM(D2:D33) -> 12928037 | E34: =SUM(E2:E32) -> 2437172 | F34: =SUM(F2:F32) -> -7619 | G34: =SUM(G2:G32) -> 0 | H34: =C34-D34 -> 2287172

Sheet 2024_8
A1: 日付 | C1: 売上 | D1: 支出 | E1: 入金 | F1: 不足 | G1: デリバリ | H1: 累計 | I1: BÁO CÁO THÁNG 08/2024 | O1: Bổ sung 補足
A2: 45505 | B2: 木 | C2: 241654 | D2: 512223 | E2: =C2-D2 -> -270569 | F2: -845 | G2: 0 | H2: =E2+F2 -> -271414 | I2: THU | O2: Bảo hiểm quán **
A3: 45506 | B3: 金 | C3: 842537 | D3: 668272 | E3: =C3-D3 -> 174265 | F3: 3 | G3: 0 | H3: =H2+E3+F3 -> -97146 | I3: TỔNG | J3: SHIP BD | K3: SHIP | L3: Chênh lệch | M3: THANH TOÁN POINT
A4: 45507 | B4: 土 | C4: 638016 | D4: 556053 | E4: =C4-D4 -> 81963 | F4: -8 | G4: 0 | H4: =H3+E4+F4 -> -15191 | I4: =C34 -> 15855146 | J4: =G34 -> 0 | L4: =F34 -> -1069 | M4: 9763
A5: 45508 | B5: 日 | C5: 391360 | D5: 110052 | E5: =C5-D5 -> 281308 | F5: -2 | G5: 0 | H5: =H4+E5+F5 -> 266115 | J5: =J4/I4 -> 0 | K5: =K4/I4 -> 0 | L5: =L4/I4 -> -6.7422905e-05 | M5: =M4/I4 -> 0.00061576223 | O5: Lương *
A6: 45509 | B6: 月 | C6: 9433 | D6: 33399 | E6: =C6-D6 -> -23966 | F6: 0 | G6: 0 | H6: =H5+E6+F6 -> 242149 | I6: CHI | O6: Anh Giang
A7: 45510 | B7: 火 | C7: 360808 | D7: 403902 | E7: =C7-D7 -> -43094 | F7: 0 | G7: 0 | H7: =H6+E7+F7 -> 199055 | I7: NHẬP HÀNG | J7: LƯƠNG | K7: CHI KHÁC | M7: TỔNG | O7: Lương CB | P7: =I13 -> 300000
A8: 45511 | B8: 水 | C8: 321655 | D8: 694073 | E8: =C8-D8 -> -372418 | F8: -54 | G8: 0 | H8: =H7+E8+F8 -> -173417 | I8: =D34 -> 13948130 | J8: =L16 -> 858500 | K8: =N19 -> 95492 | M8: =SUM(I8:L8) -> 14902122 | O8: Ship ngoài giờ | P8: 55000
A9: 45512 | B9: 木 | C9: 592359 | D9: 553004 | E9: =C9-D9 -> 39355 | F9: -12 | G9: 0 | H9: =H8+E9+F9 -> -134074 | I9: LỢI NHUẬN | J9: =I4-M8-M4+L4 -> 942192 | O9: 社会保険 | P9: 35000
A10: 45513 | B10: 金 | C10: 922656 | D10: 316092 | E10: =C10-D10 -> 606564 | F10: 0 | G10: 0 | H10: =H9+E10+F10 -> 472490 | I10: CHI TIẾT | O10: Tổng | P10: =SUM(P7:P9) -> 390000
A11: 45514 | B11: 土 | C11: 990424 | D11: 506362 | E11: =C11-D11 -> 484062 | F11: -12 | G11: 0 | H11: =H10+E11+F11 -> 956540 | I11: LƯƠNG - 給与 | O11: TÀI SẢN CÔNG TY
A12: 45515 | B12: 日 | C12: 568069 | D12: 908158 | E12: =C12-D12 -> -340089 | F12: 4 | G12: 0 | H12: =H11+E12+F12 -> 616455 | I12: A. Giang | J12: A.Thái | K12: C.Hiền | L12: Nhàn | M12: Cưng | N12: Nghĩa | O12: LỢI NHUẬN GỘP
A13: 45516 | B13: 月 | C13: 556491 | D13: 388598 | E13: =C13-D13 -> 167893 | F13: -7 | G13: 0 | H13: =H12+E13+F13 -> 784341 | I13: 300000 | J13: 74500 | K13: 137500 | L13: 0 | M13: 54500 | N13: 202000 | O13: TIỀN MẶT | Q13: JPY
A14: 45517 | B14: 火 | C14: 325783 | D14: 471128 | E14: =C14-D14 -> -145345 | F14: 0 | G14: 0 | H14: =H13+E14+F14 -> 638996 | I14: HỖ TRỢ | Q14: VND
A15: 45518 | B15: 水 | C15: 624046 | D15: 401925 | E15: =C15-D15 -> 222121 | F15: 0 | G15: 0 | H15: =H14+E15+F15 -> 861117 | I15: 0 | O15: ATM | P15: CÁ NHÂN
A16: 45519 | B16: 木 | C16: 476878 | D16: 398122 | E16: =C16-D16 -> 78756 | F16: 2 | G16: 0 | H16: =H15+E16+F16 -> 939875 | I16: TỔNG | L16: =SUM(J13:N13)+SUM(I15:N15)+P10 -> 858500 | P16: CÔNG TY
A17: 45520 | B17: 金 | C17: 626962 | D17: 310764 | E17: =C17-D17 -> 316198 | F17: -7 | G17: 0 | H17: =H16+E17+F17 -> 1256066 | I17: CHI KHÁC - その他 | O17: NỢ | P17: KHÁCH NỢ
A18: 45521 | B18: 土 | C18: 609664 | D18: 618543 | E18: =C18-D18 -> -8879 | F18: 0 | G18: 0 | H18: =H17+E18+F18 -> 1247187 | M18: Khác | N18: TỔNG | O18: TIỀN $ CÁC KHOẢN TƯƠNG ĐƯƠNG
A19: 45522 | B19: 日 | C19: 315979 | D19: 487796 | E19: =C19-D19 -> -171817 | F19: 0 | G19: 0 | H19: =H18+E19+F19 -> 1075370 | M19: =N23 -> 95492 | N19: =SUM(I19:M19) -> 95492 | O19: GIÁ TRỊ KHO ƯỚC TÍNH
A20: 45523 | B20: 月 | C20: 323976 | D20: 465375 | E20: =C20-D20 -> -141399 | F20: 0 | G20: 0 | H20: =H19+E20+F20 -> 933971 | O20: TÀI SẢN DÀI HẠN
A21: 45524 | B21: 火 | C21: 479823 | D21: 54511 | E21: =C21-D21 -> 425312 | F21: -14 | G21: 0 | H21: =H20+E21+F21 -> 1359269 | I21: 参考 | O21: TỔNG | R21: =SUM(R12:R20) -> 0
A22: 45525 | B22: 水 | C22: 265350 | D22: 597168 | E22: =C22-D22 -> -331818 | F22: 0 | G22: 0 | H22: =H21+E22+F22 -> 1027451 | I22: Giảm giá HD | J22: Khấu hao HĐ | K22: Wifi | L22: Bảo hiểm quán ** | M22: TRẢ - HUỶ | N22: TỔNG
A23: 45526 | B23: 木 | C23: 546590 | D23: 344122 | E23: =C23-D23 -> 202468 | F23: 0 | G23: 0 | H23: =H22+E23+F23 -> 1229919 | I23: 0 | J23: 0 | K23: 5750 | L23: 10000 | M23: 79742 | N23: =SUM(J23:M23) -> 95492 | O23: NỢ + CÁC KHOẢN VAY
A24: 45527 | B24: 金 | C24: 990436 | D24: 445455 | E24: =C24-D24 -> 544981 | F24: 8 | G24: 0 | H24: =H23+E24+F24 -> 1774908 | O24: NỢ NGẮN HẠN
A25: 45528 | B25: 土 | C25: 995391 | D25: 519691 | E25: =C25-D25 -> 475700 | F25: 0 | G25: 0 | H25: =H24+E25+F25 -> 2250608
A26: 45529 | B26: 日 | C26: 312176 | D26: 250777 | E26: =C26-D26 -> 61399 | F26: -84 | G26: 0 | H26: =H25+E26+F26 -> 2311923
A27: 45530 | B27: 月 | C27: 319145 | D27: 360381 | E27: =C27-D27 -> -41236 | F27: 0 | G27: 0 | H27: =H26+E27+F27 -> 2270687
A28: 45531 | B28: 火 | C28: 342559 | D28: 888574 | E28: =C28-D28 -> -546015 | F28: 0 | G28: 0 | H28: =H27+E28+F28 -> 1724672
A29: 45532 | B29: 水 | C29: 382551 | D29: 629275 | E29: =C29-D29 -> -246724 | F29: 0 | G29: 0 | H29: =H28+E29+F29 -> 1477948 | O29: NỢ DÀI HẠN
A30: 45533 | B30: 木 | C30: 6657 | D30: 0 | E30: =C30-D30 -> 6657 | F30: 0 | G30: 0 | H30: =H29+E30+F30 -> 1484605
A31: 45534 | B31: 金 | C31: 679048 | D31: 244643 | E31: =C31-D31 -> 434405 | F31: -17 | G31: 0 | H31: =H30+E31+F31 -> 1918993
A32: 45535 | B32: 土 | C32: 796670 | D32: 699692 | E32: =C32-D32 -> 96978 | F32: -24 | G32: 0 | H32: =H31+E32+F32 -> 2015947
C33: 0 | D33: 110000 | E33: =C33-D33 -> -110000 | H33: =H32+E33+F33 -> 1905947
A34: TỔNG | C34: =SUM(C2:C33) -> 15855146 | D34: =SUM(D2:D33) -> 13948130 | E34: =SUM(E2:E32) -> 2017016 | F34: =SUM(F2:F32) -> -1069 | G34: =SUM(G2:G32) -> 0 | H34: =C34-D34 -> 1907016

Sheet 2024_9
A1: 日付 | C1: 売上 | D1: 支出 | E1: 入金 | F1: 不足 | G1: デリバリ | H1: 累計 | I1: BÁO CÁO THÁNG 09/2024 | O1: Bổ sung 補足
A2: 45536 | B2: 日 | C2: 477797 | D2: 81068 | E2: =C2-D2 -> 396729 | F2: -12 | G2: 0 | H2: =E2+F2 -> 396717 | I2: THU | O2: Bảo hiểm quán **
A3: 45537 | B3: 月 | C3: 388575 | D3: 180198 | E3: =C3-D3 -> 208377 | F3: 0 | G3: 0 | H3: =H2+E3+F3 -> 605094 | I3: TỔNG | J3: SHIP BD | K3: SHIP | L3: Chênh lệch | M3: THANH TOÁN POINT
A4: 45538 | B4: 火 | C4: 442109 | D4: 623129 | E4: =C4-D4 -> -181020 | F4: 0 | G4: 0 | H4: =H3+E4+F4 -> 424074 | I4: =C34 -> 15487068 | J4: =G34 -> 0 | L4: =F34 -> -2648 | M4: 7787
A5: 45539 | B5: 水 | C5: 299831 | D5: 510152 | E5: =C5-D5 -> -210321 | F5: 0 | G5: 0 | H5: =H4+E5+F5 -> 213753 | J5: =J4/I4 -> 0 | K5: =K4/I4 -> 0 | L5: =L4/I4 -> -0.00017098136 | M5: =M4/I4 -> 0.0005028066 | O5: Lương *
A6: 45540 | B6: 木 | C6: 494740 | D6: 495862 | E6: =C6-D6 -> -1122 | F6: -871 | G6: 0 | H6: =H5+E6+F6 -> 211760 | I6: CHI | O6: Anh Giang
A7: 45541 | B7: 金 | C7: 773487 | D7: 378731 | E7: =C7-D7 -> 394756 | F7: 0 | G7: 0 | H7: =H6+E7+F7 -> 606516 | I7: NHẬP HÀNG | J7: LƯƠNG | K7: CHI KHÁC | M7: TỔNG | O7: Lương CB | P7: =I13 -> 300000
A8: 45542 | B8: 土 | C8: 646028 | D8: 392520 | E8: =C8-D8 -> 253508 | F8: -274 | G8: 0 | H8: =H7+E8+F8 -> 859750 | I8: =D34 -> 13735791 | J8: =L16 -> 847500 | K8: =N19 -> 84130 | M8: =SUM(I8:L8) -> 14667421 | O8: Ship ngoài giờ | P8: 55000
A9: 45543 | B9: 日 | C9: 368937 | D9: 622698 | E9: =C9-D9 -> -253761 | F9: 0 | G9: 0 | H9: =H8+E9+F9 -> 605989 | I9: LỢI NHUẬN | J9: =I4-M8-M4+L4 -> 809212 | O9: 社会保険 | P9: 35000
A10: 45544 | B10: 月 | C10: 436320 | D10: 148886 | E10: =C10-D10 -> 287434 | F10: -411 | G10: 0 | H10: =H9+E10+F10 -> 893012 | I10: CHI TIẾT | O10: Tổng | P10: =SUM(P7:P9) -> 390000
A11: 45545 | B11: 火 | C11: 410008 | D11: 626100 | E11: =C11-D11 -> -216092 | F11: 0 | G11: 0 | H11: =H10+E11+F11 -> 676920 | I11: LƯƠNG - 給与 | O11: TÀI SẢN CÔNG TY
A12: 45546 | B12: 水 | C12: 714027 | D12: 647399 | E12: =C12-D12 -> 66628 | F12: -14 | G12: 0 | H12: =H11+E12+F12 -> 743534 | I12: A. Giang | J12: A.Thái | K12: C.Hiền | L12: Nhàn | M12: Cưng | N12: Nghĩa | O12: LỢI NHUẬN GỘP
A13: 45547 | B13: 木 | C13: 590777 | D13: 694833 | E13: =C13-D13 -> -104056 | F13: 2 | G13: 0 | H13: =H12+E13+F13 -> 639480 | I13: 300000 | J13: 82000 | K13: 125000 | L13: 0 | M13: 53000 | N13: 197500 | O13: TIỀN MẶT | Q13: JPY
A14: 45548 | B14: 金 | C14: 854142 | D14: 527728 | E14: =C14-D14 -> 326414 | F14: 0 | G14: 0 | H14: =H13+E14+F14 -> 965894 | I14: HỖ TRỢ | Q14: VND
A15: 45549 | B15: 土 | C15: 836303 | D15: 496672 | E15: =C15-D15 -> 339631 | F15: -8 | G15: 0 | H15: =H14+E15+F15 -> 1305517 | I15: 0 | O15: ATM | P15: CÁ NHÂN
A16: 45550 | B16: 日 | C16: 409243 | D16: 523196 | E16: =C16-D16 -> -113953 | F16: 0 | G16: 0 | H16: =H15+E16+F16 -> 1191564 | I16: TỔNG | L16: =SUM(J13:N13)+SUM(I15:N15)+P10 -> 847500 | P16: CÔNG TY
A17: 45551 | B17: 月 | C17: 471921 | D17: 841696 | E17: =C17-D17 -> -369775 | F17: -471 | G17: 0 | H17: =H16+E17+F17 -> 821318 | I17: CHI KHÁC - その他 | O17: NỢ | P17: KHÁCH NỢ
A18: 45552 | B18: 火 | C18: 302688 | D18: 274871 | E18: =C18-D18 -> 27817 | F18: -11 | G18: 0 | H18: =H17+E18+F18 -> 849124 | M18: Khác | N18: TỔNG | O18: TIỀN $ CÁC KHOẢN TƯƠNG ĐƯƠNG
A19: 45553 | B19: 水 | C19: 457706 | D19: 251250 | E19: =C19-D19 -> 206456 | F19: 0 | G19: 0 | H19: =H18+E19+F19 -> 1055580 | M19: =N23 -> 84130 | N19: =SUM(I19:M19) -> 84130 | O19: GIÁ TRỊ KHO ƯỚC TÍNH
A20: 45554 | B20: 木 | C20: 382562 | D20: 342514 | E20: =C20-D20 -> 40048 | F20: 0 | G20: 0 | H20: =H19+E20+F20 -> 1095628 | O20: TÀI SẢN DÀI HẠN
A21: 45555 | B21: 金 | C21: 519011 | D21: 636196 | E21: =C21-D21 -> -117185 | F21: 0 | G21: 0 | H21: =H20+E21+F21 -> 978443 | I21: 参考 | O21: TỔNG | R21: =SUM(R12:R20) -> 0
A22: 45556 | B22: 土 | C22: 526174 | D22: 388679 | E22: =C22-D22 -> 137495 | F22: -71 | G22: 0 | H22: =H21+E22+F22 -> 1115867 | I22: Giảm giá HD | J22: Khấu hao HĐ | K22: Wifi | L22: Bảo hiểm quán ** | M22: TRẢ - HUỶ | N22: TỔNG
A23: 45557 | B23: 日 | C23: 417234 | D23: 354298 | E23: =C23-D23 -> 62936 | F23: 0 | G23: 0 | H23: =H22+E23+F23 -> 1178803 | I23: 0 | J23: 0 | K23: 5750 | L23: 10000 | M23: 68380 | N23: =SUM(J23:M23) -> 84130 | O23: NỢ + CÁC KHOẢN VAY
A24: 45558 | B24: 月 | C24: 338801 | D24: 147823 | E24: =C24-D24 -> 190978 | F24: -14 | G24: 0 | H24: =H23+E24+F24 -> 1369767 | O24: NỢ NGẮN HẠN
A25: 45559 | B25: 火 | C25: 256706 | D25: 241029 | E25: =C25-D25 -> 15677 | F25: -41 | G25: 0 | H25: =H24+E25+F25 -> 1385403
A26: 45560 | B26: 水 | C26: 385921 | D26: 559891 | E26: =C26-D26 -> -173970 | F26: 0 | G26: 0 | H26: =H25+E26+F26 -> 1211433
A27: 45561 | B27: 木 | C27: 595613 | D27: 198064 | E27: =C27-D27 -> 397549 | F27: -41 | G27: 0 | H27: =H26+E27+F27 -> 1608941
A28: 45562 | B28: 金 | C28: 1130048 | D28: 324805 | E28: =C28-D28 -> 805243 | F28: -411 | G28: 0 | H28: =H27+E28+F28 -> 2413773
A29: 45563 | B29: 土 | C29: 797518 | D29: 374283 | E29: =C29-D29 -> 423235 | F29: 0 | G29: 0 | H29: =H28+E29+F29 -> 2837008 | O29: NỢ DÀI HẠN
A30: 45564 | B30: 日 | C30: 480377 | D30: 1098677 | E30: =C30-D30 -> -618300 | F30: 0 | G30: 0 | H30: =H29+E30+F30 -> 2218708
A31: 45565 | B31: 月 | C31: 282464 | D31: 682543 | E31: =C31-D31 -> -400079 | F31: 0 | G31: 0 | H31: =H30+E31+F31 -> 1818629
E32: =C32-D32 -> 0 | G32: 0 | H32: =H31+E32+F32 -> 1818629
C33: 0 | D33: 70000 | E33: =C33-D33 -> -70000 | H33: =H32+E33+F33 -> 1748629
A34: TỔNG | C34: =SUM(C2:C33) -> 15487068 | D34: =SUM(D2:D33) -> 13735791 | E34: =SUM(E2:E32) -> 1821277 | F34: =SUM(F2:F32) -> -2648 | G34: =SUM(G2:G32) -> 0 | H34: =C34-D34 -> 1751277

Sheet 2024_10
A1: 日付 | C1: 売上 | D1: 支出 | E1: 入金 | F1: 不足 | G1: デリバリ | H1: 累計 | I1: BÁO CÁO THÁNG 10/2024 | O1: Bổ sung 補足
A2: 45566 | B2: 火 | C2: 264920 | D2: 363443 | E2: =C2-D2 -> -98523 | F2: -254 | G2: 0 | H2: =E2+F2 -> -98777 | I2: THU | O2: Bảo hiểm quán **
A3: 45567 | B3: 水 | C3: 380606 | D3: 259134 | E3: =C3-D3 -> 121472 | F3: 0 | G3: 0 | H3: =H2+E3+F3 -> 22695 | I3: TỔNG | J3: SHIP BD | K3: SHIP | L3: Chênh lệch | M3: THANH TOÁN POINT
A4: 45568 | B4: 木 | C4: 521468 | D4: 397185 | E4: =C4-D4 -> 124283 | F4: -415 | G4: 0 | H4: =H3+E4+F4 -> 146563 | I4: =C34 -> 16255296 | J4: =G34 -> 0 | L4: =F34 -> -6386 | M4: 7926
A5: 45569 | B5: 金 | C5: 724577 | D5: 561463 | E5: =C5-D5 -> 163114 | F5: -582 | G5: 0 | H5: =H4+E5+F5 -> 309095 | J5: =J4/I4 -> 0 | K5: =K4/I4 -> 0 | L5: =L4/I4 -> -0.00039285658 | M5: =M4/I4 -> 0.00048759494 | O5: Lương *
A6: 45570 | B6: 土 | C6: 526124 | D6: 451465 | E6: =C6-D6 -> 74659 | F6: -125 | G6: 0 | H6: =H5+E6+F6 -> 383629 | I6: CHI | O6: Anh Giang
A7: 45571 | B7: 日 | C7: 439784 | D7: 356803 | E7: =C7-D7 -> 82981 | F7: 0 | G7: 0 | H7: =H6+E7+F7 -> 466610 | I7: NHẬP HÀNG | J7: LƯƠNG | K7: CHI KHÁC | M7: TỔNG | O7: Lương CB | P7: =I13 -> 340000
A8: 45572 | B8: 月 | C8: 262054 | D8: 147370 | E8: =C8-D8 -> 114684 | F8: -441 | G8: 0 | H8: =H7+E8+F8 -> 580853 | I8: =D34 -> 14036193 | J8: =L16 -> 957500 | K8: =N19 -> 126130 | M8: =SUM(I8:L8) -> 15119823 | O8: Ship ngoài giờ | P8: 55000
A9: 45573 | B9: 火 | C9: 409882 | D9: 173762 | E9: =C9-D9 -> 236120 | F9: -54 | G9: 0 | H9: =H8+E9+F9 -> 816919 | I9: LỢI NHUẬN | J9: =I4-M8-M4+L4 -> 1121161 | O9: 社会保険 | P9: 35000
A10: 45574 | B10: 水 | C10: 353721 | D10: 484111 | E10: =C10-D10 -> -130390 | F10: -574 | G10: 0 | H10: =H9+E10+F10 -> 685955 | I10: CHI TIẾT | O10: Tổng | P10: =SUM(P7:P9) -> 430000
A11: 45575 | B11: 木 | C11: 658459 | D11: 516398 | E11: =C11-D11 -> 142061 | F11: 0 | G11: 0 | H11: =H10+E11+F11 -> 828016 | I11: LƯƠNG - 給与 | O11: TÀI SẢN CÔNG TY
A12: 45576 | B12: 金 | C12: 1096333 | D12: 428590 | E12: =C12-D12 -> 667743 | F12: 0 | G12: 0 | H12: =H11+E12+F12 -> 1495759 | I12: A. Giang | J12: A.Thái | K12: C.Hiền | L12: Nhàn | M12: Cưng | N12: Nghĩa | O12: LỢI NHUẬN GỘP
A13: 45577 | B13: 土 | C13: 1111405 | D13: 410837 | E13: =C13-D13 -> 700568 | F13: -454 | G13: 0 | H13: =H12+E13+F13 -> 2195873 | I13: 340000 | J13: 51000 | K13: 125500 | L13: 28000 | M13: 55000 | N13: 220000 | O13: TIỀN MẶT | Q13: JPY
A14: 45578 | B14: 日 | C14: 360317 | D14: 767854 | E14: =C14-D14 -> -407537 | F14: -84 | G14: 0 | H14: =H13+E14+F14 -> 1788252 | Q14: VND
A15: 45579 | B15: 月 | C15: 347179 | D15: 950660 | E15: =C15-D15 -> -603481 | F15: -74 | G15: 0 | H15: =H14+E15+F15 -> 1184697 | I15: 0 | M15: Hoàn | N15: 48000 | O15: ATM | P15: CÁ NHÂN
A16: 45580 | B16: 火 | C16: 335378 | D16: 232331 | E16: =C16-D16 -> 103047 | F16: 0 | G16: 0 | H16: =H15+E16+F16 -> 1287744 | I16: TỔNG | L16: =SUM(J13:N13)+SUM(I15:N15)+P10 -> 957500 | P16: CÔNG TY
A17: 45581 | B17: 水 | C17: 505920 | D17: 317061 | E17: =C17-D17 -> 188859 | F17: -44 | G17: 0 | H17: =H16+E17+F17 -> 1476559 | I17: CHI KHÁC - その他 | O17: NỢ | P17: KHÁCH NỢ
A18: 45582 | B18: 木 | C18: 508020 | D18: 890689 | E18: =C18-D18 -> -382669 | F18: -74 | G18: 0 | H18: =H17+E18+F18 -> 1093816 | M18: Khác | N18: TỔNG | O18: TIỀN $ CÁC KHOẢN TƯƠNG ĐƯƠNG
A19: 45583 | B19: 金 | C19: 623337 | D19: 863742 | E19: =C19-D19 -> -240405 | F19: 0 | G19: 0 | H19: =H18+E19+F19 -> 853411 | M19: =N23 -> 126130 | N19: =SUM(I19:M19) -> 126130 | O19: GIÁ TRỊ KHO ƯỚC TÍNH
A20: 45584 | B20: 土 | C20: 407209 | D20: 443904 | E20: =C20-D20 -> -36695 | F20: 0 | G20: 0 | H20: =H19+E20+F20 -> 816716 | O20: TÀI SẢN DÀI HẠN
A21: 45585 | B21: 日 | C21: 374751 | D21: 73699 | E21: =C21-D21 -> 301052 | F21: -741 | G21: 0 | H21: =H20+E21+F21 -> 1117027 | I21: 参考 | O21: TỔNG | R21: =SUM(R12:R20) -> 0
A22: 45586 | B22: 月 | C22: 336788 | D22: 102019 | E22: =C22-D22 -> 234769 | F22: -584 | G22: 0 | H22: =H21+E22+F22 -> 1351212 | I22: Giảm giá HD | J22: Khấu hao HĐ | K22: Wifi | L22: Bảo hiểm quán ** | M22: TRẢ - HUỶ | N22: TỔNG
A23: 45587 | B23: 火 | C23: 303088 | D23: 269685 | E23: =C23-D23 -> 33403 | F23: 0 | G23: 0 | H23: =H22+E23+F23 -> 1384615 | I23: 0 | J23: 0 | K23: 5750 | L23: 22000 | M23: 98380 | N23: =SUM(J23:M23) -> 126130 | O23: NỢ + CÁC KHOẢN VAY
A24: 45588 | B24: 水 | C24: 248407 | D24: 195332 | E24: =C24-D24 -> 53075 | F24: -85 | G24: 0 | H24: =H23+E24+F24 -> 1437605 | O24: NỢ NGẮN HẠN
A25: 45589 | B25: 木 | C25: 492265 | D25: 187161 | E25: =C25-D25 -> 305104 | F25: 0 | G25: 0 | H25: =H24+E25+F25 -> 1742709
A26: 45590 | B26: 金 | C26: 1234567 | D26: 402678 | E26: =C26-D26 -> 831889 | F26: -74 | G26: 0 | H26: =H25+E26+F26 -> 2574524
A27: 45591 | B27: 土 | C27: 1192480 | D27: 376538 | E27: =C27-D27 -> 815942 | F27: 1 | G27: 0 | H27: =H26+E27+F27 -> 3390467
A28: 45592 | B28: 日 | C28: 492084 | D28: 654425 | E28: =C28-D28 -> -162341 | F28: -77 | G28: 0 | H28: =H27+E28+F28 -> 3228049
A29: 45593 | B29: 月 | C29: 475211 | D29: 773466 | E29: =C29-D29 -> -298255 | F29: -456 | G29: 0 | H29: =H28+E29+F29 -> 2929338 | O29: NỢ DÀI HẠN
A30: 45594 | B30: 火 | C30: 383715 | D30: 417729 | E30: =C30-D30 -> -34014 | F30: -754 | G30: 0 | H30: =H29+E30+F30 -> 2894570
A31: 45595 | B31: 水 | C31: 399969 | D31: 373887 | E31: =C31-D31 -> 26082 | F31: 0 | G31: 0 | H31: =H30+E31+F31 -> 2920652
A32: 45596 | B32: 木 | C32: 485278 | D32: 542772 | E32: =C32-D32 -> -57494 | F32: -441 | G32: 0 | H32: =H31+E32+F32 -> 2862717
C33: 0 | D33: =300000+150000+200000 -> 650000 | E33: =C33-D33 -> -650000 | H33: =H32+E33+F33 -> 2212717
A34: TỔNG | C34: =SUM(C2:C33) -> 16255296 | D34: =SUM(D2:D33) -> 14036193 | E34: =SUM(E2:E32) -> 2869103 | F34: =SUM(F2:F32) -> -6386 | G34: =SUM(G2:G32) -> 0 | H34: =C34-D34 -> 2219103

Sheet 2024_11
A1: 日付 | C1: 売上 | D1: 支出 | E1: 入金 | F1: 不足 | G1: デリバリ | H1: 累計 | I1: BÁO CÁO THÁNG 11/2024 | O1: Bổ sung 補足
A2: 45597 | B2: 金 | C2: 1015447 | D2: 780873 | E2: =C2-D2 -> 234574 | F2: -14 | G2: 0 | H2: =E2+F2 -> 234560 | I2: THU | O2: Bảo hiểm quán **
A3: 45598 | B3: 土 | C3: 747841 | D3: 572699 | E3: =C3-D3 -> 175142 | F3: -447 | G3: 0 | H3: =H2+E3+F3 -> 409255 | I3: TỔNG | J3: SHIP BD | K3: SHIP | L3: Chênh lệch | M3: THANH TOÁN POINT
A4: 45599 | B4: 日 | C4: 577165 | D4: 213082 | E4: =C4-D4 -> 364083 | F4: 0 | G4: 0 | H4: =H3+E4+F4 -> 773338 | I4: =C34 -> 17425659 | J4: =G34 -> 0 | L4: =F34 -> -4217 | M4: 20234
A5: 45600 | B5: 月 | C5: 443530 | D5: 475990 | E5: =C5-D5 -> -32460 | F5: 0 | G5: 0 | H5: =H4+E5+F5 -> 740878 | J5: =J4/I4 -> 0 | K5: =K4/I4 -> 0 | L5: =L4/I4 -> -0.00024199946 | M5: =M4/I4 -> 0.0011611613 | O5: Lương *
A6: 45601 | B6: 火 | C6: 406374 | D6: 544677 | E6: =C6-D6 -> -138303 | F6: -74 | G6: 0 | H6: =H5+E6+F6 -> 602501 | I6: CHI | O6: Anh Giang
A7: 45602 | B7: 水 | C7: 290616 | D7: 431521 | E7: =C7-D7 -> -140905 | F7: -41 | G7: 0 | H7: =H6+E7+F7 -> 461555 | I7: NHẬP HÀNG | J7: LƯƠNG | K7: CHI KHÁC | M7: TỔNG | O7: Lương CB | P7: =I13 -> 340000
A8: 45603 | B8: 木 | C8: 381785 | D8: 326166 | E8: =C8-D8 -> 55619 | F8: -411 | G8: 0 | H8: =H7+E8+F8 -> 516763 | I8: =D34 -> 15441818 | J8: =L16 -> 986930 | K8: =N19 -> 116004 | M8: =SUM(I8:L8) -> 16544752 | O8: Ship ngoài giờ | P8: 55000
A9: 45604 | B9: 金 | C9: 764937 | D9: 441049 | E9: =C9-D9 -> 323888 | F9: 0 | G9: 0 | H9: =H8+E9+F9 -> 840651 | I9: LỢI NHUẬN | J9: =I4-M8-M4+L4 -> 856456 | O9: 社会保険 | P9: 35000
A10: 45605 | B10: 土 | C10: 726422 | D10: 616898 | E10: =C10-D10 -> 109524 | F10: 0 | G10: 0 | H10: =H9+E10+F10 -> 950175 | I10: CHI TIẾT | O10: Tổng | P10: =SUM(P7:P9) -> 430000
A11: 45606 | B11: 日 | C11: 320632 | D11: 485994 | E11: =C11-D11 -> -165362 | F11: -44 | G11: 0 | H11: =H10+E11+F11 -> 784769 | I11: LƯƠNG - 給与 | O11: TÀI SẢN CÔNG TY
A12: 45607 | B12: 月 | C12: 482556 | D12: 217684 | E12: =C12-D12 -> 264872 | F12: -741 | G12: 0 | H12: =H11+E12+F12 -> 1048900 | I12: A. Giang | J12: A.Thái | K12: C.Hiền | L12: Nhàn | M12: Cưng | N12: Nghĩa | O12: LỢI NHUẬN GỘP
A13: 45608 | B13: 火 | C13: 563304 | D13: 471159 | E13: =C13-D13 -> 92145 | F13: 0 | G13: 0 | H13: =H12+E13+F13 -> 1141045 | I13: 340000 | J13: 59500 | K13: 125000 | L13: 48000 | M13: 52000 | N13: 227000 | O13: TIỀN MẶT | Q13: JPY
A14: 45609 | B14: 水 | C14: 560878 | D14: 634492 | E14: =C14-D14 -> -73614 | F14: 0 | G14: 0 | H14: =H13+E14+F14 -> 1067431 | Q14: VND
A15: 45610 | B15: 木 | C15: 654239 | D15: 413732 | E15: =C15-D15 -> 240507 | F15: -415 | G15: 0 | H15: =H14+E15+F15 -> 1307523 | I15: 0 | M15: HOÀN | N15: 45430 | O15: ATM | P15: CÁ NHÂN
A16: 45611 | B16: 金 | C16: 900529 | D16: 784182 | E16: =C16-D16 -> 116347 | F16: 0 | G16: 0 | H16: =H15+E16+F16 -> 1423870 | I16: TỔNG | L16: =SUM(J13:N13)+SUM(I15:N15)+P10 -> 986930 | P16: CÔNG TY
A17: 45612 | B17: 土 | C17: 968344 | D17: 654125 | E17: =C17-D17 -> 314219 | F17: 0 | G17: 0 | H17: =H16+E17+F17 -> 1738089 | I17: CHI KHÁC - その他 | O17: NỢ | P17: KHÁCH NỢ
A18: 45613 | B18: 日 | C18: 454298 | D18: 304207 | E18: =C18-D18 -> 150091 | F18: -711 | G18: 0 | H18: =H17+E18+F18 -> 1887469 | M18: Khác | N18: TỔNG | O18: TIỀN $ CÁC KHOẢN TƯƠNG ĐƯƠNG
A19: 45614 | B19: 月 | C19: 251395 | D19: 164710 | E19: =C19-D19 -> 86685 | F19: -11 | G19: 0 | H19: =H18+E19+F19 -> 1974143 | M19: =N23 -> 116004 | N19: =SUM(I19:M19) -> 116004 | O19: GIÁ TRỊ KHO ƯỚC TÍNH
A20: 45615 | B20: 火 | C20: 275603 | D20: 493638 | E20: =C20-D20 -> -218035 | F20: 0 | G20: 0 | H20: =H19+E20+F20 -> 1756108 | O20: TÀI SẢN DÀI HẠN
A21: 45616 | B21: 水 | C21: 369401 | D21: 1262082 | E21: =C21-D21 -> -892681 | F21: -451 | G21: 0 | H21: =H20+E21+F21 -> 862976 | I21: 参考 | O21: TỔNG | R21: =SUM(R12:R20) -> 0
A22: 45617 | B22: 木 | C22: 466645 | D22: 575456 | E22: =C22-D22 -> -108811 | F22: 0 | G22: 0 | H22: =H21+E22+F22 -> 754165 | I22: Giảm giá HD | J22: Khấu hao HĐ | K22: Wifi | L22: Bảo hiểm quán ** | M22: TRẢ - HUỶ | N22: TỔNG
A23: 45618 | B23: 金 | C23: 765428 | D23: 174140 | E23: =C23-D23 -> 591288 | F23: 0 | G23: 0 | H23: =H22+E23+F23 -> 1345453 | I23: 0 | J23: 0 | K23: 5750 | L23: 22000 | M23: 88254 | N23: =SUM(J23:M23) -> 116004 | O23: NỢ + CÁC KHOẢN VAY
A24: 45619 | B24: 土 | C24: 673161 | D24: 593968 | E24: =C24-D24 -> 79193 | F24: -454 | G24: 0 | H24: =H23+E24+F24 -> 1424192 | O24: NỢ NGẮN HẠN
A25: 45620 | B25: 日 | C25: 355205 | D25: 248300 | E25: =C25-D25 -> 106905 | F25: -11 | G25: 0 | H25: =H24+E25+F25 -> 1531086
A26: 45621 | B26: 月 | C26: 530791 | D26: 541044 | E26: =C26-D26 -> -10253 | F26: 0 | G26: 0 | H26: =H25+E26+F26 -> 1520833
A27: 45622 | B27: 火 | C27: 466738 | D27: 165795 | E27: =C27-D27 -> 300943 | F27: -45 | G27: 0 | H27: =H26+E27+F27 -> 1821731
A28: 45623 | B28: 水 | C28: 586790 | D28: 1098396 | E28: =C28-D28 -> -511606 | F28: -48 | G28: 0 | H28: =H27+E28+F28 -> 1310077
A29: 45624 | B29: 木 | C29: 651765 | D29: 344575 | E29: =C29-D29 -> 307190 | F29: -221 | G29: 0 | H29: =H28+E29+F29 -> 1617046 | O29: NỢ DÀI HẠN
A30: 45625 | B30: 金 | C30: 971341 | D30: 531706 | E30: =C30-D30 -> 439635 | F30: 0 | G30: 0 | H30: =H29+E30+F30 -> 2056681
A31: 45626 | B31: 土 | C31: 802499 | D31: 269478 | E31: =C31-D31 -> 533021 | F31: -78 | G31: 0 | H31: =H30+E31+F31 -> 2589624
D32: =360000+100000+150000 -> 610000 | E32: =C32-D32 -> -610000 | G32: 0 | H32: =H31+E32+F32 -> 1979624
E33: =C33-D33 -> 0 | H33: =H32+E33+F33 -> 1979624
A34: TỔNG | C34: =SUM(C2:C33) -> 17425659 | D34: =SUM(D2:D33) -> 15441818 | E34: =SUM(E2:E32) -> 1983841 | F34: =SUM(F2:F32) -> -4217 | G34: =SUM(G2:G32) -> 0 | H34: =C34-D34 -> 1983841

Sheet 2024_12
A1: 日付 | C1: 売上 | D1: 支出 | E1: 入金 | F1: 不足 | G1: デリバリ | H1: 累計 | I1: BÁO CÁO THÁNG 12/2024 | O1: Bổ sung 補足
A2: 45627 | B2: 日 | C2: 511249 | D2: 280489 | E2: =C2-D2 -> 230760 | F2: -1414 | G2: 0 | H2: =E2+F2 -> 229346 | I2: THU | O2: Bảo hiểm quán **
A3: 45628 | B3: 月 | C3: 288805 | D3: 455905 | E3: =C3-D3 -> -167100 | F3: 0 | G3: 0 | H3: =H2+E3+F3 -> 62246 | I3: TỔNG | J3: SHIP BD | K3: SHIP | L3: Chênh lệch | M3: THANH TOÁN POINT
A4: 45629 | B4: 火 | C4: 317032 | D4: 143215 | E4: =C4-D4 -> 173817 | F4: -441 | G4: 0 | H4: =H3+E4+F4 -> 235622 | I4: =C34 -> 21151544 | J4: =G34 -> 0 | L4: =F34 -> -16279 | M4: 16261
A5: 45630 | B5: 水 | C5: 346091 | D5: 1316378 | E5: =C5-D5 -> -970287 | F5: 0 | G5: 0 | H5: =H4+E5+F5 -> -734665 | J5: =J4/I4 -> 0 | K5: =K4/I4 -> 0 | L5: =L4/I4 -> -0.00076963649 | M5: =M4/I4 -> 0.00076878548 | O5: Lương *
A6: 45631 | B6: 木 | C6: 448768 | D6: 686540 | E6: =C6-D6 -> -237772 | F6: -574 | G6: 0 | H6: =H5+E6+F6 -> -973011 | I6: CHI | O6: Anh Giang
A7: 45632 | B7: 金 | C7: 949171 | D7: 400794 | E7: =C7-D7 -> 548377 | F7: -741 | G7: 0 | H7: =H6+E7+F7 -> -425375 | I7: NHẬP HÀNG | J7: LƯƠNG | K7: CHI KHÁC | M7: TỔNG | O7: Lương CB | P7: 350000
A8: 45633 | B8: 土 | C8: 740016 | D8: 435484 | E8: =C8-D8 -> 304532 | F8: -424 | G8: 0 | H8: =H7+E8+F8 -> -121267 | I8: =D34 -> 18943520 | J8: =L16 -> 1093110 | K8: =N19 -> 108474 | M8: =SUM(I8:L8) -> 20145104 | O8: Ship ngoài giờ | P8: 55000
A9: 45634 | B9: 日 | C9: 437032 | D9: 292120 | E9: =C9-D9 -> 144912 | F9: 0 | G9: 0 | H9: =H8+E9+F9 -> 23645 | I9: LỢI NHUẬN | J9: =H34-J8-K8-M4 -> 973900 | O9: 社会保険 | P9: 35000
A10: 45635 | B10: 月 | C10: 383892 | D10: 136602 | E10: =C10-D10 -> 247290 | F10: -41 | G10: 0 | H10: =H9+E10+F10 -> 270894 | I10: CHI TIẾT | O10: Tổng | P10: =SUM(P7:P9) -> 440000
A11: 45636 | B11: 火 | C11: 560498 | D11: 321539 | E11: =C11-D11 -> 238959 | F11: 0 | G11: 0 | H11: =H10+E11+F11 -> 509853 | I11: LƯƠNG - 給与 | O11: TÀI SẢN CÔNG TY
A12: 45637 | B12: 水 | C12: 404361 | D12: 706182 | E12: =C12-D12 -> -301821 | F12: -54 | G12: 0 | H12: =H11+E12+F12 -> 207978 | I12: A. Giang | J12: A.Thái | K12: C.Hiền | L12: Nhàn | M12: Cưng | N12: Nghĩa | O12: LỢI NHUẬN GỘP | R12: 0
A13: 45638 | B13: 木 | C13: 605782 | D13: 916821 | E13: =C13-D13 -> -311039 | F13: -765 | G13: 0 | H13: =H12+E13+F13 -> -103826 | I13: =P7 -> 350000 | J13: 56500 | K13: 161000 | L13: 30800 | M13: 74800 | N13: 232000 | O13: TIỀN MẶT | Q13: JPY | R13: 0
A14: 45639 | B14: 金 | C14: 835130 | D14: 177790 | E14: =C14-D14 -> 657340 | F14: -498 | G14: 0 | H14: =H13+E14+F14 -> 553016 | I14: HỖ TRỢ | Q14: VND
A15: 45640 | B15: 土 | C15: 1173138 | D15: 700440 | E15: =C15-D15 -> 472698 | F15: -779 | G15: 0 | H15: =H14+E15+F15 -> 1024935 | I15: 0 | M15: Hoàn | N15: 98010 | O15: ATM | P15: CÁ NHÂN | R15: 0
A16: 45641 | B16: 日 | C16: 530381 | D16: 261169 | E16: =C16-D16 -> 269212 | F16: 0 | G16: 0 | H16: =H15+E16+F16 -> 1294147 | I16: TỔNG | L16: =J13+K13+L13+M13+N13+N15+P10 -> 1093110 | P16: CÔNG TY | R16: 0
A17: 45642 | B17: 月 | C17: 441630 | D17: 689004 | E17: =C17-D17 -> -247374 | F17: -441 | G17: 0 | H17: =H16+E17+F17 -> 1046332 | I17: CHI KHÁC - その他 | O17: NỢ | P17: KHÁCH NỢ | R17: 250000
A18: 45643 | B18: 火 | C18: 407715 | D18: 389464 | E18: =C18-D18 -> 18251 | F18: 0 | G18: 0 | H18: =H17+E18+F18 -> 1064583 | M18: Khác | N18: TỔNG | O18: TIỀN $ CÁC KHOẢN TƯƠNG ĐƯƠNG | R18: 0
A19: 45644 | B19: 水 | C19: 265759 | D19: 182335 | E19: =C19-D19 -> 83424 | F19: -268 | G19: 0 | H19: =H18+E19+F19 -> 1147739 | M19: =N23 -> 108474 | N19: =SUM(I19:M19) -> 108474 | O19: GIÁ TRỊ KHO ƯỚC TÍNH | R19: 5600000
A20: 45645 | B20: 木 | C20: 500916 | D20: 1410745 | E20: =C20-D20 -> -909829 | F20: -547 | G20: 0 | H20: =H19+E20+F20 -> 237363 | O20: TÀI SẢN DÀI HẠN | R20: 0
A21: 45646 | B21: 金 | C21: 795503 | D21: 704751 | E21: =C21-D21 -> 90752 | F21: -410 | G21: 0 | H21: =H20+E21+F21 -> 327705 | I21: 参考 | O21: TỔNG | R21: =SUM(R12:R20) -> 5850000
A22: 45647 | B22: 土 | C22: 730422 | D22: 296206 | E22: =C22-D22 -> 434216 | F22: -998 | G22: 0 | H22: =H21+E22+F22 -> 760923 | I22: Giảm giá HD | J22: Khấu hao HĐ | K22: Wifi | L22: Bảo hiểm quán ** | M22: TRẢ - HUỶ | N22: TỔNG
A23: 45648 | B23: 日 | C23: 491136 | D23: 427864 | E23: =C23-D23 -> 63272 | F23: 0 | G23: 0 | H23: =H22+E23+F23 -> 824195 | I23: 0 | J23: 0 | K23: 5750 | L23: 20000 | M23: 82724 | N23: =SUM(J23:M23) -> 108474 | O23: NỢ + CÁC KHOẢN VAY
A24: 45649 | B24: 月 | C24: 552936 | D24: 19120 | E24: =C24-D24 -> 533816 | F24: -745 | G24: 0 | H24: =H23+E24+F24 -> 1357266 | O24: NỢ NGẮN HẠN
A25: 45650 | B25: 火 | C25: 664907 | D25: 263799 | E25: =C25-D25 -> 401108 | F25: -645 | G25: 0 | H25: =H24+E25+F25 -> 1757729 | I25: THUYẾT MINH
A26: 45651 | B26: 水 | C26: 707640 | D26: 1380902 | E26: =C26-D26 -> -673262 | F26: -2254 | G26: 0 | H26: =H25+E26+F26 -> 1082213 | I26: 1 | J26: MUA LẠI XE ANH THÁI 200,000
A27: 45652 | B27: 木 | C27: 1465898 | D27: 749937 | E27: =C27-D27 -> 715961 | F27: -2441 | G27: 0 | H27: =H26+E27+F27 -> 1795733 | I27: 2 | J27: LƯƠNG +200,000 SO VỚI TB CÁC THÁNG
A28: 45653 | B28: 金 | C28: 1433358 | D28: 1133146 | E28: =C28-D28 -> 300212 | F28: 0 | G28: 0 | H28: =H27+E28+F28 -> 2095945
A29: 45654 | B29: 土 | C29: 1801740 | D29: 737449 | E29: =C29-D29 -> 1064291 | F29: -74 | G29: 0 | H29: =H28+E29+F29 -> 3160162 | O29: NỢ DÀI HẠN
A30: 45655 | B30: 日 | C30: 710452 | D30: 1390461 | E30: =C30-D30 -> -680009 | F30: 0 | G30: 0 | H30: =H29+E30+F30 -> 2480153
A31: 45656 | B31: 月 | C31: 939378 | D31: 669231 | E31: =C31-D31 -> 270147 | F31: -741 | G31: 0 | H31: =H30+E31+F31 -> 2749559
A32: 45657 | B32: 火 | C32: 710808 | D32: 1267638 | E32: =C32-D32 -> -556830 | F32: -984 | G32: 0 | H32: =H31+E32+F32 -> 2191745
C33: 0 | E33: =C33-D33 -> 0 | G33: 0 | H33: =H32+E33+F33 -> 2191745
A34: TỔNG | C34: =SUM(C2:C33) -> 21151544 | D34: =SUM(D2:D33) -> 18943520 | E34: =SUM(E2:E33) -> 2208024 | F34: =SUM(F2:F32) -> -16279 | G34: =SUM(G2:G32) -> 0 | H34: =C34-D34+F34 -> 2191745

Sheet 2025_1
A1: 日付 | C1: 売上 | D1: 支出 | E1: 入金 | F1: 不足 | G1: デリバリ | H1: 累計 | I1: BÁO CÁO THÁNG 01/2025 | O1: Bổ sung 補足
A2: 45658 | B2: 水 | C2: 406737 | D2: 218362 | E2: =C2-D2 -> 188375 | F2: -24 | G2: 0 | H2: =E2+F2 -> 188351 | I2: THU | O2: Bảo hiểm quán **
A3: 45659 | B3: 木 | C3: 615486 | D3: 423468 | E3: =C3-D3 -> 192018 | F3: 0 | G3: 0 | H3: =H2+E3+F3 -> 380369 | I3: TỔNG | J3: SHIP BD | K3: SHIP | L3: Chênh lệch | M3: THANH TOÁN POINT
A4: 45660 | B4: 金 | C4: 645946 | D4: 757515 | E4: =C4-D4 -> -111569 | F4: 0 | G4: 0 | H4: =H3+E4+F4 -> 268800 | I4: =C34 -> 18376433 | J4: =G34 -> 0 | L4: =F34 -> -5419 | M4: 12174
A5: 45661 | B5: 土 | C5: 702096 | D5: 157829 | E5: =C5-D5 -> 544267 | F5: -874 | G5: 0 | H5: =H4+E5+F5 -> 812193 | J5: =J4/I4 -> 0 | K5: =K4/I4 -> 0 | L5: =L4/I4 -> -0.00029488857 | M5: =M4/I4 -> 0.00066247895 | O5: Lương *
A6: 45662 | B6: 日 | C6: 332783 | D6: 598147 | E6: =C6-D6 -> -265364 | F6: 0 | G6: 0 | H6: =H5+E6+F6 -> 546829 | I6: CHI | O6: Anh Giang
A7: 45663 | B7: 月 | C7: 199501 | D7: 191205 | E7: =C7-D7 -> 8296 | F7: -41 | G7: 0 | H7: =H6+E7+F7 -> 555084 | I7: NHẬP HÀNG | J7: LƯƠNG | K7: CHI KHÁC | M7: TỔNG | O7: Lương CB | P7: 320000
A8: 45664 | B8: 火 | C8: 386873 | D8: 546241 | E8: =C8-D8 -> -159368 | F8: 0 | G8: 0 | H8: =H7+E8+F8 -> 395716 | I8: =D34 -> 16008163 | J8: =L16 -> 980050 | K8: =N19 -> 79978 | M8: =SUM(I8:L8) -> 17068191 | O8: Ship ngoài giờ | P8: 55000
A9: 45665 | B9: 水 | C9: 468097 | D9: 816032 | E9: =C9-D9 -> -347935 | F9: -451 | G9: 0 | H9: =H8+E9+F9 -> 47330 | I9: LỢI NHUẬN | J9: =H34-J8-K8-M4 -> 1296068 | O9: 社会保険 | P9: 35000
A10: 45666 | B10: 木 | C10: 522646 | D10: 203985 | E10: =C10-D10 -> 318661 | F10: -425 | G10: 0 | H10: =H9+E10+F10 -> 365566 | I10: CHI TIẾT | O10: Tổng | P10: =SUM(P7:P9) -> 410000
A11: 45667 | B11: 金 | C11: 870908 | D11: 500422 | E11: =C11-D11 -> 370486 | F11: 0 | G11: 0 | H11: =H10+E11+F11 -> 736052 | I11: LƯƠNG - 給与 | O11: TÀI SẢN CÔNG TY
A12: 45668 | B12: 土 | C12: 750594 | D12: 557851 | E12: =C12-D12 -> 192743 | F12: -451 | G12: 0 | H12: =H11+E12+F12 -> 928344 | I12: A. Giang | J12: A.Thái | K12: C.Hiền | L12: Nhàn | M12: Cưng | N12: Nghĩa | O12: LỢI NHUẬN GỘP | R12: 0
A13: 45669 | B13: 日 | C13: 491501 | D13: 273380 | E13: =C13-D13 -> 218121 | F13: -151 | G13: 0 | H13: =H12+E13+F13 -> 1146314 | I13: =P7 -> 320000 | J13: 73000 | K13: 103000 | L13: 53000 | M13: 72050 | N13: =190*1100 -> 209000 | O13: TIỀN MẶT | Q13: JPY | R13: 0
A14: 45670 | B14: 月 | C14: 488660 | D14: 801306 | E14: =C14-D14 -> -312646 | F14: 0 | G14: 0 | H14: =H13+E14+F14 -> 833668 | I14: HỖ TRỢ | Q14: VND
A15: 45671 | B15: 火 | C15: 346103 | D15: 284465 | E15: =C15-D15 -> 61638 | F15: -44 | G15: 0 | H15: =H14+E15+F15 -> 895262 | I15: 0 | M15: Hoàn | N15: 60000 | O15: ATM | P15: CÁ NHÂN | R15: 0
A16: 45672 | B16: 水 | C16: 639051 | D16: 621595 | E16: =C16-D16 -> 17456 | F16: 0 | G16: 0 | H16: =H15+E16+F16 -> 912718 | I16: TỔNG | L16: =J13+K13+L13+M13+N13+N15+P10 -> 980050 | P16: CÔNG TY | R16: 0
A17: 45673 | B17: 木 | C17: 644249 | D17: 165643 | E17: =C17-D17 -> 478606 | F17: -45 | G17: 0 | H17: =H16+E17+F17 -> 1391279 | I17: CHI KHÁC - その他 | O17: NỢ | P17: KHÁCH NỢ | R17: 250000
A18: 45674 | B18: 金 | C18: 992299 | D18: 587613 | E18: =C18-D18 -> 404686 | F18: 0 | G18: 0 | H18: =H17+E18+F18 -> 1795965 | M18: Khác | N18: TỔNG | O18: TIỀN $ CÁC KHOẢN TƯƠNG ĐƯƠNG | R18: 0
A19: 45675 | B19: 土 | C19: 577413 | D19: 162396 | E19: =C19-D19 -> 415017 | F19: -454 | G19: 0 | H19: =H18+E19+F19 -> 2210528 | M19: =N23 -> 79978 | N19: =SUM(I19:M19) -> 79978 | O19: GIÁ TRỊ KHO ƯỚC TÍNH | R19: 5600000
A20: 45676 | B20: 日 | C20: 372131 | D20: 134226 | E20: =C20-D20 -> 237905 | F20: -147 | G20: 0 | H20: =H19+E20+F20 -> 2448286 | O20: TÀI SẢN DÀI HẠN | R20: 0
A21: 45677 | B21: 月 | C21: 416258 | D21: 387867 | E21: =C21-D21 -> 28391 | F21: 0 | G21: 0 | H21: =H20+E21+F21 -> 2476677 | I21: 参考 | O21: TỔNG | R21: =SUM(R12:R20) -> 5850000
A22: 45678 | B22: 火 | C22: 476488 | D22: 824602 | E22: =C22-D22 -> -348114 | F22: -451 | G22: 0 | H22: =H21+E22+F22 -> 2128112 | I22: Giảm giá HD | J22: Khấu hao HĐ | K22: Wifi | L22: Bảo hiểm quán ** | M22: TRẢ - HUỶ | N22: TỔNG
A23: 45679 | B23: 水 | C23: 518671 | D23: 1248575 | E23: =C23-D23 -> -729904 | F23: 0 | G23: 0 | H23: =H22+E23+F23 -> 1398208 | I23: 0 | J23: 0 | K23: 5750 | L23: 22000 | M23: 52228 | N23: =SUM(J23:M23) -> 79978 | O23: NỢ + CÁC KHOẢN VAY
A24: 45680 | B24: 木 | C24: 679434 | D24: 204665 | E24: =C24-D24 -> 474769 | F24: 0 | G24: 0 | H24: =H23+E24+F24 -> 1872977 | O24: NỢ NGẮN HẠN
A25: 45681 | B25: 金 | C25: 1599605 | D25: 358380 | E25: =C25-D25 -> 1241225 | F25: -154 | G25: 0 | H25: =H24+E25+F25 -> 3114048 | I25: THUYẾT MINH
A26: 45682 | B26: 土 | C26: 1184291 | D26: 828219 | E26: =C26-D26 -> 356072 | F26: -754 | G26: 0 | H26: =H25+E26+F26 -> 3469366
A27: 45683 | B27: 日 | C27: 718413 | D27: 506557 | E27: =C27-D27 -> 211856 | F27: 0 | G27: 0 | H27: =H26+E27+F27 -> 3681222
A28: 45684 | B28: 月 | C28: 670578 | D28: 792237 | E28: =C28-D28 -> -121659 | F28: 0 | G28: 0 | H28: =H27+E28+F28 -> 3559563
A29: 45685 | B29: 火 | C29: 540703 | D29: 447543 | E29: =C29-D29 -> 93160 | F29: -45 | G29: 0 | H29: =H28+E29+F29 -> 3652678 | O29: NỢ DÀI HẠN
A30: 45686 | B30: 水 | C30: 0 | D30: 0 | E30: =C30-D30 -> 0 | F30: 0 | G30: 0 | H30: =H29+E30+F30 -> 3652678
A31: 45687 | B31: 木 | C31: 421643 | D31: 665770 | E31: =C31-D31 -> -244127 | F31: -454 | G31: 0 | H31: =H30+E31+F31 -> 3408097
A32: 45688 | B32: 金 | C32: 697275 | D32: 442067 | E32: =C32-D32 -> 255208 | F32: -454 | G32: 0 | H32: =H31+E32+F32 -> 3662851
C33: 0 | D33: =400000+200000+700000 -> 1300000 | E33: =C33-D33 -> -1300000 | G33: 0 | H33: =H32+E33+F33 -> 2362851
A34: TỔNG | C34: =SUM(C2:C33) -> 18376433 | D34: =SUM(D2:D33) -> 16008163 | E34: =SUM(E2:E33) -> 2368270 | F34: =SUM(F2:F32) -> -5419 | G34: =SUM(G2:G32) -> 0 | H34: =C34-D34 -> 2368270

Sheet 2025_2
A1: 日付 | C1: 売上 | D1: 支出 | E1: 入金 | F1: 不足 | G1: デリバリ | H1: 累計 | I1: BÁO CÁO THÁNG 02/2025 | O1: Bổ sung 補足
A2: 45689 | B2: 土 | C2: 669636 | D2: 328240 | E2: =C2-D2 -> 341396 | F2: -845 | G2: 0 | H2: =E2+F2 -> 340551 | I2: THU | O2: Bảo hiểm quán **
A3: 45690 | B3: 日 | C3: 511073 | D3: 994165 | E3: =C3-D3 -> -483092 | F3: 0 | G3: 0 | H3: =H2+E3+F3 -> -142541 | I3: TỔNG | J3: SHIP BD | K3: SHIP | L3: Chênh lệch | M3: THANH TOÁN POINT
A4: 45691 | B4: 月 | C4: 434981 | D4: 35760 | E4: =C4-D4 -> 399221 | F4: 0 | G4: 0 | H4: =H3+E4+F4 -> 256680 | I4: =C34 -> 17790543 | J4: =G34 -> 0 | L4: =F34 -> -7376 | M4: 12213
A5: 45692 | B5: 火 | C5: 503520 | D5: 568678 | E5: =C5-D5 -> -65158 | F5: 0 | G5: 0 | H5: =H4+E5+F5 -> 191522 | J5: =J4/I4 -> 0 | K5: =K4/I4 -> 0 | L5: =L4/I4 -> -0.0004146023 | M5: =M4/I4 -> 0.00068648832 | O5: Lương *
A6: 45693 | B6: 水 | C6: 314569 | D6: 960043 | E6: =C6-D6 -> -645474 | F6: -45 | G6: 0 | H6: =H5+E6+F6 -> -453997 | I6: CHI | O6: Anh Giang
A7: 45694 | B7: 木 | C7: 477594 | D7: 84451 | E7: =C7-D7 -> 393143 | F7: -451 | G7: 0 | H7: =H6+E7+F7 -> -61305 | I7: NHẬP HÀNG | J7: LƯƠNG | K7: CHI KHÁC | M7: TỔNG | O7: Lương CB | P7: 340000
A8: 45695 | B8: 金 | C8: 1040458 | D8: 493547 | E8: =C8-D8 -> 546911 | F8: 0 | G8: 0 | H8: =H7+E8+F8 -> 485606 | I8: =D34 -> 15072888 | J8: =L16 -> 963800 | K8: =N19 -> 223835 | M8: =SUM(I8:K8) -> 16260523 | O8: Ship ngoài giờ | P8: 55000
A9: 45696 | B9: 土 | C9: 965580 | D9: 278612 | E9: =C9-D9 -> 686968 | F9: -589 | G9: 0 | H9: =H8+E9+F9 -> 1171985 | I9: LỢI NHUẬN | J9: =H34-J8-K8-M4 -> 1510431 | O9: 社会保険 | P9: 35000
A10: 45697 | B10: 日 | C10: 567340 | D10: 453787 | E10: =C10-D10 -> 113553 | F10: -748 | G10: 0 | H10: =H9+E10+F10 -> 1284790 | I10: CHI TIẾT | O10: Tổng | P10: =SUM(P7:P9) -> 430000
A11: 45698 | B11: 月 | C11: 370114 | D11: 306540 | E11: =C11-D11 -> 63574 | F11: 0 | G11: 0 | H11: =H10+E11+F11 -> 1348364 | I11: LƯƠNG - 給与 | O11: TÀI SẢN CÔNG TY
A12: 45699 | B12: 火 | C12: 550989 | D12: 515021 | E12: =C12-D12 -> 35968 | F12: 0 | G12: 0 | H12: =H11+E12+F12 -> 1384332 | I12: A. Giang | J12: A.Thái | K12: C.Hiền | L12: Nhàn | M12: Cưng | N12: Nghĩa | O12: LỢI NHUẬN GỘP | R12: 0
A13: 45700 | B13: 水 | C13: 469817 | D13: 1345161 | E13: =C13-D13 -> -875344 | F13: -454 | G13: 0 | H13: =H12+E13+F13 -> 508534 | I13: =P7 -> 340000 | J13: 28000 | K13: 85000 | L13: =63*1100 -> 69300 | M13: =47*1100 -> 51700 | N13: 225000 | O13: TIỀN MẶT | Q13: JPY | R13: 0
A14: 45701 | B14: 木 | C14: 700478 | D14: 711940 | E14: =C14-D14 -> -11462 | F14: 0 | G14: 0 | H14: =H13+E14+F14 -> 497072 | Q14: VND
A15: 45702 | B15: 金 | C15: 1153271 | D15: 199274 | E15: =C15-D15 -> 953997 | F15: -987 | G15: 0 | H15: =H14+E15+F15 -> 1450082 | M15: Hoàn | N15: =68*1100 -> 74800 | O15: ATM | P15: CÁ NHÂN | R15: 0
A16: 45703 | B16: 土 | C16: 861687 | D16: 133903 | E16: =C16-D16 -> 727784 | F16: -442 | G16: 0 | H16: =H15+E16+F16 -> 2177424 | I16: TỔNG | L16: =J13+K13+L13+M13+N13+N15+P10 -> 963800 | P16: CÔNG TY | R16: 0
A17: 45704 | B17: 日 | C17: 415742 | D17: 677650 | E17: =C17-D17 -> -261908 | F17: 0 | G17: 0 | H17: =H16+E17+F17 -> 1915516 | I17: CHI KHÁC - その他 | O17: NỢ | P17: KHÁCH NỢ | R17: 800000
A18: 45705 | B18: 月 | C18: 384654 | D18: 660670 | E18: =C18-D18 -> -276016 | F18: -454 | G18: 0 | H18: =H17+E18+F18 -> 1639046 | M18: Khác | N18: TỔNG | O18: TIỀN $ CÁC KHOẢN TƯƠNG ĐƯƠNG | R18: 0
A19: 45706 | B19: 火 | C19: 396903 | D19: 339589 | E19: =C19-D19 -> 57314 | F19: 0 | G19: 0 | H19: =H18+E19+F19 -> 1696360 | M19: =N23 -> 223835 | N19: =SUM(I19:M19) -> 223835 | O19: GIÁ TRỊ KHO ƯỚC TÍNH | R19: 4000000
A20: 45707 | B20: 水 | C20: 497550 | D20: 364899 | E20: =C20-D20 -> 132651 | F20: 0 | G20: 0 | H20: =H19+E20+F20 -> 1829011 | O20: TÀI SẢN DÀI HẠN | R20: 0
A21: 45708 | B21: 木 | C21: 511424 | D21: 504626 | E21: =C21-D21 -> 6798 | F21: -445 | G21: 0 | H21: =H20+E21+F21 -> 1835364 | I21: 参考 | O21: TỔNG | R21: =SUM(R12:R20) -> 4800000
A22: 45709 | B22: 金 | C22: 1069394 | D22: 1246562 | E22: =C22-D22 -> -177168 | F22: -458 | G22: 0 | H22: =H21+E22+F22 -> 1657738 | I22: Giảm giá HD | J22: Khấu hao HĐ | K22: Wifi | L22: Bảo hiểm quán ** | M22: TRẢ - HUỶ | N22: TỔNG
A23: 45710 | B23: 土 | C23: 962335 | D23: 406086 | E23: =C23-D23 -> 556249 | F23: 0 | G23: 0 | H23: =H22+E23+F23 -> 2213987 | I23: 838 | J23: 100000 | K23: 5750 | L23: 33000 | M23: 84247 | N23: =SUM(I23:M23) -> 223835 | O23: NỢ + CÁC KHOẢN VAY
A24: 45711 | B24: 日 | C24: 430039 | D24: 564707 | E24: =C24-D24 -> -134668 | F24: -87 | G24: 0 | H24: =H23+E24+F24 -> 2079232 | O24: NỢ NGẮN HẠN
A25: 45712 | B25: 月 | C25: 474918 | D25: 583350 | E25: =C25-D25 -> -108432 | F25: 0 | G25: 0 | H25: =H24+E25+F25 -> 1970800 | I25: THUYẾT MINH
A26: 45713 | B26: 火 | C26: 428557 | D26: 185643 | E26: =C26-D26 -> 242914 | F26: -455 | G26: 0 | H26: =H25+E26+F26 -> 2213259 | I26: 500000 | J26: Trích lập dự phòng (Chi khác) từ lợi nhuận 500,000
A27: 45714 | B27: 水 | C27: 452815 | D27: 349990 | E27: =C27-D27 -> 102825 | F27: 0 | G27: 0 | H27: =H26+E27+F27 -> 2316084 | I27: 200000 | J27: Trả cổ túc 10% 200,000
A28: 45715 | B28: 木 | C28: 777777 | D28: 517378 | E28: =C28-D28 -> 260399 | F28: -42 | G28: 0 | H28: =H27+E28+F28 -> 2576441
A29: 45716 | B29: 金 | C29: 1397328 | D29: 562616 | E29: =C29-D29 -> 834712 | F29: -874 | G29: 0 | H29: =H28+E29+F29 -> 3410279 | O29: NỢ DÀI HẠN
G30: 0 | H30: =H29+E30+F30 -> 3410279
E31: =C31-D31 -> 0 | G31: 0 | H31: =H30+E31+F31 -> 3410279
E32: =C32-D32 -> 0 | G32: 0 | H32: =H31+E32+F32 -> 3410279
D33: =SUM(I26:I33) -> 700000 | E33: =C33-D33 -> -700000 | G33: 0 | H33: =H32+E33+F33 -> 2710279
A34: TỔNG | C34: =SUM(C2:C33) -> 17790543 | D34: =SUM(D2:D33) -> 15072888 | E34: =SUM(E2:E33) -> 2717655 | F34: =SUM(F2:F32) -> -7376 | G34: =SUM(G2:G32) -> 0 | H34: =C34-D34+F34 -> 2710279

Sheet 2025_3
A1: 日付 | C1: 売上 | D1: 支出 | E1: 入金 | F1: 不足 | G1: デリバリ | H1: 累計 | I1: BÁO CÁO THÁNG 03/2025 | O1: Bổ sung 補足
A2: 45717 | B2: 土 | C2: 1405846 | D2: 647605 | E2: =C2-D2 -> 758241 | F2: -784 | G2: 0 | H2: =E2+F2 -> 757457 | I2: THU | O2: Bảo hiểm quán **
A3: 45718 | B3: 日 | C3: 532956 | D3: 588339 | E3: =C3-D3 -> -55383 | F3: 0 | G3: 0 | H3: =H2+E3+F3 -> 702074 | I3: TỔNG | J3: SHIP BD | K3: SHIP | L3: Chênh lệch | M3: THANH TOÁN POINT
A4: 45719 | B4: 月 | C4: 407839 | D4: 879781 | E4: =C4-D4 -> -471942 | F4: -84 | G4: 0 | H4: =H3+E4+F4 -> 230048 | I4: =C34 -> 20173970 | J4: =G34 -> 0 | L4: =F34 -> -17105 | M4: 25301
A5: 45720 | B5: 火 | C5: 320116 | D5: 557842 | E5: =C5-D5 -> -237726 | F5: -514 | G5: 0 | H5: =H4+E5+F5 -> -8192 | J5: =J4/I4 -> 0 | K5: =K4/I4 -> 0 | L5: =L4/I4 -> -0.00084787476 | M5: =M4/I4 -> 0.0012541409 | O5: Lương *
A6: 45721 | B6: 水 | C6: 497240 | D6: 1386046 | E6: =C6-D6 -> -888806 | F6: 0 | G6: 0 | H6: =H5+E6+F6 -> -896998 | I6: CHI | O6: Anh Giang
A7: 45722 | B7: 木 | C7: 673410 | D7: 976113 | E7: =C7-D7 -> -302703 | F7: -5380 | G7: 0 | H7: =H6+E7+F7 -> -1205081 | I7: NHẬP HÀNG | J7: LƯƠNG | K7: CHI KHÁC | M7: TỔNG | O7: Lương CB | P7: 380000
A8: 45723 | B8: 金 | C8: 923198 | D8: 661803 | E8: =C8-D8 -> 261395 | F8: -425 | G8: 0 | H8: =H7+E8+F8 -> -944111 | I8: =D34 -> 18877991 | J8: =L16 -> 976776 | K8: =N19 -> 131350 | M8: =SUM(I8:L8) -> 19986117 | O8: Ship ngoài giờ | P8: 55000
A9: 45724 | B9: 土 | C9: 709108 | D9: 217159 | E9: =C9-D9 -> 491949 | F9: 0 | G9: 0 | H9: =H8+E9+F9 -> -452162 | I9: LỢI NHUẬN | J9: =I4-M8-M4+L4 -> 145447 | O9: 社会保険 | P9: 35000
A10: 45725 | B10: 日 | C10: 401358 | D10: 321329 | E10: =C10-D10 -> 80029 | F10: 0 | G10: 0 | H10: =H9+E10+F10 -> -372133 | I10: CHI TIẾT | O10: Tổng | P10: =SUM(P7:P9) -> 470000
A11: 45726 | B11: 月 | C11: 457129 | D11: 715070 | E11: =C11-D11 -> -257941 | F11: -254 | G11: 0 | H11: =H10+E11+F11 -> -630328 | I11: LƯƠNG - 給与 | O11: TÀI SẢN CÔNG TY
A12: 45727 | B12: 火 | C12: 703428 | D12: 128080 | E12: =C12-D12 -> 575348 | F12: 0 | G12: 0 | H12: =H11+E12+F12 -> -54980 | I12: A. Giang | J12: A.Thái | K12: C.Hiền | L12: Nhàn | M12: Cưng | N12: Nghĩa | O12: LỢI NHUẬN GỘP | R12: 0
A13: 45728 | B13: 水 | C13: 728184 | D13: 419516 | E13: =C13-D13 -> 308668 | F13: -1000 | G13: 0 | H13: =H12+E13+F13 -> 252688 | I13: =P7 -> 380000 | J13: 0 | K13: 0 | L13: =97*1100 -> 106700 | M13: =83850 -> 83850 | N13: 255000 | O13: TIỀN MẶT | Q13: JPY | R13: 0
A14: 45729 | B14: 木 | C14: 779674 | D14: 1229310 | E14: =C14-D14 -> -449636 | F14: -820 | G14: 0 | H14: =H13+E14+F14 -> -197768 | Q14: VND
A15: 45730 | B15: 金 | C15: 1167549 | D15: 948667 | E15: =C15-D15 -> 218882 | F15: -2540 | G15: 0 | H15: =H14+E15+F15 -> 18574 | I15: 0 | M15: Hoàn | N15: =55.66*1100 -> 61226 | O15: ATM | P15: CÁ NHÂN | R15: 0
A16: 45731 | B16: 土 | C16: 911986 | D16: 653324 | E16: =C16-D16 -> 258662 | F16: -1780 | G16: 0 | H16: =H15+E16+F16 -> 275456 | I16: TỔNG | L16: =J13+K13+L13+M13+N13+N15+P10 -> 976776 | P16: CÔNG TY | R16: 0
A17: 45732 | B17: 日 | C17: 375162 | D17: 552841 | E17: =C17-D17 -> -177679 | F17: 0 | G17: 0 | H17: =H16+E17+F17 -> 97777 | I17: CHI KHÁC - その他 | O17: NỢ | P17: KHÁCH NỢ | R17: 600000
A18: 45733 | B18: 月 | C18: 391276 | D18: 525320 | E18: =C18-D18 -> -134044 | F18: -500 | G18: 0 | H18: =H17+E18+F18 -> -36767 | M18: Khác | N18: TỔNG | O18: TIỀN $ CÁC KHOẢN TƯƠNG ĐƯƠNG | R18: 0
A19: 45734 | B19: 火 | C19: 425910 | D19: 596140 | E19: =C19-D19 -> -170230 | F19: 0 | G19: 0 | H19: =H18+E19+F19 -> -206997 | M19: =N23 -> 131350 | N19: =SUM(I19:M19) -> 131350 | O19: GIÁ TRỊ KHO ƯỚC TÍNH | R19: 5600000
A20: 45735 | B20: 水 | C20: 442773 | D20: 718640 | E20: =C20-D20 -> -275867 | F20: -870 | G20: 0 | H20: =H19+E20+F20 -> -483734 | O20: TÀI SẢN DÀI HẠN | R20: 0
A21: 45736 | B21: 木 | C21: 761548 | D21: 444302 | E21: =C21-D21 -> 317246 | F21: 0 | G21: 0 | H21: =H20+E21+F21 -> -166488 | I21: 参考 | O21: TỔNG | R21: =SUM(R12:R20) -> 6200000
A22: 45737 | B22: 金 | C22: 915433 | D22: 155297 | E22: =C22-D22 -> 760136 | F22: -1700 | G22: 0 | H22: =H21+E22+F22 -> 591948 | I22: Giảm giá HD | J22: Khấu hao HĐ | K22: Wifi | L22: Bảo hiểm quán ** | M22: TRẢ - HUỶ | N22: TỔNG
A23: 45738 | B23: 土 | C23: 740625 | D23: 1053255 | E23: =C23-D23 -> -312630 | F23: 0 | G23: 0 | H23: =H22+E23+F23 -> 279318 | I23: 0 | J23: 50000 | K23: 0 | L23: 33000 | M23: 48350 | N23: =SUM(J23:M23) -> 131350 | O23: NỢ + CÁC KHOẢN VAY
A24: 45739 | B24: 日 | C24: 307925 | D24: 305135 | E24: =C24-D24 -> 2790 | F24: 0 | G24: 0 | H24: =H23+E24+F24 -> 282108 | O24: NỢ NGẮN HẠN
A25: 45740 | B25: 月 | C25: 529877 | D25: 157353 | E25: =C25-D25 -> 372524 | F25: -454 | G25: 0 | H25: =H24+E25+F25 -> 654178 | I25: THUYẾT MINH
A26: 45741 | B26: 火 | C26: 581013 | D26: 576881 | E26: =C26-D26 -> 4132 | F26: 0 | G26: 0 | H26: =H25+E26+F26 -> 658310 | I26: 45745 | J26: Chi 200.000 làm đường điện
A27: 45742 | B27: 水 | C27: 524811 | D27: 1228048 | E27: =C27-D27 -> -703237 | F27: 0 | G27: 0 | H27: =H26+E27+F27 -> -44927 | J27: Thanh toán công nợ tháng trước
A28: 45743 | B28: 木 | C28: 801328 | D28: 1174577 | E28: =C28-D28 -> -373249 | F28: 0 | G28: 0 | H28: =H27+E28+F28 -> -418176 | J28: Mua điều hòa mới
A29: 45744 | B29: 金 | C29: 1198213 | D29: 181839 | E29: =C29-D29 -> 1016374 | F29: 0 | G29: 0 | H29: =H28+E29+F29 -> 598198 | J29: KHÔNG TRÍCH LẬP DỰ PHÒNG | O29: NỢ DÀI HẠN
A30: 45745 | B30: 土 | C30: 1101902 | D30: 374923 | E30: =C30-D30 -> 726979 | F30: 0 | G30: 0 | H30: =H29+E30+F30 -> 1325177 | J30: GIÁ TRỊ TỒN KHO + 1,600,000JPY (160MAN)
A31: 45746 | B31: 日 | C31: 457153 | D31: 311456 | E31: =C31-D31 -> 145697 | F31: 0 | G31: 0 | H31: =H30+E31+F31 -> 1470874
A32: 45747 | B32: 月 | C32: 0 | D32: 192000 | E32: =C32-D32 -> -192000 | G32: 0 | H32: =H31+E32+F32 -> 1278874
G33: 0 | H33: =H32+E33+F33 -> 1278874
A34: TỔNG | C34: =SUM(C2:C33) -> 20173970 | D34: =SUM(D2:D33) -> 18877991 | E34: =SUM(E2:E33) -> 1295979 | F34: =SUM(F2:F33) -> -17105 | G34: =SUM(G2:G33) -> 0 | H34: =C34-D34+G34 -> 1295979

Sheet 2025_4
A1: 日付 | C1: 売上 | D1: 支出 | E1: 入金 | F1: 不足 | G1: デリバリ | H1: 累計 | I1: BÁO CÁO THÁNG 04/2025 | O1: Bổ sung 補足
A2: 45748 | B2: 火 | C2: 505411 | D2: 806309 | E2: =C2-D2 -> -300898 | F2: -50 | G2: 0 | H2: =E2+F2 -> -300948 | I2: THU | O2: Bảo hiểm quán **
A3: 45749 | B3: 水 | C3: 515981 | D3: 545390 | E3: =C3-D3 -> -29409 | F3: -125 | G3: 0 | H3: =H2+E3+F3 -> -330482 | I3: TỔNG | J3: SHIP BD | K3: SHIP | L3: Chênh lệch | M3: THANH TOÁN POINT
A4: 45750 | B4: 木 | C4: 380785 | D4: 619542 | E4: =C4-D4 -> -238757 | F4: 0 | G4: 0 | H4: =H3+E4+F4 -> -569239 | I4: =C34 -> 18224357 | J4: =G34 -> 0 | K4: 0 | L4: =F34 -> -5045 | M4: 18286
A5: 45751 | B5: 金 | C5: 1121371 | D5: 157218 | E5: =C5-D5 -> 964153 | F5: -254 | G5: 0 | H5: =H4+E5+F5 -> 394660 | J5: =J4/I4 -> 0 | K5: =K4/I4 -> 0 | L5: =L4/I4 -> -0.00027682733 | M5: =M4/I4 -> 0.0010033825 | O5: Lương *
A6: 45752 | B6: 土 | C6: 705671 | D6: 321097 | E6: =C6-D6 -> 384574 | F6: 0 | G6: 0 | H6: =H5+E6+F6 -> 779234 | I6: CHI | O6: Anh Giang
A7: 45753 | B7: 日 | C7: 399400 | D7: 1142284 | E7: =C7-D7 -> -742884 | F7: -5 | G7: 0 | H7: =H6+E7+F7 -> 36345 | I7: NHẬP HÀNG | J7: LƯƠNG | K7: CHI KHÁC | M7: TỔNG | O7: Lương CB | P7: 300000
A8: 45754 | B8: 月 | C8: 404577 | D8: 625513 | E8: =C8-D8 -> -220936 | F8: -54 | G8: 0 | H8: =H7+E8+F8 -> -184645 | I8: =D34 -> 16179744 | J8: =L16 -> 940600 | K8: =N19 -> 125780 | M8: =SUM(I8:L8) -> 17246124 | O8: Ship ngoài giờ | P8: 55000
A9: 45755 | B9: 火 | C9: 339941 | D9: 198938 | E9: =C9-D9 -> 141003 | F9: -120 | G9: 0 | H9: =H8+E9+F9 -> -43762 | I9: LỢI NHUẬN | J9: =I4-M8-M4+L4 -> 954902 | O9: 社会保険 | P9: 35000
A10: 45756 | B10: 水 | C10: 308253 | D10: 134450 | E10: =C10-D10 -> 173803 | F10: -77 | G10: 0 | H10: =H9+E10+F10 -> 129964 | I10: CHI TIẾT | O10: Tổng | P10: =SUM(P7:P9) -> 390000
A11: 45757 | B11: 木 | C11: 830174 | D11: 818617 | E11: =C11-D11 -> 11557 | F11: 0 | G11: 0 | H11: =H10+E11+F11 -> 141521 | I11: LƯƠNG - 給与 | O11: TÀI SẢN CÔNG TY
A12: 45758 | B12: 金 | C12: 1034356 | D12: 576233 | E12: =C12-D12 -> 458123 | F12: -654 | G12: 0 | H12: =H11+E12+F12 -> 598990 | I12: A. Giang | J12: A.Thái | K12: C.Hiền | L12: Nhàn | M12: Cưng | N12: Nghĩa | O12: LỢI NHUẬN GỘP | R12: 0
A13: 45759 | B13: 土 | C13: 1023704 | D13: 637424 | E13: =C13-D13 -> 386280 | F13: 0 | G13: 0 | H13: =H12+E13+F13 -> 985270 | I13: =P7 -> 300000 | J13: 55000 | K13: 130000 | L13: =87*1100 -> 95700 | M13: =66*1100 -> 72600 | N13: 95000 | O13: TIỀN MẶT | Q13: JPY | R13: 0
A14: 45760 | B14: 日 | C14: 502458 | D14: 336124 | E14: =C14-D14 -> 166334 | F14: -74 | G14: 0 | H14: =H13+E14+F14 -> 1151530 | Q14: VND | R14: 0
A15: 45761 | B15: 月 | C15: 459089 | D15: 743371 | E15: =C15-D15 -> -284282 | F15: -45 | G15: 0 | H15: =H14+E15+F15 -> 867203 | I15: 0 | M15: Hoàn | N15: =93*1100 -> 102300 | O15: ATM | P15: CÁ NHÂN | R15: 0
A16: 45762 | B16: 火 | C16: 720043 | D16: 540190 | E16: =C16-D16 -> 179853 | F16: 0 | G16: 0 | H16: =H15+E16+F16 -> 1047056 | I16: TỔNG | L16: =J13+K13+L13+M13+N13+N15+P10 -> 940600 | P16: CÔNG TY | R16: 0
A17: 45763 | B17: 水 | C17: 565199 | D17: 727756 | E17: =C17-D17 -> -162557 | F17: -741 | G17: 0 | H17: =H16+E17+F17 -> 883758 | I17: CHI KHÁC - その他 | O17: NỢ | P17: KHÁCH NỢ | R17: 0
A18: 45764 | B18: 木 | C18: 490528 | D18: 166730 | E18: =C18-D18 -> 323798 | F18: -541 | G18: 0 | H18: =H17+E18+F18 -> 1207015 | M18: Khác | N18: TỔNG | O18: TIỀN & CÁC KHOẢN TƯƠNG ĐƯƠNG | R18: 0
A19: 45765 | B19: 金 | C19: 777832 | D19: 352963 | E19: =C19-D19 -> 424869 | F19: -1254 | G19: 0 | H19: =H18+E19+F19 -> 1630630 | M19: =N23 -> 125780 | N19: =SUM(I19:M19) -> 125780 | O19: GIÁ TRỊ KHO ƯỚC TÍNH | R19: 6524462
A20: 45766 | B20: 土 | C20: 887728 | D20: 916184 | E20: =C20-D20 -> -28456 | F20: 0 | G20: 0 | H20: =H19+E20+F20 -> 1602174 | O20: TÀI SẢN DÀI HẠN | R20: 6000000
A21: 45767 | B21: 日 | C21: 389181 | D21: 510295 | E21: =C21-D21 -> -121114 | F21: -11 | G21: 0 | H21: =H20+E21+F21 -> 1481049 | I21: 参考 | O21: TỔNG | R21: =SUM(R12:R20) -> 12524462
A22: 45768 | B22: 月 | C22: 380275 | D22: 242262 | E22: =C22-D22 -> 138013 | F22: 0 | G22: 0 | H22: =H21+E22+F22 -> 1619062 | I22: Giảm giá HD | J22: Khấu hao HĐ | K22: Wifi | L22: Bảo hiểm quán ** | M22: TRẢ - HUỶ | N22: TỔNG
A23: 45769 | B23: 火 | C23: 233850 | D23: 190270 | E23: =C23-D23 -> 43580 | F23: -85 | G23: 0 | H23: =H22+E23+F23 -> 1662557 | I23: 706 | J23: 50000 | K23: 0 | L23: 33000 | M23: 42780 | N23: =SUM(J23:M23) -> 125780 | O23: NỢ + CÁC KHOẢN VAY
A24: 45770 | B24: 水 | C24: 372889 | D24: 718572 | E24: =C24-D24 -> -345683 | F24: 0 | G24: 0 | H24: =H23+E24+F24 -> 1316874 | O24: NỢ NGẮN HẠN
A25: 45771 | B25: 木 | C25: 354516 | D25: 182617 | E25: =C25-D25 -> 171899 | F25: -455 | G25: 0 | H25: =H24+E25+F25 -> 1488318 | I25: THUYẾT MINH
A26: 45772 | B26: 金 | C26: 1503777 | D26: 297677 | E26: =C26-D26 -> 1206100 | F26: 0 | G26: 0 | H26: =H25+E26+F26 -> 2694418 | J26: Mua thêm tủ lạnh 130,000JPY
A27: 45773 | B27: 土 | C27: 938886 | D27: 275451 | E27: =C27-D27 -> 663435 | F27: -45 | G27: 0 | H27: =H26+E27+F27 -> 3357808 | J27: Không trích lập dự phòng
A28: 45774 | B28: 日 | C28: 503877 | D28: 572911 | E28: =C28-D28 -> -69034 | F28: -451 | G28: 0 | H28: =H27+E28+F28 -> 3288323 | J28: GIÁ TRỊ TỒN KHO +900,000 (90MAN)
A29: 45775 | B29: 月 | C29: 522822 | D29: 541780 | E29: =C29-D29 -> -18958 | F29: -4 | G29: 0 | H29: =H28+E29+F29 -> 3269361 | O29: NỢ DÀI HẠN
A30: 45776 | B30: 火 | C30: 580679 | D30: 838508 | E30: =C30-D30 -> -257829 | F30: 0 | G30: 0 | H30: =H29+E30+F30 -> 3011532
A31: 45777 | B31: 水 | C31: 471104 | D31: 1393068 | E31: =C31-D31 -> -921964 | F31: 0 | G31: 0 | H31: =H30+E31+F31 -> 2089568
D32: 50000 | E32: =C32-D32 -> -50000 | G32: 0 | H32: =H31+E32+F32 -> 2039568
G33: 0 | H33: =H32+E33+F33 -> 2039568
A34: TỔNG | C34: =SUM(C2:C33) -> 18224357 | D34: =SUM(D2:D33) -> 16179744 | E34: =SUM(E2:E33) -> 2044613 | F34: =SUM(F2:F33) -> -5045 | G34: =SUM(G2:G33) -> 0 | H34: =C34-D34+G34 -> 2044613

Sheet 2025_5
A1: 日付 | C1: 売上 | D1: 支出 | E1: 入金 | F1: 不足 | G1: デリバリ | H1: 累計 | J1: NHẬP HÀNG | K1: XĂNG -DẦU | L1: TÚI BÓNG | M1: BĂNG DÍNH | N1: KHÁC* | O1: PHÍ CỐ ĐỊNH | Q1: BÁO CÁO THÁNG 05 /2025 | X1: BẢNG CƠ CẤU CHI PHÍ CHI PHÍ | AE1: Bổ sung 補足
A2: 45778 | B2: 木 | C2: 949479 | D2: 516192 | E2: =C2-D2 -> 433287 | F2: 0 | G2: 0 | H2: =E2+F2 -> 433287 | J2: =D2-SUM(K2:O2) -> 483979 | K2: =11055+9000 -> 20055 | L2: 12158 | Q2: THU | X2: CHI PHÍ KINH DOANH | AB2: =Z13+AC13 -> 0.88942638 | AE2: Bảo hiểm quán **
A3: 45779 | B3: 金 | C3: 1059838 | D3: 650204 | E3: =C3-D3 -> 409634 | F3: -100 | G3: 0 | H3: =H2+E3+F3 -> 842821 | J3: =D3-SUM(K3:O3) -> 642541 | K3: =7663 -> 7663 | Q3: TỔNG | S3: SHIP BD | T3: SHIP | U3: Chênh lệch | V3: POINT | X3: CỐ ĐỊNH | AA3: LƯU ĐỘNG
A4: 45780 | B4: 土 | C4: 723294 | D4: 313528 | E4: =C4-D4 -> 409766 | F4: -952 | G4: 0 | H4: =H3+E4+F4 -> 1251635 | J4: =D4-SUM(K4:O4) -> 304662 | M4: 3366 | O4: 5500 | Q4: =C34 -> 19619825 | S4: 0 | T4: 0 | U4: =F34 -> -6480 | V4: 29761 | X4: TIỀN NHÀ | Y4: 132550 | Z4: =Y4/$Q$4 -> 0.0067559216 | AA4: LƯƠNG | AB4: =SUM(Q13:W13)+75000 -> 999600 | AC4: =AB4/$Q$4 -> 0.050948467
A5: 45781 | B5: 日 | C5: 468840 | D5: 376707 | E5: =C5-D5 -> 92133 | F5: -200 | G5: 0 | H5: =H4+E5+F5 -> 1343568 | J5: =D5-SUM(K5:O5) -> 376707 | S5: =S4/Q4 -> 0 | T5: =T4/Q4 -> 0 | U5: =U4/Q4 -> -0.00033027818 | V5: =V4/Q4 -> 0.0015168841 | X5: BÃI XE | Y5: 26055 | Z5: =Y5/$Q$4 -> 0.0013279935 | AA5: THƯỞNG | AB5: =SUM(Q14:W14) -> 0 | AC5: =AB5/$Q$4 -> 0 | AE5: Lương *
A6: 45782 | B6: 月 | C6: 415370 | D6: 329718 | E6: =C6-D6 -> 85652 | F6: 0 | G6: 0 | H6: =H5+E6+F6 -> 1429220 | J6: =D6-SUM(K6:O6) -> 289272 | K6: 8898 | N6: 31548 | Q6: CHI | X6: WIFI | Y6: 5280 | Z6: =Y6/$Q$4 -> 0.00026911555 | AA6: TIỀN ĐIỆN | AB6: 48397 | AC6: =AB6/$Q$4 -> 0.0024667396 | AE6: Anh Giang
A7: 45783 | B7: 火 | C7: 388189 | D7: 821606 | E7: =C7-D7 -> -433417 | F7: 0 | G7: 0 | H7: =H6+E7+F7 -> 995803 | J7: =D7-SUM(K7:O7) -> 821606 | Q7: NHẬP HÀNG | R7: LƯƠNG | S7: CHI KHÁC | U7: TỔNG | X7: BẢO HIỂM | Y7: 33000 | Z7: =Y7/$Q$4 -> 0.0016819722 | AA7: TIỀN NƯỚC | AB7: =2890+3396 -> 6286 | AC7: =AB7/$Q$4 -> 0.00032039022 | AE7: Lương CB | AF7: 300000
A8: 45784 | B8: 水 | C8: 412545 | D8: 838601 | E8: =C8-D8 -> -426056 | F8: 0 | G8: 0 | H8: =H7+E8+F8 -> 569747 | J8: =D8-SUM(K8:O8) -> 838601 | Q8: =D34 -> 16415400 | R8: =T16 -> 999600 | S8: =V19 -> 208180 | U8: =SUM(Q8:T8) -> 17623180 | X8: DIỆT GIÁN | Y8: 5500 | Z8: =Y8/$Q$4 -> 0.0002803287 | AA8: BĂNG DÍNH | AB8: =M34 -> 23014 | AC8: =AB8/$Q$4 -> 0.0011729972 | AE8: Ship ngoài giờ | AF8: 55000
A9: 45785 | B9: 木 | C9: 457935 | D9: 44180 | E9: =C9-D9 -> 413755 | F9: -411 | G9: 0 | H9: =H8+E9+F9 -> 983091 | J9: =D9-SUM(K9:O9) -> 44180 | Q9: LỢI NHUẬN | R9: =Q4-U8-U4+T4 -> 2003125 | X9: PHÍ LUẬT SƯ | Y9: 187000 | Z9: =Y9/$Q$4 -> 0.0095311757 | AA9: TÚI BÓNG | AB9: =L34 -> 75496 | AC9: =AB9/$Q$4 -> 0.0038479446 | AE9: 社会保険 | AF9: 35000
A10: 45786 | B10: 金 | C10: 673180 | D10: 675272 | E10: =C10-D10 -> -2092 | F10: 0 | G10: 0 | H10: =H9+E10+F10 -> 980999 | J10: =D10-SUM(K10:O10) -> 641550 | K10: 6062 | N10: 27660 | Q10: CHI TIẾT | X10: THUẾ XE | Y10: 90800 | Z10: =Y10/$Q$4 -> 0.004627972 | AA10: XĂNG | AB10: =K34 -> 127052 | AC10: =AB10/$Q$4 -> 0.0064756949 | AE10: Tổng | AF10: =SUM(AF7:AF9) -> 390000
A11: 45787 | B11: 土 | C11: 1052333 | D11: 185384 | E11: =C11-D11 -> 866949 | F11: -841 | G11: 0 | H11: =H10+E11+F11 -> 1847107 | J11: =D11-SUM(K11:O11) -> 179575 | L11: 3739 | M11: 2070 | Q11: LƯƠNG - 給与 | X11: THUẾ | Y11: 313600 | Z11: =Y11/$Q$4 -> 0.015983833 | AA11: NHẬP HÀNG | AB11: =J34 -> 15063976 | AC11: =AB11/$Q$4 -> 0.7677936 | AE11: TÀI SẢN CÔNG TY
A12: 45788 | B12: 日 | C12: 469218 | D12: 632916 | E12: =C12-D12 -> -163698 | F12: 0 | G12: 0 | H12: =H11+E12+F12 -> 1683409 | J12: =D12-SUM(K12:O12) -> 604870 | K12: 20400 | L12: 7646 | Q12: A. Giang | R12: A.Thái | S12: C.Hiền | T12: Nhàn | U12: Cưng | V12: Nghĩa | W12: Hoàn | AA12: CHI KHÁC | AB12: =N34 -> 312784 | AC12: =AB12/$Q$4 -> 0.015942242 | AE12: LỢI NHUẬN GỘP | AH12: 0
A13: 45789 | B13: 月 | C13: 396098 | D13: 749401 | E13: =C13-D13 -> -353303 | F13: 0 | G13: 0 | H13: =H12+E13+F13 -> 1330106 | J13: =D13-SUM(K13:O13) -> 739944 | K13: 9457 | Q13: =AF10-75000 -> 315000 | R13: 55000 | S13: 128500 | T13: =75*1100 -> 82500 | U13: =66*1100 -> 72600 | V13: 150000 | W13: =110*1100 -> 121000 | X13: TỔNG | Y13: =SUM(Y4:Y12) -> 793785 | Z13: =SUM(Z4:Z12) -> 0.040458312 | AA13: TỔNG | AB13: =SUM(AB4:AB12) -> 16656605 | AC13: =SUM(AC4:AC12) -> 0.84896807 | AE13: TIỀN MẶT | AG13: JPY | AH13: 2365016
A14: 45790 | B14: 火 | C14: 548633 | D14: 63075 | E14: =C14-D14 -> 485558 | F14: -12 | G14: 0 | H14: =H13+E14+F14 -> 1815652 | J14: =D14-SUM(K14:O14) -> 63075 | Q14: 0 | R14: 0 | S14: 0 | T14: 0 | U14: 0 | V14: 0 | W14: 0 | X14: CHI PHÍ PHÁT SINH KHÁC | AB14: =Z21+AC21 -> 0.010618545 | AG14: VND | AH14: 293211
A15: 45791 | B15: 水 | C15: 420960 | D15: 1057329 | E15: =C15-D15 -> -636369 | F15: -514 | G15: 0 | H15: =H14+E15+F15 -> 1178769 | J15: =D15-SUM(K15:O15) -> 1057329 | Q15: =SUM(Q13:Q14) -> 315000 | R15: =SUM(R13:R14) -> 55000 | S15: =SUM(S13:S14) -> 128500 | T15: =SUM(T13:T14) -> 82500 | U15: =SUM(U13:U14) -> 72600 | V15: =SUM(V13:V14) -> 150000 | W15: =SUM(W13:W14) -> 121000 | X15: KHẤU TRỪ | AA15: THU KHÁC | AE15: ATM | AF15: CÁ NHÂN | AH15: 13227
A16: 45792 | B16: 木 | C16: 895919 | D16: 139798 | E16: =C16-D16 -> 756121 | F16: 0 | G16: 0 | H16: =H15+E16+F16 -> 1934890 | J16: =D16-SUM(K16:O16) -> 120160 | K16: 6000 | L16: 13638 | Q16: TỔNG | T16: =SUM(R15:W15)+AF10 -> 999600 | X16: HỦY ĐƠN | Y16: =T23 -> 32400 | Z16: =Y16/$Q$4 -> 0.0016513909 | AA16: TT ĐIỂM | AB16: =V4 -> 29761 | AC16: =AB16/$Q$4 -> 0.0015168841 | AF16: CÔNG TY | AH16: 372890
A17: 45793 | B17: 金 | C17: 1126216 | D17: 157147 | E17: =C17-D17 -> 969069 | F17: -451 | G17: 0 | H17: =H16+E17+F17 -> 2903508 | J17: =D17-SUM(K17:O17) -> 108750 | O17: 48397 | Q17: CHI KHÁC - その他 | X17: TRẢ HÀNG | Y17: =U23 -> 92780 | Z17: =Y17/$Q$4 -> 0.0047288903 | AA17: GIẢM GIÁ HĐ | AB17: =Q23 -> 3393 | AC17: =AB17/$Q$4 -> 0.00017293732 | AE17: NỢ | AF17: KHÁCH NỢ | AH17: 812296
A18: 45794 | B18: 土 | C18: 850714 | D18: 543702 | E18: =C18-D18 -> 307012 | F18: -741 | G18: 0 | H18: =H17+E18+F18 -> 3209779 | J18: =D18-SUM(K18:O18) -> 538002 | M18: 5700 | T18: Bảo hiểm quán ** | U18: Khác | V18: TỔNG | X18: TRỪ SHIP | Y18: =S23 -> 0 | Z18: =Y18/$Q$4 -> 0 | AE18: TIỀN & CÁC KHOẢN TƯƠNG ĐƯƠNG | AH18: 1067000
A19: 45795 | B19: 日 | C19: 374314 | D19: 994416 | E19: =C19-D19 -> -620102 | F19: 0 | G19: 0 | H19: =H18+E19+F19 -> 2589677 | J19: =D19-SUM(K19:O19) -> 977676 | K19: =8700+7000 -> 15700 | N19: 1040 | T19: 33000 | U19: =V23 -> 175180 | V19: =SUM(Q19:U19) -> 208180 | X19: KHẤU HAO HĐ | Y19: =R23 -> 50000 | Z19: =Y19/$Q$4 -> 0.0025484427 | AE19: GIÁ TRỊ KHO ƯỚC TÍNH | AH19: 6335494
A20: 45796 | B20: 月 | C20: 420908 | D20: 567058 | E20: =C20-D20 -> -146150 | F20: -41 | G20: 0 | H20: =H19+E20+F20 -> 2443486 | J20: =D20-SUM(K20:O20) -> 567058 | AE20: TÀI SẢN DÀI HẠN | AH20: 6000000
A21: 45797 | B21: 火 | C21: 336508 | D21: 631326 | E21: =C21-D21 -> -294818 | F21: -146 | G21: 0 | H21: =H20+E21+F21 -> 2148522 | J21: =D21-SUM(K21:O21) -> 631326 | Q21: 参考 | X21: TỔNG | Y21: =SUM(Y16:Y20) -> 175180 | Z21: =SUM(Z16:Z20) -> 0.0089287239 | AA21: TỔNG | AB21: =SUM(AB16:AB20) -> 33154 | AC21: =SUM(AC16:AC20) -> 0.0016898214 | AE21: TỔNG | AH21: =SUM(AH12:AH20) -> 17259134
A22: 45798 | B22: 水 | C22: 250622 | D22: 810381 | E22: =C22-D22 -> -559759 | F22: 0 | G22: 0 | H22: =H21+E22+F22 -> 1588763 | J22: =D22-SUM(K22:O22) -> 810381 | Q22: Giảm giá HD | R22: Khấu hao HĐ | S22: TRỪ SHIP | T22: HỦY ĐƠN | U22: TRẢ HÀNG | V22: TỔNG | X22: TỔNG CHI PHÍ | AB22: =AB14+AB2 -> 0.90004493
A23: 45799 | B23: 木 | C23: 639332 | D23: 393158 | E23: =C23-D23 -> 246174 | F23: 0 | G23: 0 | H23: =H22+E23+F23 -> 1834937 | J23: =D23-SUM(K23:O23) -> 379512 | K23: 9000 | M23: 4646 | Q23: 3393 | R23: 50000 | S23: 0 | T23: 32400 | U23: 92780 | V23: =SUM(R23:U23) -> 175180 | AE23: NỢ + CÁC KHOẢN VAY
A24: 45800 | B24: 金 | C24: 1366411 | D24: 143072 | E24: =C24-D24 -> 1223339 | F24: -417 | G24: 0 | H24: =H23+E24+F24 -> 3057859 | J24: =D24-SUM(K24:O24) -> 125792 | N24: 17280 | X24: BÁO CÁO TỔNG QUAN | AE24: NỢ NGẮN HẠN
A25: 45801 | B25: 土 | C25: 768211 | D25: 768332 | E25: =C25-D25 -> -121 | F25: -521 | G25: 0 | H25: =H24+E25+F25 -> 3057217 | J25: =D25-SUM(K25:O25) -> 552885 | K25: 6010 | L25: 21837 | N25: 600 | O25: 187000 | Q25: THUYẾT MINH | Y25: THÁNG TRƯỚC | AA25: THÁNG NÀY | AB25: CÙNG KỲ
A26: 45802 | B26: 日 | C26: 646146 | D26: 279563 | E26: =C26-D26 -> 366583 | F26: 0 | G26: 0 | H26: =H25+E26+F26 -> 3423800 | J26: =D26-SUM(K26:O26) -> 278790 | N26: 773 | R26: Nhập hàng chiếm 76,78% | X26: DOANH THU | Y26: 18224357 | Z26: =(AA26/Y26)-100% -> 0.07657159 | AA26: =C34 -> 19619825 | AB26: 14861786 | AC26: =AA26/AB26-100% -> 0.32015257
A27: 45803 | B27: 月 | C27: 461449 | D27: 417110 | E27: =C27-D27 -> 44339 | F27: 0 | G27: 0 | H27: =H26+E27+F27 -> 3468139 | J27: =D27-SUM(K27:O27) -> 417110 | R27: Các chi phí khác chiếm 13,22% | X27: CHI | Y27: ='2025_4'!M8 -> 17246124 | Z27: =(AA27/Y27)-100% -> 0.021863231 | AA27: =U8 -> 17623180 | AB27: ='2024_5'!M8 -> 13682046 | AC27: =AA27/AB27-100% -> 0.28805151
A28: 45804 | B28: 火 | C28: 501169 | D28: 359550 | E28: =C28-D28 -> 141619 | F28: -254 | G28: 0 | H28: =H27+E28+F28 -> 3609504 | J28: =D28-SUM(K28:O28) -> 214939 | K28: 3520 | M28: 7232 | N28: 33883 | O28: =2890+6286+90800 -> 99976 | R28: Lợi nhuận Ròng 10,00% | X28: LỢI NHUẬN | Y28: ='2025_4'!J9 -> 954902 | Z28: =(AA28/Y28)-100% -> 1.0977284 | AA28: =R9 -> 2003125 | AB28: ='2024_5'!J9 -> 1179740 | AC28: =AA28/AB28-100% -> 0.69793768
A29: 45805 | B29: 水 | C29: 415420 | D29: 1236702 | E29: =C29-D29 -> -821282 | F29: -51 | G29: 0 | H29: =H28+E29+F29 -> 2788171 | J29: =D29-SUM(K29:O29) -> 908815 | K29: =6778+7509 -> 14287 | O29: 313600 | X29: SỐ HÓA ĐƠN | Y29: 3684 | Z29: =(AA29/Y29)-100% -> 0.094733985 | AA29: 4033 | AB29: 3524 | AC29: =AA29/AB29-100% -> 0.14443814 | AE29: NỢ DÀI HẠN
A30: 45806 | B30: 木 | C30: 491236 | D30: 779059 | E30: =C30-D30 -> -287823 | F30: 0 | G30: 0 | H30: =H29+E30+F30 -> 2500348 | J30: =D30-SUM(K30:O30) -> 620454 | O30: =132550+26055 -> 158605 | X30: TB HÓA ĐƠN | Y30: =Y26/Y29 -> 4946.8939 | Z30: =(AA30/Y30)-100% -> -0.016590692 | AA30: =AA26/AA29 -> 4864.8215 | AB30: =AB26/AB29 -> 4217.3059 | AC30: =AA30/AB30-100% -> 0.15353773
A31: 45807 | B31: 金 | C31: 742011 | D31: 344562 | E31: =C31-D31 -> 397449 | F31: -244 | G31: 0 | H31: =H30+E31+F31 -> 2897553 | J31: =D31-SUM(K31:O31) -> 328084 | L31: 16478 | X31: TB NGÀY | Y31: =Y26/30 -> 607478.57 | Z31: =(AA31/Y31)-100% -> 0.041843475 | AA31: =AA26/31 -> 632897.58 | AB31: =AB26/31 -> 479412.45 | AC31: =AA31/AB31-100% -> 0.32015257
A32: 45808 | B32: 土 | C32: 897327 | D32: 396351 | E32: =C32-D32 -> 500976 | F32: -584 | G32: 0 | H32: =H31+E32+F32 -> 3397945 | J32: =D32-SUM(K32:O32) -> 396351
D33: 200000 | E33: =C33-D33 -> -200000 | G33: 0 | H33: =H32+E33+F33 -> 3197945 | J33: =D33-SUM(K33:N33) -> 0 | N33: 200000
A34: TỔNG | C34: =SUM(C2:C33) -> 19619825 | D34: =SUM(D2:D33) -> 16415400 | E34: =SUM(E2:E33) -> 3204425 | F34: =SUM(F2:F33) -> -6480 | G34: =SUM(G2:G33) -> 0 | H34: =C34-D34+G34 -> 3204425 | J34: =SUM(J2:J33) -> 15063976 | K34: =SUM(K2:K33) -> 127052 | L34: =SUM(L2:L33) -> 75496 | M34: =SUM(M2:M33) -> 23014 | N34: =SUM(N2:N33) -> 312784 | O34: =SUM(O2:O33) -> 813078

Sheet 2025_6
A1: 日付 | C1: 売上 | D1: 支出 | E1: 入金 | F1: 不足 | G1: デリバリ | H1: 累計 | J1: NHẬP HÀNG | K1: XĂNG -DẦU | L1: TÚI BÓNG | M1: BĂNG DÍNH | N1: KHÁC* | O1: PHÍ CỐ ĐỊNH | Q1: BÁO CÁO THÁNG 06 /2025 | X1: BẢNG CƠ CẤU CHI PHÍ CHI PHÍ | AE1: Bổ sung 補足
A2: 45809 | B2: 日 | C2: 464914 | D2: 262450 | E2: =C2-D2 -> 202464 | F2: 0 | G2: 0 | H2: =E2+F2 -> 202464 | J2: =D2-SUM(K2:O2) -> 262450 | Q2: THU | X2: CHI PHÍ KINH DOANH | AB2: =Z13+AC13 -> 0.91808519 | AE2: Bảo hiểm quán **
A3: 45810 | B3: 月 | C3: 393165 | D3: 681162 | E3: =C3-D3 -> -287997 | F3: -100 | G3: 0 | H3: =H2+E3+F3 -> -85633 | J3: =D3-SUM(K3:O3) -> 674046 | K3: 7116 | Q3: TỔNG | S3: SHIP BD | T3: SHIP | U3: Chênh lệch | V3: POINT | X3: CỐ ĐỊNH | AA3: LƯU ĐỘNG
A4: 45811 | B4: 火 | C4: 442082 | D4: 570280 | E4: =C4-D4 -> -128198 | F4: -952 | G4: 0 | H4: =H3+E4+F4 -> -214783 | J4: =D4-SUM(K4:O4) -> 570280 | Q4: =C34 -> 16973354 | S4: 0 | T4: 0 | U4: =-F34 -> 5896 | V4: 13956 | X4: TIỀN NHÀ | Y4: 132550 | Z4: =Y4/$Q$4 -> 0.0078092992 | AA4: LƯƠNG | AB4: =SUM(Q13:W13)+75000 -> 959900 | AC4: =AB4/$Q$4 -> 0.056553348
A5: 45812 | B5: 水 | C5: 356423 | D5: 134669 | E5: =C5-D5 -> 221754 | F5: -200 | G5: 0 | H5: =H4+E5+F5 -> 6771 | J5: =D5-SUM(K5:O5) -> 134669 | S5: =S4/Q4 -> 0 | T5: =T4/Q4 -> 0 | U5: =U4/Q4 -> 0.000347368 | V5: =V4/Q4 -> 0.00082222995 | X5: BÃI XE | Y5: 26055 | Z5: =Y5/$Q$4 -> 0.0015350531 | AA5: THƯỞNG | AB5: =SUM(Q14:W14) -> 9000 | AC5: =AB5/$Q$4 -> 0.00053024287 | AE5: Lương *
A6: 45813 | B6: 木 | C6: 497900 | D6: 356393 | E6: =C6-D6 -> 141507 | F6: 0 | G6: 0 | H6: =H5+E6+F6 -> 148278 | J6: =D6-SUM(K6:O6) -> 240394 | K6: 6666 | M6: 4636 | N6: =1117+68424+35156 -> 104697 | Q6: CHI | X6: WIFI | Y6: 6080 | Z6: =Y6/$Q$4 -> 0.00035820852 | AA6: TIỀN ĐIỆN | AB6: 68424 | AC6: =AB6/$Q$4 -> 0.0040312598 | AE6: Anh Giang
A7: 45814 | B7: 金 | C7: 854113 | D7: 664172 | E7: =C7-D7 -> 189941 | F7: 0 | G7: 0 | H7: =H6+E7+F7 -> 338219 | J7: =D7-SUM(K7:O7) -> 664172 | Q7: NHẬP HÀNG | R7: LƯƠNG | S7: CHI KHÁC | U7: TỔNG | X7: BẢO HIỂM | Y7: 33000 | Z7: =Y7/$Q$4 -> 0.0019442239 | AA7: TIỀN NƯỚC | AB7: =2890+3396 -> 6286 | AC7: =AB7/$Q$4 -> 0.00037034519 | AE7: Lương CB | AF7: 300000
A8: 45815 | B8: 土 | C8: 634142 | D8: 822670 | E8: =C8-D8 -> -188528 | F8: 0 | G8: 0 | H8: =H7+E8+F8 -> 149691 | J8: =D8-SUM(K8:O8) -> 822670 | Q8: =D34 -> 14580320 | R8: =T16 -> 968900 | S8: =V19 -> 165906 | U8: =SUM(Q8:T8) -> 15715126 | X8: DIỆT GIÁN | Y8: 5500 | Z8: =Y8/$Q$4 -> 0.00032403731 | AA8: BĂNG DÍNH | AB8: =M34 -> 15569 | AC8: =AB8/$Q$4 -> 0.00091726126 | AE8: Ship ngoài giờ | AF8: 55000
A9: 45816 | B9: 日 | C9: 356441 | D9: 902304 | E9: =C9-D9 -> -545863 | F9: -411 | G9: 0 | H9: =H8+E9+F9 -> -396583 | J9: =D9-SUM(K9:O9) -> 709804 | O9: =187000+5500 -> 192500 | Q9: LỢI NHUẬN | R9: =Q4-U8-V4-U4 -> 1238376 | X9: PHÍ LUẬT SƯ | Y9: 187000 | Z9: =Y9/$Q$4 -> 0.011017269 | AA9: TÚI BÓNG | AB9: =L34 -> 47712 | AC9: =AB9/$Q$4 -> 0.0028109942 | AE9: 社会保険 | AF9: 35000
A10: 45817 | B10: 月 | C10: 274819 | D10: 180285 | E10: =C10-D10 -> 94534 | F10: 0 | G10: 0 | H10: =H9+E10+F10 -> -302049 | J10: =D10-SUM(K10:O10) -> 180285 | Q10: CHI TIẾT | X10: THUẾ XE | Y10: 0 | Z10: =Y10/$Q$4 -> 0 | AA10: XĂNG | AB10: =K34 -> 79669 | AC10: =AB10/$Q$4 -> 0.0046937688 | AE10: Tổng | AF10: =SUM(AF7:AF9) -> 390000
A11: 45818 | B11: 火 | C11: 649453 | D11: 0 | E11: =C11-D11 -> 649453 | F11: -841 | G11: 0 | H11: =H10+E11+F11 -> 346563 | J11: =D11-SUM(K11:O11) -> 0 | Q11: LƯƠNG - 給与 | X11: THUẾ | Y11: 0 | Z11: =Y11/$Q$4 -> 0 | AA11: NHẬP HÀNG | AB11: =J34 -> 13766469 | AC11: =AB11/$Q$4 -> 0.81106356 | AE11: TÀI SẢN CÔNG TY
A12: 45819 | B12: 水 | C12: 420734 | D12: 651196 | E12: =C12-D12 -> -230462 | F12: 0 | G12: 0 | H12: =H11+E12+F12 -> 116101 | J12: =D12-SUM(K12:O12) -> 641544 | K12: 7777 | M12: 1875 | Q12: A. Giang | R12: A.Thái | S12: C.Hiền | T12: Nhàn | U12: Cưng | V12: Nghĩa | W12: Hoàn | AA12: CHI KHÁC | AB12: =N34 -> 239771 | AC12: =AB12/$Q$4 -> 0.014126318 | AE12: LỢI NHUẬN GỘP | AH12: 0
A13: 45820 | B13: 木 | C13: 661417 | D13: 136095 | E13: =C13-D13 -> 525322 | F13: 0 | G13: 0 | H13: =H12+E13+F13 -> 641423 | J13: =D13-SUM(K13:O13) -> 117530 | K13: 10251 | L13: 8314 | Q13: =AF10-75000 -> 315000 | R13: =47.5*1100 -> 52250 | S13: =110.5*1100 -> 121550 | T13: =81.5*1100 -> 89650 | U13: =64*1100 -> 70400 | V13: 120000 | W13: =105.5*1100 -> 116050 | X13: TỔNG | Y13: =SUM(Y4:Y12) -> 390185 | Z13: =SUM(Z4:Z12) -> 0.022988091 | AA13: TỔNG | AB13: =SUM(AB4:AB12) -> 15192800 | AC13: =SUM(AC4:AC12) -> 0.8950971 | AE13: TIỀN MẶT | AG13: JPY | AH13: 1900000
A14: 45821 | B14: 金 | C14: 1178690 | D14: 191067 | E14: =C14-D14 -> 987623 | F14: -12 | G14: 0 | H14: =H13+E14+F14 -> 1629034 | J14: =D14-SUM(K14:O14) -> 184400 | K14: 6667 | Q14: 0 | R14: 0 | S14: 0 | T14: 3000 | U14: 3000 | V14: 0 | W14: 3000 | X14: CHI PHÍ PHÁT SINH KHÁC | AB14: =Z21+AC21 -> 0.0091954719 | AG14: VND | AH14: 133394
A15: 45822 | B15: 土 | C15: 889904 | D15: 384745 | E15: =C15-D15 -> 505159 | F15: -514 | G15: 0 | H15: =H14+E15+F15 -> 2133679 | J15: =D15-SUM(K15:O15) -> 381613 | M15: 2612 | N15: 520 | Q15: =SUM(Q13:Q14) -> 315000 | R15: =SUM(R13:R14) -> 52250 | S15: =SUM(S13:S14) -> 121550 | T15: =SUM(T13:T14) -> 92650 | U15: =SUM(U13:U14) -> 73400 | V15: =SUM(V13:V14) -> 120000 | W15: =SUM(W13:W14) -> 119050 | X15: KHẤU TRỪ | AA15: THU KHÁC | AE15: ATM | AF15: CÁ NHÂN | AH15: 33127
A16: 45823 | B16: 日 | C16: 397481 | D16: 898836 | E16: =C16-D16 -> -501355 | F16: 0 | G16: 0 | H16: =H15+E16+F16 -> 1632324 | J16: =D16-SUM(K16:O16) -> 893212 | L16: 5624 | Q16: TỔNG | T16: =SUM(R15:W15)+AF10 -> 968900 | X16: HỦY ĐƠN | Y16: =T23 -> 22400 | Z16: =Y16/$Q$4 -> 0.0013197156 | AA16: TT ĐIỂM | AB16: =V4 -> 13956 | AC16: =AB16/$Q$4 -> 0.00082222995 | AF16: CÔNG TY | AH16: 1566251
A17: 45824 | B17: 月 | C17: 413714 | D17: 575375 | E17: =C17-D17 -> -161661 | F17: -451 | G17: 0 | H17: =H16+E17+F17 -> 1470212 | J17: =D17-SUM(K17:O17) -> 575375 | Q17: CHI KHÁC - その他 | X17: TRẢ HÀNG | Y17: =U23 -> 50781 | Z17: =Y17/$Q$4 -> 0.002991807 | AA17: GIẢM GIÁ HĐ | AB17: =Q23 -> 3320 | AC17: =AB17/$Q$4 -> 0.0001956007 | AE17: NỢ | AF17: KHÁCH NỢ | AH17: 812296
A18: 45825 | B18: 火 | C18: 350957 | D18: 500168 | E18: =C18-D18 -> -149211 | F18: -741 | G18: 0 | H18: =H17+E18+F18 -> 1320260 | J18: =D18-SUM(K18:O18) -> 408675 | K18: 7319 | N18: 84174 | T18: Bảo hiểm quán ** | U18: Khác | V18: TỔNG | X18: TRỪ SHIP | Y18: =S23 -> 9725 | Z18: =Y18/$Q$4 -> 0.00057295688 | AE18: TIỀN & CÁC KHOẢN TƯƠNG ĐƯƠNG | AH18: 70000
A19: 45826 | B19: 水 | C19: 246800 | D19: 983473 | E19: =C19-D19 -> -736673 | F19: 0 | G19: 0 | H19: =H18+E19+F19 -> 583587 | J19: =D19-SUM(K19:O19) -> 983473 | T19: 33000 | U19: =V23 -> 132906 | V19: =SUM(Q19:U19) -> 165906 | X19: KHẤU HAO HĐ | Y19: =R23 -> 50000 | Z19: =Y19/$Q$4 -> 0.0029457937 | AE19: GIÁ TRỊ KHO ƯỚC TÍNH | AH19: 5500390
A20: 45827 | B20: 木 | C20: 462095 | D20: 158967 | E20: =C20-D20 -> 303128 | F20: -41 | G20: 0 | H20: =H19+E20+F20 -> 886674 | J20: =D20-SUM(K20:O20) -> 138850 | K20: =7699+3850 -> 11549 | L20: 8568 | X20: CHÊNH LỆCH | Y20: =U4 -> 5896 | Z20: =Y20/$Q$4 -> 0.000347368 | AE20: TÀI SẢN DÀI HẠN | AH20: 6000000
A21: 45828 | B21: 金 | C21: 626104 | D21: 115531 | E21: =C21-D21 -> 510573 | F21: -146 | G21: 0 | H21: =H20+E21+F21 -> 1397101 | J21: =D21-SUM(K21:O21) -> 70745 | M21: 6446 | N21: =3900+34440 -> 38340 | Q21: 参考 | X21: TỔNG | Y21: =SUM(Y16:Y20) -> 138802 | Z21: =SUM(Z16:Z20) -> 0.0081776413 | AA21: TỔNG | AB21: =SUM(AB16:AB20) -> 17276 | AC21: =SUM(AC16:AC20) -> 0.0010178307 | AE21: TỔNG | AH21: =SUM(AH12:AH20) -> 16015458
A22: 45829 | B22: 土 | C22: 792281 | D22: 220707 | E22: =C22-D22 -> 571574 | F22: 0 | G22: 0 | H22: =H21+E22+F22 -> 1968675 | J22: =D22-SUM(K22:O22) -> 220707 | Q22: Giảm giá HD | R22: Khấu hao HĐ | S22: TRỪ SHIP | T22: HỦY ĐƠN | U22: TRẢ HÀNG | V22: TỔNG | X22: TỔNG CHI PHÍ | AB22: =AB14+AB2 -> 0.92728067
A23: 45830 | B23: 日 | C23: 319650 | D23: 455436 | E23: =C23-D23 -> -135786 | F23: 0 | G23: 0 | H23: =H22+E23+F23 -> 1832889 | J23: =D23-SUM(K23:O23) -> 455436 | Q23: 3320 | R23: 50000 | S23: 9725 | T23: 22400 | U23: 50781 | V23: =SUM(R23:U23) -> 132906 | AE23: NỢ + CÁC KHOẢN VAY
A24: 45831 | B24: 月 | C24: 293894 | D24: 206427 | E24: =C24-D24 -> 87467 | F24: -417 | G24: 0 | H24: =H23+E24+F24 -> 1919939 | J24: =D24-SUM(K24:O24) -> 198650 | K24: 7777 | X24: BÁO CÁO TỔNG QUAN | AE24: NỢ NGẮN HẠN
A25: 45832 | B25: 火 | C25: 358874 | D25: 414440 | E25: =C25-D25 -> -55566 | F25: -521 | G25: 0 | H25: =H24+E25+F25 -> 1863852 | J25: =D25-SUM(K25:O25) -> 404120 | L25: 9800 | N25: 520 | Q25: THUYẾT MINH | Y25: THÁNG TRƯỚC | AA25: THÁNG NÀY | AB25: CÙNG KỲ
A26: 45833 | B26: 水 | C26: 579662 | D26: 536562 | E26: =C26-D26 -> 43100 | F26: 0 | G26: 0 | H26: =H25+E26+F26 -> 1906952 | J26: =D26-SUM(K26:O26) -> 519462 | N26: 11020 | O26: 6080 | R26: Nhập hàng / Doanh thu TĂNG 4,33% | X26: DOANH THU | Y26: 19619825 | Z26: =(AA26/Y26)-100% -> -0.13488759 | AA26: =C34 -> 16973354 | AB26: 14566013 | AC26: =AA26/AB26-100% -> 0.1652711
A27: 45834 | B27: 木 | C27: 877677 | D27: 420435 | E27: =C27-D27 -> 457242 | F27: 0 | G27: 0 | H27: =H26+E27+F27 -> 2364194 | J27: =D27-SUM(K27:O27) -> 401180 | K27: 14547 | L27: 4208 | N27: 500 | R27: Nhập hàng chiếm 81,11% | X27: CHI | Y27: 17623180 | Z27: =(AA27/Y27)-100% -> -0.10826956 | AA27: =U8 -> 15715126 | AB27: 14075478 | AC27: =AA27/AB27-100% -> 0.11648969
A28: 45835 | B28: 金 | C28: 1464520 | D28: 1054951 | E28: =C28-D28 -> 409569 | F28: -254 | G28: 0 | H28: =H27+E28+F28 -> 2773509 | J28: =D28-SUM(K28:O28) -> 1054951 | R28: Các chi phí khác chiếm 11,62% | X28: LỢI NHUẬN | Y28: 2003125 | Z28: =(AA28/Y28)-100% -> -0.38177797 | AA28: =R9 -> 1238376 | AB28: =AB26-AB27 -> 490535 | AC28: =AA28/AB28-100% -> 1.5245416
A29: 45836 | B29: 土 | C29: 708246 | D29: 1129788 | E29: =C29-D29 -> -421542 | F29: -51 | G29: 0 | H29: =H28+E29+F29 -> 2351916 | J29: =D29-SUM(K29:O29) -> 1129788 | R29: Lợi nhuận Ròng 7,27% | X29: SỐ HÓA ĐƠN | Y29: 4033 | Z29: =(AA29/Y29)-100% -> -0.06744359 | AA29: 3761 | AB29: 3412 | AC29: =AA29/AB29-100% -> 0.10228605 | AE29: NỢ DÀI HẠN
A30: 45837 | B30: 日 | C30: 586609 | D30: 637777 | E30: =C30-D30 -> -51168 | F30: 0 | G30: 0 | H30: =H29+E30+F30 -> 2300748 | J30: =D30-SUM(K30:O30) -> 626579 | L30: 11198 | X30: TB HÓA ĐƠN | Y30: =$Y$26/Y29 -> 4864.8215 | Z30: =(AA30/Y30)-100% -> -0.072321635 | AA30: =AA26/AA29 -> 4512.9896 | AB30: =AB26/AB29 -> 4269.0542 | AC30: =AA30/AB30-100% -> 0.057140387
A31: 45838 | B31: 月 | C31: 420593 | D31: 233959 | E31: =C31-D31 -> 186634 | F31: -244 | G31: 0 | H31: =H30+E31+F31 -> 2487138 | J31: =D31-SUM(K31:O31) -> 101409 | O31: 132550 | X31: TB NGÀY | Y31: =Y26/31 -> 632897.58 | Z31: =(AA31/Y31)-100% -> -0.10605051 | AA31: =AA26/30 -> 565778.47 | AB31: =AB26/30 -> 485533.77 | AC31: =AA31/AB31-100% -> 0.1652711
H32: =H31+E32+F32 -> 2487138 | J32: =D32-SUM(K32:O32) -> 0
D33: 100000 | E33: =C33-D33 -> -100000 | G33: 0 | H33: =H32+E33+F33 -> 2387138 | J33: =D33-SUM(K33:O33) -> 0 | O33: 100000
A34: TỔNG | C34: =SUM(C2:C33) -> 16973354 | D34: =SUM(D2:D33) -> 14580320 | E34: =SUM(E2:E33) -> 2393034 | F34: =SUM(F2:F33) -> -5896 | G34: =SUM(G2:G33) -> 0 | H34: =C34-D34+G34 -> 2393034 | J34: =SUM(J2:J33) -> 13766469 | K34: =SUM(K2:K33) -> 79669 | L34: =SUM(L2:L33) -> 47712 | M34: =SUM(M2:M33) -> 15569 | N34: =SUM(N2:N33) -> 239771 | O34: =SUM(O2:O33) -> 431130

Sheet 2025_7
A1: 日付 | C1: 売上 | D1: 支出 | E1: 入金 | F1: 不足 | G1: デリバリ | H1: 累計 | J1: NHẬP HÀNG | K1: XĂNG -DẦU | L1: TÚI BÓNG | M1: BĂNG DÍNH | N1: KHÁC* | O1: PHÍ CỐ ĐỊNH | Q1: BÁO CÁO THÁNG 07 /2025 | Y1: BẢNG CƠ CẤU CHI PHÍ CHI PHÍ | AF1: Bổ sung 補足
A2: 45839 | B2: 火 | C2: 690861 | D2: 464231 | E2: =C2-D2 -> 226630 | F2: -24 | G2: 0 | H2: =E2+F2 -> 226606 | J2: =D2-SUM(K2:O2) -> 438176 | O2: 26055 | Q2: THU | Y2: CHI PHÍ KINH DOANH | AB2: =AC13+Z13 -> 16198140 | AC2: =AA13+AD13 -> 0.95957083 | AF2: Bảo hiểm quán **
A3: 45840 | B3: 水 | C3: 360054 | D3: 1390381 | E3: =C3-D3 -> -1030327 | F3: -22 | G3: 0 | H3: =H2+E3+F3 -> -803743 | J3: =D3-SUM(K3:O3) -> 1379856 | K3: 7000 | M3: 3205 | N3: 320 | Q3: TỔNG DOANH THU | S3: SHIP BD | T3: SHIP | U3: Chênh lệch | V3: Thanh toán POINT | Y3: CỐ ĐỊNH | AB3: LƯU ĐỘNG
A4: 45841 | B4: 木 | C4: 600165 | D4: 365141 | E4: =C4-D4 -> 235024 | F4: 0 | G4: 0 | H4: =H3+E4+F4 -> -568719 | J4: =D4-SUM(K4:O4) -> 356232 | K4: 8909 | Q4: =C34 -> 16880609 | S4: 0 | T4: 0 | U4: =-F34 -> 3020 | V4: 26215 | Y4: TIỀN NHÀ | Z4: 132550 | AA4: =Z4/$Q$4 -> 0.0078522049 | AB4: LƯƠNG | AC4: =R8 -> 1003700 | AD4: =AC4/$Q$4 -> 0.059458755
A5: 45842 | B5: 金 | C5: 813359 | D5: 211956 | E5: =C5-D5 -> 601403 | F5: -445 | G5: 0 | H5: =H4+E5+F5 -> 32239 | J5: =D5-SUM(K5:O5) -> 194785 | L5: 10348 | N5: 6823 | S5: =S4/Q4 -> 0 | T5: =T4/Q4 -> 0 | U5: =U4/Q4 -> 0.0001789035 | V5: =V4/Q4 -> 0.0015529653 | Y5: BÃI XE | Z5: 26055 | AA5: =Z5/$Q$4 -> 0.001543487 | AB5: THƯỞNG | AC5: =SUM(Q14:W14) -> 6000 | AD5: =AC5/$Q$4 -> 0.00035543741 | AF5: Lương *
A6: 45843 | B6: 土 | C6: 728237 | D6: 722111 | E6: =C6-D6 -> 6126 | F6: -554 | G6: 0 | H6: =H5+E6+F6 -> 37811 | J6: =D6-SUM(K6:O6) -> 691364 | K6: 4545 | N6: 26202 | Q6: CHI | Y6: WIFI | Z6: 6080 | AA6: =Z6/$Q$4 -> 0.00036017658 | AB6: TIỀN ĐIỆN | AC6: 92394 | AD6: =AC6/$Q$4 -> 0.0054733807 | AF6: Anh Giang
A7: 45844 | B7: 日 | C7: 445719 | D7: 886953 | E7: =C7-D7 -> -441234 | F7: 0 | G7: 0 | H7: =H6+E7+F7 -> -403423 | J7: =D7-SUM(K7:O7) -> 866302 | K7: 8451 | N7: =700+11500 -> 12200 | Q7: NHẬP HÀNG | R7: LƯƠNG | S7: CHI KHÁC | U7: TỔNG | Y7: BẢO HIỂM | Z7: =T19 -> 46990 | AA7: =Z7/$Q$4 -> 0.0027836673 | AB7: TIỀN NƯỚC | AC7: 3396 | AD7: =AC7/$Q$4 -> 0.00020117758 | AF7: Lương CB | AG7: 300000
A8: 45845 | B8: 月 | C8: 332222 | D8: 149860 | E8: =C8-D8 -> 182362 | F8: -54 | G8: 0 | H8: =H7+E8+F8 -> -221115 | J8: =D8-SUM(K8:O8) -> 149860 | Q8: =D34 -> 14962005 | R8: =T16 -> 1003700 | S8: =V19 -> 238874 | U8: =SUM(Q8:T8) -> 16204579 | Y8: DIỆT GIÁN | Z8: 5500 | AA8: =Z8/$Q$4 -> 0.00032581763 | AB8: BĂNG DÍNH | AC8: =M34 -> 13495 | AD8: =AC8/$Q$4 -> 0.00079943798 | AF8: Ship ngoài giờ | AG8: 55000
A9: 45846 | B9: 火 | C9: 435144 | D9: 497200 | E9: =C9-D9 -> -62056 | F9: 0 | G9: 0 | H9: =H8+E9+F9 -> -283171 | J9: =D9-SUM(K9:O9) -> 495145 | N9: 2055 | Q9: LỢI NHUẬN | R9: =Q4-U8-V4-U4 -> 646795 | Y9: PHÍ LUẬT SƯ | Z9: 0 | AA9: =Z9/$Q$4 -> 0 | AB9: TÚI BÓNG | AC9: =L34 -> 45334 | AD9: =AC9/$Q$4 -> 0.0026855666 | AF9: 社会保険 | AG9: 35000
A10: 45847 | B10: 水 | C10: 213038 | D10: 369683 | E10: =C10-D10 -> -156645 | F10: -21 | G10: 0 | H10: =H9+E10+F10 -> -439837 | J10: =D10-SUM(K10:O10) -> 353990 | K10: 8461 | M10: 7232 | Q10: CHI TIẾT | Y10: THUẾ XE | Z10: 0 | AA10: =Z10/$Q$4 -> 0 | AB10: XĂNG | AC10: =K34 -> 95177 | AD10: =AC10/$Q$4 -> 0.0056382444 | AF10: Tổng | AG10: =SUM(AG7:AG9) -> 390000
A11: 45848 | B11: 木 | C11: 816908 | D11: 670479 | E11: =C11-D11 -> 146429 | F11: -24 | G11: 0 | H11: =H10+E11+F11 -> -293432 | J11: =D11-SUM(K11:O11) -> 657311 | N11: 13168 | Q11: LƯƠNG - 給与 | Y11: THUẾ | Z11: 0 | AA11: =Z11/$Q$4 -> 0 | AB11: NHẬP HÀNG | AC11: =J34 -> 13988049 | AD11: =AC11/$Q$4 -> 0.82864599 | AF11: TÀI SẢN CÔNG TY
A12: 45849 | B12: 金 | C12: 1054775 | D12: 95540 | E12: =C12-D12 -> 959235 | F12: -441 | G12: 0 | H12: =H11+E12+F12 -> 665362 | J12: =D12-SUM(K12:O12) -> 95540 | Q12: A. Giang | R12: A.Thái | S12: C.Hiền | T12: Nhàn | U12: Cưng | V12: Nghĩa | W12: Hoàn | Y12: ĐT_CCQ | Z12: 200000 | AA12: =Z12/$Q$4 -> 0.011847914 | AB12: CHI KHÁC | AC12: =N34 -> 533420 | AD12: =AC12/$Q$4 -> 0.031599571 | AF12: LỢI NHUẬN GỘP | AI12: 0
A13: 45850 | B13: 土 | C13: 1003223 | D13: 353655 | E13: =C13-D13 -> 649568 | F13: 0 | G13: 0 | H13: =H12+E13+F13 -> 1314930 | J13: =D13-SUM(K13:O13) -> 342620 | K13: 8650 | N13: 2385 | Q13: =AG10-75000 -> 315000 | R13: =52*1100 -> 57200 | S13: =28.5*1100 -> 31350 | T13: =137.5*1100 -> 151250 | U13: =87*1100 -> 95700 | V13: 160000 | W13: =102*1100 -> 112200 | Y13: TỔNG | Z13: =SUM(Z4:Z12) -> 417175 | AA13: =SUM(AA4:AA12) -> 0.024713267 | AB13: TỔNG | AC13: =SUM(AC4:AC12) -> 15780965 | AD13: =SUM(AD4:AD12) -> 0.93485756 | AF13: TIỀN MẶT | AH13: JPY | AI13: 1000000
A14: 45851 | B14: 日 | C14: 314195 | D14: 599822 | E14: =C14-D14 -> -285627 | F14: 0 | G14: 0 | H14: =H13+E14+F14 -> 1029303 | J14: =D14-SUM(K14:O14) -> 599822 | Q14: 0 | R14: 0 | S14: 0 | T14: 3000 | U14: 0 | V14: 0 | W14: 3000 | Y14: CHI PHÍ PHÁT SINH KHÁC | AB14: =Z21+AC21 -> 161119 | AC14: =AA21+AD21 -> 0.0095446201 | AH14: VND | AI14: 133394
A15: 45852 | B15: 月 | C15: 307024 | D15: 518307 | E15: =C15-D15 -> -211283 | F15: -11 | G15: 0 | H15: =H14+E15+F15 -> 818009 | J15: =D15-SUM(K15:O15) -> 510530 | K15: 7777 | Q15: =SUM(Q13:Q14) -> 315000 | R15: =SUM(R13:R14) -> 57200 | S15: =SUM(S13:S14) -> 31350 | T15: =SUM(T13:T14) -> 154250 | U15: =SUM(U13:U14) -> 95700 | V15: =SUM(V13:V14) -> 160000 | W15: =SUM(W13:W14) -> 115200 | Y15: KHẤU TRỪ | AB15: THU KHÁC | AF15: ATM | AG15: CÁ NHÂN | AI15: 33127
A16: 45853 | B16: 火 | C16: 668635 | D16: 314633 | E16: =C16-D16 -> 354002 | F16: 0 | G16: 0 | H16: =H15+E16+F16 -> 1172011 | J16: =D16-SUM(K16:O16) -> 195756 | N16: =16687+320 -> 17007 | O16: =6080+92394+3396 -> 101870 | Q16: TỔNG | T16: =SUM(R15:W15)+AG10 -> 1003700 | Y16: HỦY ĐƠN | Z16: =T23 -> 43541 | AA16: =Z16/$Q$4 -> 0.0025793501 | AB16: TT ĐIỂM | AC16: =V4 -> 26215 | AD16: =AC16/$Q$4 -> 0.0015529653 | AG16: CÔNG TY | AI16: 2200000
A17: 45854 | B17: 水 | C17: 490519 | D17: 960580 | E17: =C17-D17 -> -470061 | F17: -41 | G17: 0 | H17: =H16+E17+F17 -> 701909 | J17: =D17-SUM(K17:O17) -> 943528 | L17: 17052 | Q17: CHI KHÁC - その他 | Y17: TRẢ HÀNG | Z17: =U23 -> 22541 | AA17: =Z17/$Q$4 -> 0.0013353191 | AB17: GIẢM GIÁ HĐ | AC17: =Q23 -> 3302 | AD17: =AC17/$Q$4 -> 0.00019560906 | AF17: NỢ | AG17: KHÁCH NỢ | AI17: 812296
A18: 45855 | B18: 木 | C18: 599946 | D18: 665409 | E18: =C18-D18 -> -65463 | F18: 0 | G18: 0 | H18: =H17+E18+F18 -> 636446 | J18: =D18-SUM(K18:O18) -> 640979 | K18: 6600 | L18: 7030 | N18: 10800 | S18: Lương Ship | T18: Bảo hiểm quán ** | U18: Khác | V18: TỔNG | Y18: TRỪ SHIP | Z18: =S23 -> 12500 | AA18: =Z18/$Q$4 -> 0.00074049461 | AF18: TIỀN & CÁC KHOẢN TƯƠNG ĐƯƠNG | AI18: 70000
A19: 45856 | B19: 金 | C19: 786295 | D19: 876891 | E19: =C19-D19 -> -90596 | F19: -223 | G19: 0 | H19: =H18+E19+F19 -> 545627 | J19: =D19-SUM(K19:O19) -> 474341 | N19: 402550 | S19: =6500*9+1500 -> 60000 | T19: =39940+7050 -> 46990 | U19: =V23 -> 131884 | V19: =SUM(Q19:U19) -> 238874 | Y19: KHẤU HAO HĐ | Z19: =R23 -> 50000 | AA19: =Z19/$Q$4 -> 0.0029619784 | AF19: GIÁ TRỊ KHO ƯỚC TÍNH | AI19: 6466578
A20: 45857 | B20: 土 | C20: 707611 | D20: 623719 | E20: =C20-D20 -> 83892 | F20: -54 | G20: 0 | H20: =H19+E20+F20 -> 629465 | J20: =D20-SUM(K20:O20) -> 619875 | L20: 786 | M20: 3058 | Y20: CHÊNH LỆCH | Z20: =U4 -> 3020 | AA20: =Z20/$Q$4 -> 0.0001789035 | AF20: TÀI SẢN DÀI HẠN | AI20: 6000000
A21: 45858 | B21: 日 | C21: 416415 | D21: 204880 | E21: =C21-D21 -> 211535 | F21: 2 | G21: 0 | H21: =H20+E21+F21 -> 841002 | J21: =D21-SUM(K21:O21) -> 204880 | Q21: KHÁC | Y21: TỔNG | Z21: =SUM(Z16:Z20) -> 131602 | AA21: =SUM(AA16:AA20) -> 0.0077960457 | AB21: TỔNG | AC21: =SUM(AC16:AC20) -> 29517 | AD21: =SUM(AD16:AD20) -> 0.0017485744 | AF21: TỔNG | AI21: =SUM(AI12:AI20) -> 16715395
A22: 45859 | B22: 月 | C22: 335943 | D22: 325016 | E22: =C22-D22 -> 10927 | F22: -1 | G22: 0 | H22: =H21+E22+F22 -> 851928 | J22: =D22-SUM(K22:O22) -> 325016 | Q22: Giảm giá HD | R22: Khấu hao HĐ* | S22: TRỪ SHIP | T22: HỦY ĐƠN | U22: TRẢ HÀNG | V22: TỔNG | Y22: TỔNG CHI PHÍ | AC22: =AC14+AC2 -> 0.96911545
A23: 45860 | B23: 火 | C23: 239658 | D23: 107359 | E23: =C23-D23 -> 132299 | F23: 0 | G23: 0 | H23: =H22+E23+F23 -> 984227 | J23: =D23-SUM(K23:O23) -> 107359 | Q23: 3302 | R23: 50000 | S23: 12500 | T23: 43541 | U23: 22541 | V23: =SUM(Q23:U23) -> 131884 | AF23: NỢ + CÁC KHOẢN VAY
A24: 45861 | B24: 水 | C24: 179389 | D24: 162438 | E24: =C24-D24 -> 16951 | F24: -42 | G24: 0 | H24: =H23+E24+F24 -> 1001136 | J24: =D24-SUM(K24:O24) -> 144500 | K24: 5000 | L24: 10118 | N24: =2500+320 -> 2820 | Y24: BÁO CÁO TỔNG QUAN | AF24: NỢ NGẮN HẠN
A25: 45862 | B25: 木 | C25: 351671 | D25: 125800 | E25: =C25-D25 -> 225871 | F25: 0 | G25: 0 | H25: =H24+E25+F25 -> 1227007 | J25: =D25-SUM(K25:O25) -> 118790 | N25: =5000+2010 -> 7010 | Q25: THUYẾT MINH | Z25: THÁNG TRƯỚC | AB25: THÁNG NÀY | AC25: CÙNG KỲ
A26: 45863 | B26: 金 | C26: 1076930 | D26: 292190 | E26: =C26-D26 -> 784740 | F26: -454 | G26: 0 | H26: =H25+E26+F26 -> 2011293 | J26: =D26-SUM(K26:O26) -> 279270 | K26: 12000 | N26: 920 | R26: Giá trị kho +1,000,000 | Y26: DOANH THU | Z26: 19619825 | AA26: =(AB26/Z26)-100% -> -0.1396147 | AB26: =C34 -> 16880609 | AC26: 15215209 | AD26: =AB26/AC26-100% -> 0.10945627
A27: 45864 | B27: 土 | C27: 779548 | D27: 65056 | E27: =C27-D27 -> 714492 | F27: -14 | G27: 0 | H27: =H26+E27+F27 -> 2725771 | J27: =D27-SUM(K27:O27) -> 52272 | K27: 12784 | R27: Sale 1 tháng lợi nhuận giảm 10% | Y27: CHI | Z27: 17623180 | AA27: =(AB27/Z27)-100% -> -0.080496312 | AB27: =U8 -> 16204579 | AC27: 13784641 | AD27: =AB27/AC27-100% -> 0.17555321
A28: 45865 | B28: 日 | C28: 430246 | D28: 517311 | E28: =C28-D28 -> -87065 | F28: 0 | G28: 0 | H28: =H27+E28+F28 -> 2638706 | J28: =D28-SUM(K28:O28) -> 348856 | N28: 9850 | O28: =132550+26055 -> 158605 | R28: Tăng thêm giờ làm buổi chiều -> Lương tăng | Y28: LỢI NHUẬN | Z28: 2003125 | AA28: =(AB28/Z28)-100% -> -0.67710702 | AB28: =R9 -> 646795 | AC28: =AC26-AC27 -> 1430568 | AD28: =AB28/AC28-100% -> -0.54787539
A29: 45866 | B29: 月 | C29: 373338 | D29: 357960 | E29: =C29-D29 -> 15378 | F29: -41 | G29: 0 | H29: =H28+E29+F29 -> 2654043 | J29: =D29-SUM(K29:O29) -> 357960 | R29: Tăng thêm lương người ship | Y29: SỐ HÓA ĐƠN | Z29: 3761 | AA29: =(AB29/Z29)-100% -> 0.0521138 | AB29: 3957 | AC29: 3512 | AD29: =AB29/AC29-100% -> 0.12670843 | AF29: NỢ DÀI HẠN
A30: 45867 | B30: 火 | C30: 381779 | D30: 100523 | E30: =C30-D30 -> 281256 | F30: -11 | G30: 0 | H30: =H29+E30+F30 -> 2935288 | J30: =D30-SUM(K30:O30) -> 100523 | R30: MUA XE Ô TÔ 402.550 | Y30: TB HÓA ĐƠN | Z30: 4512.9896 | AA30: =(AB30/Z30)-100% -> -0.054725974 | AB30: =AB26/AB29 -> 4266.0119 | AC30: =AC26/AC29 -> 4332.3488 | AD30: =AB30/AC30-100% -> -0.015312
A31: 45868 | B31: 水 | C31: 326694 | D31: 980884 | E31: =C31-D31 -> -654190 | F31: 0 | G31: 0 | H31: =H30+E31+F31 -> 2281098 | J31: =D31-SUM(K31:O31) -> 980244 | N31: 640 | R31: Tiền điện >> 60.000 | Y31: TB NGÀY | Z31: =Z26/31 -> 632897.58 | AA31: =(AB31/Z31)-100% -> -0.1396147 | AB31: =AB26/31 -> 544535.77 | AC31: =AC26/31 -> 490813.19 | AD31: =AB31/AC31-100% -> 0.10945627
A32: 45869 | B32: 木 | C32: 621068 | D32: 886037 | E32: =C32-D32 -> -264969 | F32: -545 | G32: 0 | H32: =H31+E32+F32 -> 2015584 | J32: =D32-SUM(K32:O32) -> 862367 | K32: 5000 | N32: 18670 | R32: Bắt đầu đầu tư CCQ 200.000
D33: 100000 | E33: =C33-D33 -> -100000 | G33: 0 | H33: =H32+E33+F33 -> 1915584 | J33: =D33-SUM(K33:O33) -> 100000
A34: TỔNG | C34: =SUM(C2:C33) -> 16880609 | D34: =SUM(D2:D33) -> 14962005 | E34: =SUM(E2:E33) -> 1918604 | F34: =SUM(F2:F33) -> -3020 | G34: =SUM(G2:G33) -> 0 | H34: =C34-D34+G34 -> 1918604 | J34: =SUM(J2:J33) -> 13988049 | K34: =SUM(K2:K33) -> 95177 | L34: =SUM(L2:L33) -> 45334 | M34: =SUM(M2:M33) -> 13495 | N34: =SUM(N2:N33) -> 533420 | O34: =SUM(O2:O33) -> 286530

Sheet 2025_8
A1: 日付 | C1: 売上 | D1: 支出 | E1: 入金 | F1: 不足 | G1: デリバリ | H1: 累計 | J1: NHẬP HÀNG | K1: XĂNG -DẦU | L1: TÚI BÓNG | M1: BĂNG DÍNH | N1: KHÁC* | O1: PHÍ CỐ ĐỊNH | Q1: BÁO CÁO THÁNG 08 /2025 | Y1: BẢNG CƠ CẤU CHI PHÍ CHI PHÍ | AF1: Bổ sung 補足
A2: 45870 | B2: 金 | C2: 659585 | D2: 270010 | E2: =C2-D2 -> 389575 | F2: -125 | G2: 0 | H2: =E2+F2 -> 389450 | J2: =D2-SUM(K2:O2) -> 264810 | K2: 3000 | N2: 2200 | Q2: THU | Y2: CHI PHÍ KINH DOANH | AB2: =AC13+Z13 -> 16417020 | AC2: =AA13+AD13 -> 0.91297092 | AF2: Bảo hiểm quán **
A3: 45871 | B3: 土 | C3: 542376 | D3: 285368 | E3: =C3-D3 -> 257008 | F3: 0 | G3: 0 | H3: =H2+E3+F3 -> 646458 | J3: =D3-SUM(K3:O3) -> 256911 | K3: 5000 | L3: 8374 | M3: 7430 | N3: =2200+3586+1867 -> 7653 | Q3: TỔNG DOANH THU | S3: SHIP BD | T3: SHIP | U3: Chênh lệch | V3: Thanh toán POINT | Y3: CỐ ĐỊNH | AB3: LƯU ĐỘNG
A4: 45872 | B4: 日 | C4: 376904 | D4: 215460 | E4: =C4-D4 -> 161444 | F4: -22 | G4: 0 | H4: =H3+E4+F4 -> 807880 | J4: =D4-SUM(K4:O4) -> 199410 | K4: 5000 | N4: 11050 | Q4: =C34 -> 17981975 | S4: 0 | T4: 0 | U4: =-F34 -> 2738 | V4: 27723 | Y4: TIỀN NHÀ | Z4: 192550 | AA4: =Z4/$Q$4 -> 0.010707945 | AB4: LƯƠNG | AC4: =R8 -> 1060000 | AD4: =AC4/$Q$4 -> 0.058947919
A5: 45873 | B5: 月 | C5: 341439 | D5: 535586 | E5: =C5-D5 -> -194147 | F5: 0 | G5: 0 | H5: =H4+E5+F5 -> 613733 | J5: =D5-SUM(K5:O5) -> 526580 | K5: 7646 | N5: 1360 | S5: =S4/Q4 -> 0 | T5: =T4/Q4 -> 0 | U5: =U4/Q4 -> 0.00015226359 | V5: =V4/Q4 -> 0.0015417105 | Y5: BÃI XE | Z5: 26055 | AA5: =Z5/$Q$4 -> 0.001448951 | AB5: THƯỞNG | AC5: =SUM(Q14:W14) -> 69000 | AD5: =AC5/$Q$4 -> 0.0038371758 | AF5: Lương *
A6: 45874 | B6: 火 | C6: 423409 | D6: 626468 | E6: =C6-D6 -> -203059 | F6: -24 | G6: 0 | H6: =H5+E6+F6 -> 410650 | J6: =D6-SUM(K6:O6) -> 617768 | K6: 8700 | Q6: CHI | Y6: WIFI | Z6: 6080 | AA6: =Z6/$Q$4 -> 0.00033811636 | AB6: TIỀN ĐIỆN | AC6: 137812 | AD6: =AC6/$Q$4 -> 0.0076638968 | AF6: Anh Giang
A7: 45875 | B7: 水 | C7: 345131 | D7: 851130 | E7: =C7-D7 -> -505999 | F7: 0 | G7: 0 | H7: =H6+E7+F7 -> -95349 | J7: =D7-SUM(K7:O7) -> 653070 | N7: 320 | O7: 197740 | Q7: NHẬP HÀNG | R7: LƯƠNG | S7: CHI KHÁC | U7: TỔNG | Y7: BẢO HIỂM | Z7: =T19 -> 46990 | AA7: =Z7/$Q$4 -> 0.0026131724 | AB7: TIỀN NƯỚC | AC7: 3396 | AD7: =AC7/$Q$4 -> 0.00018885578 | AF7: Lương CB | AG7: 300000
A8: 45876 | B8: 木 | C8: 534975 | D8: 236934 | E8: =C8-D8 -> 298041 | F8: -24 | G8: 0 | H8: =H7+E8+F8 -> 202668 | J8: =D8-SUM(K8:O8) -> 236934 | Q8: =D34 -> 15232194 | R8: =T16 -> 1060000 | S8: =V19 -> 285572 | U8: =SUM(Q8:T8) -> 16577766 | Y8: DIỆT GIÁN | Z8: 5500 | AA8: =Z8/$Q$4 -> 0.00030586184 | AB8: BĂNG DÍNH | AC8: =M34 -> 15058 | AD8: =AC8/$Q$4 -> 0.00083739411 | AF8: Ship ngoài giờ | AG8: 55000
A9: 45877 | B9: 金 | C9: 867909 | D9: 130176 | E9: =C9-D9 -> 737733 | F9: 0 | G9: 0 | H9: =H8+E9+F9 -> 940401 | J9: =D9-SUM(K9:O9) -> 124450 | N9: 4626 | O9: 1100 | Q9: LỢI NHUẬN | R9: =Q4-U8-V4-U4 -> 1373748 | Y9: PHÍ LUẬT SƯ | Z9: 0 | AA9: =Z9/$Q$4 -> 0 | AB9: TÚI BÓNG | AC9: =L34 -> 59770 | AD9: =AC9/$Q$4 -> 0.0033238841 | AF9: 社会保険 | AG9: 35000
A10: 45878 | B10: 土 | C10: 1124670 | D10: 659210 | E10: =C10-D10 -> 465460 | F10: -241 | G10: 0 | H10: =H9+E10+F10 -> 1405620 | J10: =D10-SUM(K10:O10) -> 620875 | K10: =3000+8890 -> 11890 | L10: 19882 | N10: =320+2597+1538+128+1980 -> 6563 | Q10: CHI TIẾT | Y10: THUẾ XE | Z10: 0 | AA10: =Z10/$Q$4 -> 0 | AB10: XĂNG | AC10: =K34 -> 92812 | AD10: =AC10/$Q$4 -> 0.0051613908 | AF10: Tổng | AG10: =SUM(AG7:AG9) -> 390000
A11: 45879 | B11: 日 | C11: 210856 | D11: 242050 | E11: =C11-D11 -> -31194 | F11: -241 | G11: 0 | H11: =H10+E11+F11 -> 1374185 | J11: =D11-SUM(K11:O11) -> 242050 | Q11: LƯƠNG - 給与 | Y11: THUẾ | Z11: 0 | AA11: =Z11/$Q$4 -> 0 | AB11: NHẬP HÀNG | AC11: =J34 -> 13978777 | AD11: =AC11/$Q$4 -> 0.77737718 | AF11: TÀI SẢN CÔNG TY
A12: 45880 | B12: 月 | C12: 780746 | D12: 858968 | E12: =C12-D12 -> -78222 | F12: 0 | G12: 0 | H12: =H11+E12+F12 -> 1295963 | J12: =D12-SUM(K12:O12) -> 835700 | N12: 23268 | Q12: A. Giang | R12: A.Thái | S12: C.Hiền | T12: Nhàn | U12: Cưng | V12: Nghĩa | W12: Hoàn | Y12: ĐT_CCQ | Z12: =70000000/177 -> 395480.23 | AA12: =Z12/$Q$4 -> 0.021993147 | AB12: CHI KHÁC | AC12: =N34 -> 327740 | AD12: =AC12/$Q$4 -> 0.018226029 | AF12: LỢI NHUẬN GỘP | AI12: 0
